Workbook

Sheet Premissas
A1: Premissa | B1: Valor
A2: Crescimento mensal receita (%)
A3: Ticket médio MUVX
A4: Qtd trainers ativos
A5: Alunos por trainer
A6: % Comissão média
A7: Custos fixos mensais
A8: Despesas variáveis (% receita)
A13: Incluir projeções de vendas

Sheet DRE_Mensal
B1: TRAÇÃO | F1: ESCALA
A2: Categoria | B2: Jan/26 | C2: Feb/26 | D2: Mar/26 | E2: Apr/26 | F2: May/26 | G2: Jun/26 | H2: Jul/26 | I2: Aug/26 | J2: Sep/26 | K2: Oct/26 | L2: Nov/26 | M2: Dec/26
A3: Receita Operacional | B3: =Fluxo_Caixa_Mensal!H4 -> 0 | C3: =Fluxo_Caixa_Mensal!I4 -> 0 | D3: =Fluxo_Caixa_Mensal!J4 -> 0 | E3: =Fluxo_Caixa_Mensal!K4 -> 83839.594 | F3: =Fluxo_Caixa_Mensal!L4 -> 157390.49 | G3: =Fluxo_Caixa_Mensal!M4 -> 311990.17 | H3: =Fluxo_Caixa_Mensal!N4 -> 752576.37 | I3: =Fluxo_Caixa_Mensal!O4 -> 1662897.6 | ... M3: =Fluxo_Caixa_Mensal!S4 -> 7049208.6
A4: COGS | B4: =Fluxo_Caixa_Mensal!H76 -> 0 | C4: =Fluxo_Caixa_Mensal!I76 -> 0 | D4: =Fluxo_Caixa_Mensal!J76 -> 3300 | E4: =Fluxo_Caixa_Mensal!K76 -> 3300 | F4: =Fluxo_Caixa_Mensal!L76 -> 7826.4 | G4: =Fluxo_Caixa_Mensal!M76 -> 15052.8 | H4: =Fluxo_Caixa_Mensal!N76 -> 23042.4 | I4: =Fluxo_Caixa_Mensal!O76 -> 31272 | ... M4: =Fluxo_Caixa_Mensal!S76 -> 57874.963
A5: Resultado Bruto | B5: =B3-B4 -> 0 | C5: =C3-C4 -> 0 | D5: =D3-D4 -> -3300 | E5: =E3-E4 -> 80539.594 | F5: =F3-F4 -> 149564.09 | G5: =G3-G4 -> 296937.37 | H5: =H3-H4 -> 729533.97 | I5: =I3-I4 -> 1631625.6 | ... M5: =M3-M4 -> 6991333.7
A6: Custos Fixos | B6: =Fluxo_Caixa_Mensal!H26 -> 145929.15 | C6: =Fluxo_Caixa_Mensal!I26 -> 173607.66 | D6: =Fluxo_Caixa_Mensal!J26 -> 156816.4 | E6: =Fluxo_Caixa_Mensal!K26 -> 146809.87 | F6: =Fluxo_Caixa_Mensal!L26 -> 106584.09 | G6: =Fluxo_Caixa_Mensal!M26 -> 122702.5 | H6: =Fluxo_Caixa_Mensal!N26 -> 188251.75 | I6: =Fluxo_Caixa_Mensal!O26 -> 271393.51 | ... M6: =Fluxo_Caixa_Mensal!S26 -> 484218.94
A7: Despesas Variáveis | B7: =Fluxo_Caixa_Mensal!H86 -> 76755.16 | C7: =Fluxo_Caixa_Mensal!I86 -> 41903.51 | D7: =Fluxo_Caixa_Mensal!J86 -> 51966.51 | E7: =Fluxo_Caixa_Mensal!K86 -> 56252.17 | F7: =Fluxo_Caixa_Mensal!L86 -> 84221.646 | G7: =Fluxo_Caixa_Mensal!M86 -> 123155.67 | H7: =Fluxo_Caixa_Mensal!N86 -> 371408.01 | I7: =Fluxo_Caixa_Mensal!O86 -> 463246.73 | ... M7: =Fluxo_Caixa_Mensal!S86 -> 904607.97
A8: Resultado Operacional | B8: =B5-B6-B7 -> -222684.31 | C8: =C5-C6-C7 -> -215511.17 | D8: =D5-D6-D7 -> -212082.91 | E8: =E5-E6-E7 -> -122522.45 | F8: =F5-F6-F7 -> -41241.65 | G8: =G5-G6-G7 -> 51079.2 | H8: =H5-H6-H7 -> 169874.21 | I8: =I5-I6-I7 -> 896985.32 | ... M8: =M5-M6-M7 -> 5602506.8
A9: Depreciação | B9: 0 | C9: 0 | D9: 0 | E9: 0 | F9: 0 | G9: 0 | H9: 0 | I9: 0 | J9: 0 | K9: 0 | L9: 0 | M9: 0
A10: Amortização | B10: 0 | C10: 0 | D10: 0 | E10: 0 | F10: 0 | G10: 0 | H10: 0 | I10: 0 | J10: 0 | K10: 0 | L10: 0 | M10: 0
A11: EBITDA | B11: =B8-B9-B10 -> -222684.31 | C11: =C8-C9-C10 -> -215511.17 | D11: =D8-D9-D10 -> -212082.91 | E11: =E8-E9-E10 -> -122522.45 | F11: =F8-F9-F10 -> -41241.65 | G11: =G8-G9-G10 -> 51079.2 | H11: =H8-H9-H10 -> 169874.21 | I11: =I8-I9-I10 -> 896985.32 | ... M11: =M8-M9-M10 -> 5602506.8
A12: Margem Bruta | B12: =IFERROR(B5/B3,0) -> 0 | C12: =IFERROR(C5/C3,0) -> 0 | D12: =IFERROR(D5/D3,0) -> 0 | E12: =IFERROR(E5/E3,0) -> 0.96063912 | F12: =IFERROR(F5/F3,0) -> 0.950274 | G12: =IFERROR(G5/G3,0) -> 0.95175233 | H12: =IFERROR(H5/H3,0) -> 0.96938198 | I12: =IFERROR(I5/I3,0) -> 0.98119427 | ... M12: =IFERROR(M5/M3,0) -> 0.99178986
A13: Margem Operacional | B13: =IFERROR(B8/B3,0) -> 0 | C13: =IFERROR(C8/C3,0) -> 0 | D13: =IFERROR(D8/D3,0) -> 0 | E13: =IFERROR(E8/E3,0) -> -1.4613912 | F13: =IFERROR(F8/F3,0) -> -0.26203395 | G13: =IFERROR(G8/G3,0) -> 0.16372054 | H13: =IFERROR(H8/H3,0) -> 0.22572355 | I13: =IFERROR(I8/I3,0) -> 0.53941105 | ... M13: =IFERROR(M8/M3,0) -> 0.79477102
A14: Margem EBITDA | B14: =IFERROR(B11/B3,0) -> 0 | C14: =IFERROR(C11/C3,0) -> 0 | D14: =IFERROR(D11/D3,0) -> 0 | E14: =IFERROR(E11/E3,0) -> -1.4613912 | F14: =IFERROR(F11/F3,0) -> -0.26203395 | G14: =IFERROR(G11/G3,0) -> 0.16372054 | H14: =IFERROR(H11/H3,0) -> 0.22572355 | I14: =IFERROR(I11/I3,0) -> 0.53941105 | ... M14: =IFERROR(M11/M3,0) -> 0.79477102
A15: Burn Rate (Operacional) | B15: =Fluxo_Caixa_Mensal!H25-Fluxo_Caixa_Mensal!H4 -> 222684.31 | C15: =Fluxo_Caixa_Mensal!I25-Fluxo_Caixa_Mensal!I4 -> 215511.17 | D15: =Fluxo_Caixa_Mensal!J25-Fluxo_Caixa_Mensal!J4 -> 212082.91 | E15: =Fluxo_Caixa_Mensal!K25-Fluxo_Caixa_Mensal!K4 -> 122522.45 | F15: =Fluxo_Caixa_Mensal!L25-Fluxo_Caixa_Mensal!L4 -> 46272.026 | G15: =Fluxo_Caixa_Mensal!M25-Fluxo_Caixa_Mensal!M4 -> -41635.771 | H15: =Fluxo_Caixa_Mensal!N25-Fluxo_Caixa_Mensal!N4 -> -151154.8 | I15: =Fluxo_Caixa_Mensal!O25-Fluxo_Caixa_Mensal!O4 -> -851830.74 | ... M15: =Fluxo_Caixa_Mensal!S25-Fluxo_Caixa_Mensal!S4 -> -5266556.2
A16: Runway (Médio) | B16: =Fluxo_Caixa_Mensal!H167/(AVERAGE(DRE_Mensal!$B$15:$F$15)) -> 0.015190651 | C16: =Fluxo_Caixa_Mensal!I167/(AVERAGE(DRE_Mensal!$B$15:$F$15)) -> -0.030135475 | D16: =Fluxo_Caixa_Mensal!J167/(AVERAGE(DRE_Mensal!$B$15:$F$15)) -> 0.018854794 | E16: =Fluxo_Caixa_Mensal!K167/(AVERAGE(DRE_Mensal!$B$15:$F$15)) -> -0.20714736 | F16: =Fluxo_Caixa_Mensal!L167/(AVERAGE(DRE_Mensal!$B$15:$F$15)) -> -0.30835964 | G16: N/A | H16: N/A | I16: N/A | J16: N/A | K16: N/A | L16: N/A | M16: N/A
A17: Runway (Mensal) | B17: =Fluxo_Caixa_Mensal!H167/DRE_Mensal!B15 -> 0.011174788 | C17: =Fluxo_Caixa_Mensal!I167/DRE_Mensal!C15 -> -0.022906609 | D17: =Fluxo_Caixa_Mensal!J167/DRE_Mensal!D15 -> 0.014563597 | E17: =Fluxo_Caixa_Mensal!K167/DRE_Mensal!E15 -> -0.2769595 | F17: =Fluxo_Caixa_Mensal!L167/DRE_Mensal!F15 -> -1.0916704 | G17: N/A | H17: N/A | I17: N/A | J17: N/A | K17: N/A | L17: N/A | M17: N/A
A18: Tx Crescimento | E18: =E11/F11 -> 2.9708425 | F18: =F11/G11 -> -0.80740595 | G18: =G11/H11 -> 0.30068838 | H18: =H11/I11 -> 0.18938349 | I18: =I11/J11 -> 0.46450903 | J18: =J11/K11 -> 0.64610633 | K18: =K11/L11 -> 0.6861819 | L18: =L11/M11 -> 0.77743758

Sheet Fluxo_Caixa_Mensal
B1: PROJETO | F1: GO-LIVE E HYPERCARE | H1: TRAÇÃO | L1: PRÉ-ESCALA
A2: Categoria | B2: 45839 | C2: 45870 | D2: 45901 | E2: 45931 | F2: 45962 | G2: 45992 | H2: 46023 | I2: 46054 | J2: 46082 | K2: 46113 | L2: 46143 | M2: 46174 | N2: 46204 | O2: 46235 | P2: 46266 | Q2: 46296 | R2: 46327 | S2: 46357 | T2: Total Anual (2026)
A3: Valuation Estimado (ARR-Based) | B3: =C5*4 -> 0 | C3: =D5*4 -> 0 | D3: =E5*4 -> 0 | E3: =F5*4 -> 0 | F3: =G5*4 -> 0 | G3: =H5*4 -> 0 | H3: =(I5*12)*4 -> 0 | I3: =(J5*12)*4 -> 0 | J3: =(K5*12)*4 -> 4024300.5 | K3: =(L5*12)*4 -> 7554743.3 | L3: =(M5*12)*4 -> 14975528 | M3: =(N5*12)*4 -> 36123666 | N3: =(O5*12)*4 -> 79819083 | O3: =(P5*12)*4 -> 1.3526606e+08 | ... R3: =(S5*12)*4 -> 3.3836201e+08
A4: Entradas Operacionais | B4: =B5+B20 -> 0 | C4: =C5+C20 -> 0 | D4: =D5+D20 -> 0 | E4: =E5+E20 -> 0 | F4: =F5+F20 -> 0 | G4: =G5+G20 -> 0 | H4: =H5+H20 -> 0 | I4: =I5+I20 -> 0 | ... S4: =S5+S20 -> 7049208.6 | T4: =SUM(H4:S4) -> 22497351
A5: Receita Recorrente / Transacional | B5: =SUM(B6:B19) -> 0 | C5: =SUM(C6:C19) -> 0 | D5: =SUM(D6:D19) -> 0 | E5: =SUM(E6:E19) -> 0 | F5: =SUM(F6:F19) -> 0 | G5: =SUM(G6:G19) -> 0 | H5: =SUM(H6:H19) -> 0 | I5: =SUM(I6:I19) -> 0 | ... S5: =SUM(S6:S19) -> 7049208.6 | T5: =SUM(H5:S5) -> 22497351
A6: Receita MUVX % - Estimado | B6: 0 | C6: 0 | D6: 0 | E6: 0 | F6: 0 | G6: 0 | H6: 0 | I6: 0 | K6: {=INDEX('Proj. Vendas MUVX Core New'!$AD$66:$AD$76, COLUMN(K6)-COLUMN($J$6)+1)} -> 14932.917 | L6: {=INDEX('Proj. Vendas MUVX Core New'!$AD$66:$AD$76, COLUMN(L6)-COLUMN($J$6)+1)} -> 16062.562 | M6: {=INDEX('Proj. Vendas MUVX Core New'!$AD$66:$AD$76, COLUMN(M6)-COLUMN($J$6)+1)} -> 21040.331 | N6: {=INDEX('Proj. Vendas MUVX Core New'!$AD$66:$AD$76, COLUMN(N6)-COLUMN($J$6)+1)} -> 64678.342 | O6: {=INDEX('Proj. Vendas MUVX Core New'!$AD$66:$AD$76, COLUMN(O6)-COLUMN($J$6)+1)} -> 215065.82 | P6: {=INDEX('Proj. Vendas MUVX Core New'!$AD$66:$AD$76, COLUMN(P6)-COLUMN($J$6)+1)} -> 368901.16 | Q6: {=INDEX('Proj. Vendas MUVX Core New'!$AD$66:$AD$76, COLUMN(Q6)-COLUMN($J$6)+1)} -> 528847.3 | R6: {=INDEX('Proj. Vendas MUVX Core New'!$AD$66:$AD$76, COLUMN(R6)-COLUMN($J$6)+1)} -> 689647.23 | S6: {=INDEX('Proj. Vendas MUVX Core New'!$AD$66:$AD$76, COLUMN(S6)-COLUMN($J$6)+1)} -> 867828.03 | T6: =SUM(H6:S6) -> 2787003.7
A7: Receita MUVX % - Realizado | B7: 0 | C7: 0 | D7: 0 | E7: 0 | F7: 0 | G7: 0 | H7: 0 | I7: 0 | K7: 0 | L7: 0 | M7: 0 | N7: 0 | O7: 0 | P7: 0 | Q7: 0 | R7: 0 | S7: 0 | T7: =SUM(H7:S7) -> 0
A8: Receita MUVX Premium - Estimado | B8: 0 | C8: 0 | D8: 0 | E8: 0 | F8: 0 | G8: 0 | H8: 0 | I8: 0 | K8: {=INDEX('Proj. Vendas MUVX Core New'!$AE$66:$AE$77, COLUMN(K8)-COLUMN($J$8)+1)} -> 9414.1024 | L8: {=INDEX('Proj. Vendas MUVX Core New'!$AE$66:$AE$77, COLUMN(L8)-COLUMN($J$8)+1)} -> 11796.707 | M8: {=INDEX('Proj. Vendas MUVX Core New'!$AE$66:$AE$77, COLUMN(M8)-COLUMN($J$8)+1)} -> 33240.877 | N8: {=INDEX('Proj. Vendas MUVX Core New'!$AE$66:$AE$77, COLUMN(N8)-COLUMN($J$8)+1)} -> 106216.9 | O8: {=INDEX('Proj. Vendas MUVX Core New'!$AE$66:$AE$77, COLUMN(O8)-COLUMN($J$8)+1)} -> 178663.47 | P8: {=INDEX('Proj. Vendas MUVX Core New'!$AE$66:$AE$77, COLUMN(P8)-COLUMN($J$8)+1)} -> 251841.82 | Q8: {=INDEX('Proj. Vendas MUVX Core New'!$AE$66:$AE$77, COLUMN(Q8)-COLUMN($J$8)+1)} -> 323204.77 | R8: {=INDEX('Proj. Vendas MUVX Core New'!$AE$66:$AE$77, COLUMN(R8)-COLUMN($J$8)+1)} -> 400423.52 | S8: {=INDEX('Proj. Vendas MUVX Core New'!$AE$66:$AE$77, COLUMN(S8)-COLUMN($J$8)+1)} -> 471771.47 | T8: =SUM(H8:S8) -> 1786573.6
A9: Receita MUVX Premium - Realizado | B9: 0 | C9: 0 | D9: 0 | E9: 0 | F9: 0 | G9: 0 | H9: 0 | I9: 0 | K9: 0 | L9: 0 | M9: 0 | N9: 0 | O9: 0 | P9: 0 | Q9: 0 | R9: 0 | S9: 0 | T9: =SUM(H9:S9) -> 0
A10: Receita MUVX (Alunos) Fee - Estimado | B10: 0 | C10: 0 | D10: 0 | E10: 0 | F10: 0 | G10: 0 | H10: 0 | I10: 0 | K10: {=INDEX('Proj. Vendas MUVX Core New'!$AF$66:$AF$77, COLUMN(K10)-COLUMN($J$10)+1)} -> 4554.33 | L10: {=INDEX('Proj. Vendas MUVX Core New'!$AF$66:$AF$77, COLUMN(L10)-COLUMN($J$10)+1)} -> 5305.2455 | M10: {=INDEX('Proj. Vendas MUVX Core New'!$AF$66:$AF$77, COLUMN(M10)-COLUMN($J$10)+1)} -> 12031.322 | N10: {=INDEX('Proj. Vendas MUVX Core New'!$AF$66:$AF$77, COLUMN(N10)-COLUMN($J$10)+1)} -> 35063.269 | O10: {=INDEX('Proj. Vendas MUVX Core New'!$AF$66:$AF$77, COLUMN(O10)-COLUMN($J$10)+1)} -> 57895.956 | P10: {=INDEX('Proj. Vendas MUVX Core New'!$AF$66:$AF$77, COLUMN(P10)-COLUMN($J$10)+1)} -> 80959.276 | Q10: {=INDEX('Proj. Vendas MUVX Core New'!$AF$66:$AF$77, COLUMN(Q10)-COLUMN($J$10)+1)} -> 103434.25 | R10: {=INDEX('Proj. Vendas MUVX Core New'!$AF$66:$AF$77, COLUMN(R10)-COLUMN($J$10)+1)} -> 127787.16 | S10: {=INDEX('Proj. Vendas MUVX Core New'!$AF$66:$AF$77, COLUMN(S10)-COLUMN($J$10)+1)} -> 150257.4 | T10: =SUM(H10:S10) -> 577288.2
A11: Receita MUVX (Alunos) Fee - Realizado | B11: 0 | C11: 0 | D11: 0 | E11: 0 | F11: 0 | G11: 0 | H11: 0 | I11: 0 | K11: 0 | L11: 0 | M11: 0 | N11: 0 | O11: 0 | P11: 0 | Q11: 0 | R11: 0 | S11: 0 | T11: =SUM(H11:S11) -> 0
A12: Receita Embaixadores - Estimado | B12: 0 | C12: 0 | D12: 0 | E12: 0 | F12: 0 | G12: 0 | H12: 0 | I12: 0 | K12: 16537.5 | L12: 17364.375 | M12: 18232.594 | N12: 19144.223 | O12: 20101.435 | P12: 21106.506 | Q12: 22161.832 | R12: 23269.923 | S12: 24433.419 | T12: =SUM(H12:S12) -> 182351.81
A13: Receita Embaixadores - Realizado | B13: 0 | C13: 0 | D13: 0 | E13: 0 | F13: 0 | G13: 0 | H13: 0 | I13: 0 | K13: 0 | L13: 0 | M13: 0 | N13: 0 | O13: 0 | P13: 0 | Q13: 0 | R13: 0 | S13: 0 | T13: =SUM(H13:S13) -> 0
A14: Receita Influencer - Estimado | B14: 0 | C14: 0 | D14: 0 | E14: 0 | F14: 0 | G14: 0 | H14: 0 | I14: 0 | K14: {=INDEX('Proj. Vendas Influencia Faixa'!$H$47:$H$58, COLUMN(K14)-COLUMN($J$14)+1)} -> 18105.6 | L14: {=INDEX('Proj. Vendas Influencia Faixa'!$H$47:$H$58, COLUMN(L14)-COLUMN($J$14)+1)} -> 36211.2 | M14: {=INDEX('Proj. Vendas Influencia Faixa'!$H$47:$H$58, COLUMN(M14)-COLUMN($J$14)+1)} -> 63369.6 | N14: {=INDEX('Proj. Vendas Influencia Faixa'!$H$47:$H$58, COLUMN(N14)-COLUMN($J$14)+1)} -> 90528 | O14: {=INDEX('Proj. Vendas Influencia Faixa'!$H$47:$H$58, COLUMN(O14)-COLUMN($J$14)+1)} -> 117686.4 | P14: {=INDEX('Proj. Vendas Influencia Faixa'!$H$47:$H$58, COLUMN(P14)-COLUMN($J$14)+1)} -> 145750.08 | Q14: {=INDEX('Proj. Vendas Influencia Faixa'!$H$47:$H$58, COLUMN(Q14)-COLUMN($J$14)+1)} -> 152793.16 | R14: {=INDEX('Proj. Vendas Influencia Faixa'!$H$47:$H$58, COLUMN(R14)-COLUMN($J$14)+1)} -> 159836.24 | S14: {=INDEX('Proj. Vendas Influencia Faixa'!$H$47:$H$58, COLUMN(S14)-COLUMN($J$14)+1)} -> 166879.32 | T14: =SUM(H14:S14) -> 951159.59
A15: Receita Influencer - Realizado | B15: 0 | C15: 0 | D15: 0 | E15: 0 | F15: 0 | G15: 0 | H15: 0 | I15: 0 | K15: 0 | L15: 0 | M15: 0 | N15: 0 | O15: 0 | P15: 0 | Q15: 0 | R15: 0 | S15: 0 | T15: =SUM(H15:S15) -> 0
A16: Receita MUVX Digital % - Estimado | B16: 0 | C16: 0 | D16: 0 | E16: 0 | F16: 0 | G16: 0 | H16: 0 | I16: 0 | K16: {=INDEX('Proj. Vendas MUVX Digital'!$X$65:$X$73, COLUMN(K16)-COLUMN($K$16)+1)} -> 7161.7101 | L16: {=INDEX('Proj. Vendas MUVX Digital'!$X$65:$X$73, COLUMN(L16)-COLUMN($K$16)+1)} -> 17524.204 | M16: {=INDEX('Proj. Vendas MUVX Digital'!$X$65:$X$73, COLUMN(M16)-COLUMN($K$16)+1)} -> 71950.648 | N16: {=INDEX('Proj. Vendas MUVX Digital'!$X$65:$X$73, COLUMN(N16)-COLUMN($K$16)+1)} -> 126639.33 | O16: {=INDEX('Proj. Vendas MUVX Digital'!$X$65:$X$73, COLUMN(O16)-COLUMN($K$16)+1)} -> 432960.92 | P16: {=INDEX('Proj. Vendas MUVX Digital'!$X$65:$X$73, COLUMN(P16)-COLUMN($K$16)+1)} -> 907108.54 | Q16: {=INDEX('Proj. Vendas MUVX Digital'!$X$65:$X$73, COLUMN(Q16)-COLUMN($K$16)+1)} -> 1498353.9 | R16: {=INDEX('Proj. Vendas MUVX Digital'!$X$65:$X$73, COLUMN(R16)-COLUMN($K$16)+1)} -> 2091384.1 | S16: {=INDEX('Proj. Vendas MUVX Digital'!$X$65:$X$73, COLUMN(S16)-COLUMN($K$16)+1)} -> 3119976.9 | T16: =SUM(H16:S16) -> 8273060.3
A17: Receita MUVX Digital % - Realizado | B17: 0 | C17: 0 | D17: 0 | E17: 0 | F17: 0 | G17: 0 | H17: 0 | I17: 0 | J17: 0 | K17: 0 | L17: 0 | M17: 0 | N17: 0 | O17: 0 | P17: 0 | Q17: 0 | R17: 0 | S17: 0 | T17: =SUM(H17:S17) -> 0
A18: Receita MUVX Digital (Alunos) Fee - Estimado | B18: 0 | C18: 0 | D18: 0 | E18: 0 | F18: 0 | G18: 0 | H18: 0 | I18: 0 | J18: 0 | K18: {=INDEX('Proj. Vendas MUVX Digital'!$Y$65:$Y$73, COLUMN(Y16)-COLUMN($Y$16)+1)} -> 13133.435 | L18: {=INDEX('Proj. Vendas MUVX Digital'!$Y$65:$Y$73, COLUMN(Z16)-COLUMN($Y$16)+1)} -> 53126.193 | M18: {=INDEX('Proj. Vendas MUVX Digital'!$Y$65:$Y$73, COLUMN(AA16)-COLUMN($Y$16)+1)} -> 92124.798 | N18: {=INDEX('Proj. Vendas MUVX Digital'!$Y$65:$Y$73, COLUMN(AB16)-COLUMN($Y$16)+1)} -> 310306.3 | O18: {=INDEX('Proj. Vendas MUVX Digital'!$Y$65:$Y$73, COLUMN(AC16)-COLUMN($Y$16)+1)} -> 640523.57 | P18: {=INDEX('Proj. Vendas MUVX Digital'!$Y$65:$Y$73, COLUMN(AD16)-COLUMN($Y$16)+1)} -> 1042375.6 | Q18: {=INDEX('Proj. Vendas MUVX Digital'!$Y$65:$Y$73, COLUMN(AE16)-COLUMN($Y$16)+1)} -> 1433433.6 | R18: {=INDEX('Proj. Vendas MUVX Digital'!$Y$65:$Y$73, COLUMN(AF16)-COLUMN($Y$16)+1)} -> 2106828.2 | S18: {=INDEX('Proj. Vendas MUVX Digital'!$Y$65:$Y$73, COLUMN(AG16)-COLUMN($Y$16)+1)} -> 2248062.1 | T18: =SUM(H18:S18) -> 7939913.7
A19: Receita MUVX Digital (Alunos) Fee - Realizado | B19: 0 | C19: 0 | D19: 0 | E19: 0 | F19: 0 | G19: 0 | H19: 0 | I19: 0 | J19: 0 | K19: 0 | L19: 0 | M19: 0 | N19: 0 | O19: 0 | P19: 0 | Q19: 0 | R19: 0 | S19: 0 | T19: =SUM(H19:S19) -> 0
A20: Receita Não Recorrente | B20: =SUM(B21:B24) -> 0 | C20: =SUM(C21:C24) -> 0 | D20: =SUM(D21:D24) -> 0 | E20: =SUM(E21:E24) -> 0 | F20: =SUM(F21:F24) -> 0 | G20: =SUM(G21:G24) -> 0 | H20: =SUM(H21:H24) -> 0 | I20: =SUM(I21:I24) -> 0 | ... S20: =SUM(S21:S24) -> 0 | T20: =SUM(H20:S20) -> 0
A21: Patrocínio Eventos - Estimado | B21: 0 | C21: 0 | D21: 0 | E21: 0 | F21: 0 | G21: 0 | H21: 0 | I21: 0 | J21: 0 | K21: 0 | L21: 0 | M21: 0 | N21: 0 | O21: 0 | P21: 0 | Q21: 0 | R21: 0 | S21: 0 | T21: =SUM(H21:S21) -> 0
A22: Patrocínio Eventos - Realizado | B22: 0 | C22: 0 | D22: 0 | E22: 0 | F22: 0 | G22: 0 | H22: 0 | I22: 0 | J22: 0 | K22: 0 | L22: 0 | M22: 0 | N22: 0 | O22: 0 | P22: 0 | Q22: 0 | R22: 0 | S22: 0 | T22: =SUM(H22:S22) -> 0
A23: Receita Eventos - Estimado | B23: 0 | C23: 0 | D23: 0 | E23: 0 | F23: 0 | G23: 0 | H23: 0 | I23: 0 | J23: 0 | K23: 0 | L23: 0 | M23: 0 | N23: 0 | O23: 0 | P23: 0 | Q23: 0 | R23: 0 | S23: 0 | T23: =SUM(H23:S23) -> 0
A24: Receita Eventos - Realizado | B24: 0 | C24: 0 | D24: 0 | E24: 0 | F24: 0 | G24: 0 | H24: 0 | I24: 0 | J24: 0 | K24: 0 | L24: 0 | M24: 0 | N24: 0 | O24: 0 | P24: 0 | Q24: 0 | R24: 0 | S24: 0 | T24: =SUM(H24:S24) -> 0
A25: Saídas Operacionais | B25: =B26+B76+B86+B142 -> 0 | C25: =C26+C76+C86+C142 -> 3887.33 | D25: =D26+D76+D86+D142 -> 73368.93 | E25: =E26+E76+E86+E142 -> 165876.82 | F25: =F26+F76+F86+F142 -> 217155.82 | G25: =G26+G76+G86+G142 -> 211330.67 | H25: =H26+H76+H86+H142 -> 222684.31 | I25: =I26+I76+I86+I142 -> 215511.17 | ... S25: =S26+S76+S86+S142 -> 1782652.5 | T25: =SUM(H25:S25) -> 8242464.2
A26: Custos Fixos Operacionais | B26: =B27+B34+B37+B68 -> 0 | C26: =C27+C34+C37+C68 -> 3637.33 | D26: =D27+D34+D37+D68 -> 71613.93 | E26: =E27+E34+E37+E68 -> 111603.38 | F26: =F27+F34+F37+F68 -> 136259.63 | G26: =G27+G34+G37+G68 -> 156573.31 | H26: =H27+H34+H37+H68 -> 145929.15 | I26: =I27+I34+I37+I68 -> 173607.66 | ... S26: =S27+S34+S37+S68 -> 484218.94 | T26: =SUM(H26:S26) -> 2892038
A27: Custos com pessoal | B27: =SUM(B28:B33) -> 0 | C27: =SUM(C28:C33) -> 0 | D27: =SUM(D28:D33) -> 66667.12 | E27: =SUM(E28:E33) -> 82399.38 | F27: =SUM(F28:F33) -> 105680.58 | G27: =SUM(G28:G33) -> 109604.61 | H27: =SUM(H28:H33) -> 111812.77 | I27: =SUM(I28:I33) -> 141622.32 | ... S27: =SUM(S28:S33) -> 399911.28 | T27: =SUM(H27:S27) -> 2251114.3
A28: Gympass/Wellhub | E28: 1447.9 | G28: 3061 | I28: 1326.44 | J28: 1224.41 | K28: 1000 | L28: =K28*1.1 -> 1100 | M28: =L28*1.2 -> 1320 | N28: =M28*1.2 -> 1584 | O28: =N28*1.3 -> 2059.2 | P28: =O28*1.3 -> 2676.96 | Q28: =P28*1.3 -> 3480.048 | R28: =Q28*1.3 -> 4524.0624 | S28: =R28*1.3 -> 5881.2811 | T28: =SUM(H28:S28) -> 26176.402
A29: Salários | B29: 0 | C29: 0 | D29: 66667.12 | E29: 80951.48 | F29: 101227.58 | G29: 106458.61 | H29: 111812.77 | I29: 140295.88 | J29: 135000 | K29: 115000 | L29: 90000 | M29: =L29*1.1 -> 99000 | N29: =M29*1.1 -> 108900 | O29: =N29*1.2 -> 130680 | P29: =O29*1.2 -> 156816 | Q29: =P29*1.2 -> 188179.2 | R29: =Q29*1.25 -> 235224 | S29: =R29*1.25 -> 294030 | T29: =SUM(H29:S29) -> 1804937.9
A30: Salário CEO | O30: 60000 | P30: 60000 | Q30: 100000 | R30: 100000 | S30: 100000 | T30: =SUM(H30:S30) -> 420000
A31: Gerar (estágio) | F31: 85 | G31: 85 | T31: =SUM(H31:S31) -> 0
A32: Férias | T32: =SUM(H32:S32) -> 0
A33: Ajuda de Custo Presencial | F33: 4368 | T33: =SUM(H33:S33) -> 0
A34: Infraestrutura | B34: =SUM(B35:B36) -> 0 | C34: =SUM(C35:C36) -> 0 | D34: =SUM(D35:D36) -> 0 | E34: =SUM(E35:E36) -> 4360 | F34: =SUM(F35:F36) -> 0 | G34: =SUM(G35:G36) -> 14560 | H34: =SUM(H35:H36) -> 0 | I34: =SUM(I35:I36) -> 0 | ... S34: =SUM(S35:S36) -> 45000 | T34: =SUM(H34:S34) -> 284560
A35: Escritorio | E35: 4360 | G35: 14560 | K35: =14560 -> 14560 | N35: 20000 | O35: 20000 | P35: 20000 | Q35: 20000 | R35: 20000 | S35: 20000 | T35: =SUM(H35:S35) -> 134560
A36: Base Executiva SP | N36: 25000 | O36: 25000 | P36: 25000 | Q36: 25000 | R36: 25000 | S36: 25000 | T36: =SUM(H36:S36) -> 150000
A37: Software + Equipamentos | B37: =SUM(B38:B67) -> 0 | C37: =SUM(C38:C67) -> 440.33 | D37: =SUM(D38:D67) -> 1145.94 | E37: =SUM(E38:E67) -> 8692.72 | F37: =SUM(F38:F67) -> 8355.65 | G37: =SUM(G38:G67) -> 10249.7 | H37: =SUM(H38:H67) -> 17704.38 | I37: =SUM(I38:I67) -> 15170.34 | ... S37: =SUM(S38:S67) -> 21592.664 | T37: =SUM(H37:S37) -> 185986.72
A38: Office365 | D38: 560 | E38: 1869.32 | F38: 0 | G38: 4171.2 | H38: 2980.32 | I38: =2921.48+48.08 -> 2969.56 | J38: =2921.48 -> 2921.48 | K38: 1962.45 | L38: 600 | M38: =L38*1.2 -> 720 | N38: =M38*1.2 -> 864 | O38: =N38*1.3 -> 1123.2 | P38: =O38*1.3 -> 1460.16 | Q38: =P38*1.3 -> 1898.208 | R38: =Q38*1.3 -> 2467.6704 | S38: =R38*1.3 -> 3207.9715 | T38: =SUM(H38:S38) -> 23175.02
A39: Equipamentos | E39: 273.95 | F39: 273.95 | G39: 954.34 | H39: 2135.76 | I39: 273.95 | J39: 273.95 | K39: 273.95 | L39: 273.95 | M39: 273.95 | T39: =SUM(H39:S39) -> 3505.51
A40: Equipamentos - Transferência de Ativos | I40: =383.33+283.42+287.59+633.52 -> 1587.86 | J40: 670.92 | K40: 670.92 | L40: 287.59 | T40: =SUM(H40:S40) -> 3217.29
A41: Atlassian | C41: 0 | D41: 0 | E41: 0 | F41: 0 | G41: 1037.89 | H41: 958.39 | I41: =390.9+1275.47 -> 1666.37 | J41: =541.02+653.09 -> 1194.11 | K41: 0 | L41: 0 | M41: 0 | N41: 0 | O41: 0 | P41: 0 | Q41: 0 | R41: 0 | S41: 0 | T41: =SUM(H41:S41) -> 3818.87
A42: Bitbucket | C42: 175.07 | D42: 175.07 | E42: 217.24 | F42: 468.48 | I42: 468.48 | K42: 217.24 | L42: 217.24 | M42: 217.24 | N42: 217.24 | O42: 217.24 | P42: 217.24 | Q42: 217.24 | R42: 217.24 | S42: 217.24 | T42: =SUM(H42:S42) -> 2423.64
A43: Figma | C43: 265.26 | D43: 265.26 | E43: 636.86 | F43: 919 | H43: 962.78 | I43: 1039.22 | J43: 1172.66 | K43: 919 | L43: 919 | M43: 919 | N43: 919 | O43: 919 | P43: 919 | Q43: 919 | R43: 919 | S43: 919 | T43: =SUM(H43:S43) -> 11445.66
A44: Sendmail | C44: 0 | D44: 0 | E44: 636.13 | F44: 187.45 | H44: 209.05 | I44: 199.5 | J44: 194.25 | K44: 636.13 | L44: 636.13 | M44: 636.13 | N44: 636.13 | O44: 636.13 | P44: 636.13 | Q44: 636.13 | R44: 636.13 | S44: 636.13 | T44: =SUM(H44:S44) -> 6327.97
A45: Adobe | C45: 0 | D45: 0 | E45: 280 | F45: 280 | G45: 280 | H45: 280 | I45: =118+162 -> 280 | J45: =118+162 -> 280 | K45: 280 | L45: 280 | M45: 280 | N45: 280 | O45: 280 | P45: 280 | Q45: 280 | R45: 280 | S45: 280 | T45: =SUM(H45:S45) -> 3360
A46: Zendesk | C46: 0 | D46: 0 | E46: 0 | F46: 0 | G46: 0 | H46: 297.89 | I46: 274.97 | J46: 268.75 | K46: 0 | L46: 900 | M46: 900 | N46: 900 | O46: 900 | P46: 900 | Q46: 900 | R46: 900 | S46: 900 | T46: =SUM(H46:S46) -> 8041.61
A47: Active Campaing | C47: 0 | D47: 0 | E47: 0 | F47: 1054.8 | H47: 4452.62 | I47: 564.6 | J47: 194.24 | Q47: 0 | R47: 0 | S47: 0 | T47: =SUM(H47:S47) -> 5211.46
A48: Asana | C48: 0 | D48: 0 | E48: 1499.91 | F48: 1202.35 | G48: 1203.77 | H48: 1208.42 | I48: =1167.33 -> 1167.33 | J48: =1165.19 -> 1165.19 | K48: 400 | L48: =K48*1.2 -> 480 | M48: =L48*1.2 -> 576 | N48: =M48*1.2 -> 691.2 | O48: =N48*1.3 -> 898.56 | P48: =O48*1.3 -> 1168.128 | Q48: =P48*1.3 -> 1518.5664 | R48: =Q48*1.3 -> 1974.1363 | S48: =R48*1.3 -> 2566.3772 | T48: =SUM(H48:S48) -> 13813.908
A49: Canva | C49: 0 | D49: 0 | E49: 34.9 | F49: 34.9 | G49: 34.9 | H49: 34.9 | I49: 34.9 | J49: 34.9 | K49: 34.9 | L49: 34.9 | M49: 34.9 | N49: 34.9 | O49: 34.9 | P49: 34.9 | Q49: 34.9 | R49: 34.9 | S49: 34.9 | T49: =SUM(H49:S49) -> 418.8
A50: CapCut | J50: 65.9
A51: Typeform | C51: 0 | D51: 0 | E51: 343.72 | F51: 345.77 | G51: 337.74 | H51: 350.3 | I51: 329.55 | J51: 319.2 | K51: 343.32 | L51: 343.32 | M51: 343.32 | N51: 343.32 | O51: 343.32 | P51: 343.32 | Q51: 343.32 | R51: 343.32 | S51: 343.32 | T51: =SUM(H51:S51) -> 4088.93
A52: Manychat | C52: 0 | D52: 0 | E52: 143.59 | T52: =SUM(H52:S52) -> 0
A53: Lovable | C53: 0 | D53: 0 | E53: 1005.42 | F53: 144.14 | G53: 429.91 | H53: 289.98 | I53: =168.35 -> 168.35 | J53: =84.83+84.83+85+166.98 -> 421.64 | K53: 180 | L53: 180 | M53: 180 | N53: 180 | O53: 180 | P53: 180 | Q53: 180 | R53: 180 | S53: 180 | T53: =SUM(H53:S53) -> 2499.97
A54: Supabase | C54: 0 | D54: 145.61 | E54: 253.64 | F54: 269.55 | G54: 260.79 | H54: 262.08 | I54: 247.47 | J54: =53.5 -> 53.5 | K54: 145.61 | L54: 145.61 | M54: 145.61 | N54: 145.61 | O54: 145.61 | P54: 145.61 | Q54: 145.61 | R54: 145.61 | S54: 145.61 | T54: =SUM(H54:S54) -> 1873.54
A55: ChatGPT | C55: 0 | D55: 0 | E55: 808.88 | F55: 820.48 | G55: 796.95 | H55: 1009.76 | I55: =839.12+111.82 -> 950.94 | J55: =977.66+107.48 -> 1085.14 | K55: 807.95 | L55: 807.95 | M55: 807.95 | N55: 807.95 | O55: 807.95 | P55: 807.95 | Q55: 807.95 | R55: 807.95 | S55: 807.95 | T55: =SUM(H55:S55) -> 10317.39
A56: Clicksign | C56: 0 | D56: 0 | E56: 69 | F56: 69 | G56: 120.3 | H56: 69 | I56: 69 | J56: 69 | K56: 69 | L56: 69 | M56: 69 | N56: 69 | O56: 69 | P56: 69 | Q56: 69 | R56: 69 | S56: 69 | T56: =SUM(H56:S56) -> 828
A57: Hostinger | F57: 122.17 | H57: 91.07 | J57: 100.08 | T57: =SUM(H57:S57) -> 191.15
A58: Brazu | E58: 0 | F58: 190.63 | H58: 381.26 | T58: =SUM(H58:S58) -> 381.26
A59: Framer | E59: 0 | F59: 1352.91 | H59: 296.12 | I59: 294.51 | J59: 296.92 | R59: 1704 | T59: =SUM(H59:S59) -> 2591.55
A60: AWS | E60: 0 | F60: 0 | G60: 0 | H60: 0 | I60: 0 | J60: 0 | K60: 0 | L60: 0 | M60: 8000 | N60: 8400 | O60: 8820 | P60: 9261 | Q60: 9724.05 | R60: 10210.253 | S60: 10720.765 | T60: =SUM(H60:S60) -> 65136.068
A61: Railway | E61: 28.63 | F61: 29.31 | G61: 28.5 | H61: 29.78 | I61: 29 | J61: 30 | K61: 30 | L61: 30 | T61: =SUM(H61:S61) -> 148.78
A62: HubSpot | I62: 167.4 | J62: 167.4 | K62: 167.4 | L62: 167.4 | M62: 167.4 | N62: 167.4 | O62: 167.4 | P62: 167.4 | Q62: 167.4 | R62: 167.4 | S62: 167.4 | T62: =SUM(H62:S62) -> 1841.4
A63: Freepik | I63: 1126.38 | T63: =SUM(H63:S63) -> 1126.38
A64: Curseduca | H64: 397 | I64: 397 | J64: 397 | K64: 397 | L64: 397 | M64: 397 | N64: 397 | O64: 397 | P64: 397 | Q64: 397 | R64: 397 | S64: 397 | T64: =SUM(H64:S64) -> 4764
A65: Browserstack | H65: 289.1 | I65: 271.95 | J65: 268.52 | T65: =SUM(H65:S65) -> 829.57
A66: Zoom | H66: 126.59 | T66: =SUM(H66:S66) -> 126.59
A67: Claude | E67: 591.53 | F67: 590.76 | G67: 593.41 | H67: 592.21 | I67: =571.24+20.81 -> 592.05 | J67: =569.8+26.85+635.59 -> 1232.24 | K67: 1000 | L67: 1000 | T67: =SUM(H67:S67) -> 4416.5
A68: Serviços de terceiros | B68: =SUM(B69:B75) -> 0 | C68: =SUM(C69:C75) -> 3197 | D68: =SUM(D69:D75) -> 3800.87 | E68: =SUM(E69:E75) -> 16151.28 | F68: =SUM(F69:F75) -> 22223.4 | G68: =SUM(G69:G75) -> 22159 | H68: =SUM(H69:H75) -> 16412 | I68: =SUM(I69:I75) -> 16815 | ... S68: =SUM(S69:S75) -> 17715 | T68: =SUM(H68:S68) -> 170377
A69: Jurídico | E69: 5700 | F69: 7125 | G69: 7125 | H69: 7125 | I69: 7125 | J69: 7125 | K69: 7125 | L69: 7125 | M69: 7125 | N69: 7125 | O69: 7125 | P69: 7125 | Q69: 7125 | R69: 7125 | S69: 7125 | T69: =SUM(H69:S69) -> 85500
A70: Contabilidade | D70: 603.87 | E70: 587 | F70: 835 | G70: 587 | H70: 587 | I70: 590 | J70: 590 | K70: 590 | L70: 590 | M70: 590 | N70: 590 | O70: 590 | P70: 590 | Q70: 590 | R70: 590 | S70: 590 | T70: =SUM(H70:S70) -> 7077
A71: Trafego - Ramon | E71: 4000 | F71: 4000 | G71: 4000 | H71: 4000 | I71: 4000 | N71: 4000 | O71: 4000 | P71: 4000 | Q71: 4000 | R71: 4000 | S71: 4000 | T71: =SUM(H71:S71) -> 32000
A72: Consultoria - Matheus | C72: 3197 | D72: 3197 | E72: 3197 | F72: 4797 | G72: 4797 | T72: =SUM(H72:S72) -> 0
A73: Filmmaker | F73: 5466.4 | G73: 4100 | H73: 4100 | I73: 4100 | N73: 4100 | O73: 4100 | P73: 4100 | Q73: 4100 | R73: 4100 | S73: 4100 | T73: =SUM(H73:S73) -> 32800
A74: BPO - BeOrange | E74: 2667.28 | N74: 1900 | O74: 1900 | P74: 1900 | Q74: 1900 | R74: 1900 | S74: 1900 | T74: =SUM(H74:S74) -> 11400
A75: Criadora de Conteúdo | G75: 1550 | H75: 600 | I75: 1000 | T75: =SUM(H75:S75) -> 1600
A76: Custos Variáveis Diretos (COGS) | B76: =(B77+B84) -> 0 | C76: =(C77+C84) -> 0 | D76: =(D77+D84) -> 0 | E76: =(E77+E84) -> 0 | F76: =(F77+F84) -> 0 | G76: =(G77+G84) -> 0 | H76: =(H77+H84) -> 0 | I76: =(I77+I84) -> 0 | ... S76: =(S77+S84) -> 57874.963 | T76: =SUM(H76:S76) -> 283465.49
A77: Comissões | B77: =SUM(B78:B83) -> 0 | C77: =SUM(C78:C83) -> 0 | D77: =SUM(D78:D83) -> 0 | E77: =SUM(E78:E83) -> 0 | F77: =SUM(F78:F83) -> 0 | G77: =SUM(G78:G83) -> 0 | H77: =SUM(H78:H83) -> 0 | I77: =SUM(I78:I83) -> 0 | ... S77: =SUM(S78:S83) -> 39959.059 | T77: =SUM(H77:S77) -> 196070.07
A78: Comissões Embaixadores - Estimado | T78: =SUM(H78:S78) -> 0
A79: Comissões Embaixadores - Realizado | T79: =SUM(H79:S79) -> 0
A80: Comissões Agencia Parça - Estimado | H80: =G14*5% -> 0 | I80: =H14*5% -> 0 | J80: =I14*5% -> 0 | K80: =J14*5% -> 0 | L80: =K14*5% -> 905.28 | M80: =L14*5% -> 1810.56 | N80: =M14*5% -> 3168.48 | O80: =N14*5% -> 4526.4 | ... S80: =R14*5% -> 7991.8118 | T80: =SUM(H80:S80) -> 39214.014
A81: Comissões Agencia Parça - Realizado | H81: =G15*5% -> 0 | I81: =H15*5% -> 0 | J81: =I15*5% -> 0 | K81: =J15*5% -> 0 | L81: =K15*5% -> 0 | M81: =L15*5% -> 0 | N81: =M15*5% -> 0 | O81: =N15*5% -> 0 | ... S81: =R15*5% -> 0 | T81: =SUM(H81:S81) -> 0
A82: Comissões Influenciadores - Estimado | H82: =G14*20% -> 0 | I82: =H14*20% -> 0 | J82: =I14*20% -> 0 | K82: =J14*20% -> 0 | L82: =K14*20% -> 3621.12 | M82: =L14*20% -> 7242.24 | N82: =M14*20% -> 12673.92 | O82: =N14*20% -> 18105.6 | ... S82: =R14*20% -> 31967.247 | T82: =SUM(H82:S82) -> 156856.06
A83: Comissões Influenciadores - Realizado | H83: =G15*20% -> 0 | I83: =H15*20% -> 0 | J83: =I15*20% -> 0 | K83: =J15*20% -> 0 | L83: =K15*20% -> 0 | M83: =L15*20% -> 0 | N83: =M15*20% -> 0 | O83: =N15*20% -> 0 | ... S83: =R15*20% -> 0 | T83: =SUM(H83:S83) -> 0
A84: Infraestrutura AWS | B84: =SUM(B85) -> 0 | C84: =SUM(C85) -> 0 | D84: =SUM(D85) -> 0 | E84: =SUM(E85) -> 0 | F84: =SUM(F85) -> 0 | G84: =SUM(G85) -> 0 | H84: =SUM(H85) -> 0 | I84: =SUM(I85) -> 0 | ... S84: =SUM(S85) -> 17915.904 | T84: =SUM(H84:S84) -> 87395.424
A85: AWS | B85: 0 | C85: 0 | D85: 0 | E85: 0 | F85: 0 | G85: 0 | H85: 0 | I85: 0 | J85: 3300 | K85: 3300 | L85: 3300 | M85: 6000 | N85: =M85*1.2 -> 7200 | O85: =N85*1.2 -> 8640 | P85: =O85*1.2 -> 10368 | Q85: =P85*1.2 -> 12441.6 | R85: =Q85*1.2 -> 14929.92 | S85: =R85*1.2 -> 17915.904 | T85: =SUM(H85:S85) -> 87395.424
A86: Despesas Operacionais Variáveis | B86: =B87+B95+B99+B116 -> 0 | C86: =C87+C95+C99+C116+C142 -> 250 | D86: =D87+D95+D99+D116+D142 -> 1755 | E86: =E87+E95+E99+E116+E142 -> 54273.44 | F86: =F87+F95+F99+F116+F142 -> 80896.19 | G86: =G87+G95+G99+G116+G142 -> 54757.36 | H86: =H87+H95+H99+H116+H142 -> 76755.16 | I86: =I87+I95+I99+I116+I142 -> 41903.51 | J86: =J87+J95+J99+J116+J142 -> 51966.51 | ... S86: =S87+S95+S99+S116+S142 -> 904607.97 | T86: =SUM(H86:S86) -> 4140072.2
A87: Marketing e Growth | B87: =SUM(B88:B94) -> 0 | C87: =SUM(C88:C94) -> 0 | D87: =SUM(D88:D94) -> 0 | E87: =SUM(E88:E94) -> 19539.42 | F87: =SUM(F88:F94) -> 17011.84 | G87: =SUM(G88:G94) -> 41861.56 | H87: =SUM(H88:H94) -> 57688.26 | I87: =SUM(I88:I94) -> 35867.57 | ... S87: =SUM(S88:S94) -> 566585.24 | T87: =SUM(H87:S87) -> 3140709.3
A88: Influenciadores | D88: 0 | E88: 18964.42 | F88: 14000 | G88: 19000 | H88: 18000 | I88: 20000 | J88: 20000 | K88: 20000 | L88: 20000 | M88: 20000 | N88: 60000 | O88: 100000 | P88: 100000 | Q88: 100000 | R88: 100000 | S88: 100000 | T88: =SUM(H88:S88) -> 678000
A89: Patrocinio de Eventos | H89: 200 | T89: =SUM(H89:S89) -> 200
A90: Trafego | D90: 0 | F90: 2436.84 | G90: 5861.56 | H90: 31338.26 | I90: =3129.5+0.2+2162.87 -> 5292.57 | J90: 1000 | K90: 1000 | L90: 5000 | M90: 30000 | N90: 100000 | O90: 100000 | P90: 100000 | Q90: 100000 | R90: 100000 | S90: 100000 | T90: =SUM(H90:S90) -> 673630.83
A91: Investimento MUVX Digital (Influencia e Trafego) | J91: 10000 | K91: 10000 | L91: 30000 | M91: 40000 | N91: 174800 | O91: 201020 | P91: 231173 | Q91: 265848.95 | R91: 305726.29 | S91: 351585.24 | T91: =SUM(H91:S91) -> 1620153.5
A92: Gestão Mkt Influencia | G92: 17000 | H92: 7000 | I92: 5000 | J92: 5000 | K92: 5000 | L92: 5000 | M92: 5000 | N92: 5000 | O92: 5000 | P92: 5000 | Q92: 5000 | R92: 5000 | S92: 5000 | T92: =SUM(H92:S92) -> 62000
A93: Embaixadores chaves | I93: 5000 | J93: 10000 | K93: 10000 | L93: 10000 | M93: 10000 | N93: 10000 | O93: 10000 | P93: 10000 | Q93: 10000 | R93: 10000 | S93: 10000
A94: Identidade Visual/Marca/Branding | E94: 575 | F94: 575 | H94: 1150 | I94: 575 | T94: =SUM(H94:S94) -> 1725
A95: Pessoas e Recrutamento | B95: =SUM(B96:B98) -> 0 | C95: =SUM(C96:C98) -> 0 | D95: =SUM(D96:D98) -> 0 | E95: =SUM(E96:E98) -> 6540.06 | F95: =SUM(F96:F98) -> 7112.85 | G95: =SUM(G96:G98) -> 6424.32 | H95: =SUM(H96:H98) -> 3376.64 | I95: =SUM(I96:I98) -> 1199.42 | ... S95: =SUM(S96:S98) -> 72.15 | T95: =SUM(H95:S95) -> 22339.58
A96: Treinamento MKT | E96: 5483.35 | F96: 5483.35 | G96: 5483.35 | H96: 2325.6 | I96: =72.15 -> 72.15 | J96: 72.15 | K96: =5483.35+72.15 -> 5555.5 | L96: =5483.35+72.15 -> 5555.5 | M96: =5483.35+72.15 -> 5555.5 | N96: 72.15 | O96: 72.15 | P96: 72.15 | Q96: 72.15 | R96: 72.15 | S96: 72.15 | T96: =SUM(H96:S96) -> 19569.3
A97: LinkedIn | Vagas | E97: 1056.71 | F97: 668.5 | G97: 940.97 | H97: 1051.04 | I97: =243.21+536.42+128.44+219.2 -> 1127.27 | J97: 591.97 | T97: =SUM(H97:S97) -> 2770.28
A98: Eventos/Treinamentos Equipe | F98: 961 | T98: =SUM(H98:S98) -> 0
A99: Operacional e Geral | B99: =SUM(B100:B115) -> 0 | C99: =SUM(C100:C115) -> 250 | D99: =SUM(D100:D115) -> 1755 | E99: =SUM(E100:E115) -> 7718.16 | F99: =SUM(F100:F115) -> 5222.82 | G99: =SUM(G100:G115) -> 1279.97 | H99: =SUM(H100:H115) -> 8039.14 | I99: =SUM(I100:I115) -> 2450.93 | ... S99: =SUM(S100:S115) -> 2000 | T99: =SUM(H99:S99) -> 34662.62
A100: Press Kit | D100: 875 | E100: 2967.17 | F100: 3779.54 | G100: 71.94 | H100: 6676.66 | I100: =71.97+816.45+117.83 -> 1006.25 | J100: 816.45 | K100: 816.45 | L100: 816.45 | M100: 816.45 | N100: 816.45 | T100: =SUM(H100:S100) -> 11765.16
...

Sheet Proj. Vendas MUVX Core New
C1: Top | E1: Install | G1: Ativação | I1: Conversão | N1: Cenário sem perdas operacionais | X1: Cenário com perdas operacionais
A2: Mês | B2: Investimento no Mês (Growth) // 5% | C2: CPL - Tráfego (cadastro) | D2: Novos Cadastros LP | E2: Tx. % Install | F2: Novos Installs no App | G2: Tx % Ativações | H2: Novos Personais Habilitados | I2: Tx % de Conversão | J2: Cadastros Evento Presencial | K2: Tx % Ativação Presencial | L2: Novos Personais Ativados | M2: Personais Totais | N2: CAC (ativação) | O2: Tx. % Churn | P2: Qtde. Churn no Mês | Q2: Personais Ativos Mês | R2: Média Alunos Estimada Total Personal | S2: Ticket Médio Aluno Personal | T2: Média Faturamento Estimada Personal | U2: Total Usuários Estimado | V2: Faturamento Estimado | W2: Receita MUVX Estimada (2%) | X2: Média Real Alunos Ativos Personal | Y2: Tx. % Real Alunos não ativados | Z2: Média Real por Personal | AA2: Total Real Usuários | AB2: Faturamento Real Bruto | AC2: Receita MUVX (2%) | AD2: Faturamento Real Acumulado | AE2: Receita MUVX Acumulada | AF2: Investimento Acumulado | AG2: ROI | AH2: ROI Acumulado
A3: 46023 | B3: =B64*0.05 -> 1566.913 | C3: =C64 -> 12 | D3: =Table15313[[#This Row],[Investimento no Mês (Growth) // 5%]]/Table15313[[#This Row],[CPL - Tráfego (cadastro)]] -> 130.57608 | E3: =E64 -> 0.06 | F3: =Table15313[[#This Row],[Novos Cadastros LP]]*Table15313[[#This Row],[Tx. % Install]] -> 7.834565 | G3: =G64 -> 0 | H3: =Table15313[[#This Row],[Novos Installs no App]]*Table15313[[#This Row],[Tx % Ativações]] -> 0 | I3: =I64 -> 0.7 | J3: =J64*20% -> 0 | K3: =K64 -> 0 | L3: =(Table15313[[#This Row],[Novos Personais Habilitados]]*Table15313[[#This Row],[Tx % de Conversão]])+(Table15313[[#This Row],[Cadastros Evento Presencial]]*Table15313[[#This Row],[Tx % Ativação Presencial]]) -> 0 | M3: =Table15313[[#This Row],[Novos Personais Ativados]] -> 0 | N3: =Table15313[[#This Row],[Investimento no Mês (Growth) // 5%]]/Table15313[[#This Row],[Novos Personais Ativados]] -> #DIV/0! | O3: 0 | P3: =Table15313[[#This Row],[Personais Totais]]*Table15313[[#This Row],[Tx. % Churn]] -> 0 | Q3: =Table15313[[#This Row],[Personais Totais]]-Table15313[[#This Row],[Qtde. Churn no Mês]] -> 0 | R3: 15 | S3: 0 | T3: 0 | U3: =Table15313[[#This Row],[Personais Ativos Mês]]+(Table15313[[#This Row],[Personais Ativos Mês]]*Table15313[[#This Row],[Média Alunos Estimada Total Personal]]) -> 0 | V3: 0 | W3: =Table15313[[#This Row],[Faturamento Estimado]]*2% -> 0 | X3: =Table15313[[#This Row],[Média Alunos Estimada Total Personal]]-(Table15313[[#This Row],[Tx. % Real Alunos não ativados]]*Table15313[[#This Row],[Média Alunos Estimada Total Personal]]) -> 9.75 | Y3: 0.35 | Z3: =AB3/Q3 -> #DIV/0! | AA3: =Table15313[[#This Row],[Média Real Alunos Ativos Personal]]*Table15313[[#This Row],[Personais Ativos Mês]] -> 0 | AB3: 0 | AC3: 0 | AD3: =Table15313[[#This Row],[Faturamento Real Bruto]] -> 0 | AE3: 0 | AF3: =Table15313[[#This Row],[Investimento no Mês (Growth) // 5%]] -> 1566.913 | AG3: 0 | AH3: 0
A4: 46054 | B4: =B65*0.05 -> 264.6285 | C4: =C65 -> 14 | D4: 1031 | E4: =E65 -> 0.2 | F4: =Table15313[[#This Row],[Novos Cadastros LP]]*Table15313[[#This Row],[Tx. % Install]] -> 206.2 | G4: =G65 -> 0.5 | H4: =Table15313[[#This Row],[Novos Installs no App]]*Table15313[[#This Row],[Tx % Ativações]] -> 103.1 | I4: =I65 -> 0.3 | J4: =J65*20% -> 0 | K4: =K65 -> 0 | L4: =(Table15313[[#This Row],[Novos Personais Habilitados]]*Table15313[[#This Row],[Tx % de Conversão]])+(Table15313[[#This Row],[Cadastros Evento Presencial]]*Table15313[[#This Row],[Tx % Ativação Presencial]]) -> 30.93 | M4: =Table15313[[#This Row],[Novos Personais Ativados]]+M3 -> 30.93 | N4: =Table15313[[#This Row],[Investimento no Mês (Growth) // 5%]]/Table15313[[#This Row],[Novos Personais Ativados]] -> 8.5557226 | O4: 0.02 | P4: =M3*Table15313[[#This Row],[Tx. % Churn]] -> 0 | Q4: =Table15313[[#This Row],[Personais Totais]]-Table15313[[#This Row],[Qtde. Churn no Mês]] -> 30.93 | R4: 15 | S4: 250 | T4: =Table15313[[#This Row],[Média Alunos Estimada Total Personal]]*Table15313[[#This Row],[Ticket Médio Aluno Personal]] -> 3750 | U4: =Table15313[[#This Row],[Personais Ativos Mês]]+(Table15313[[#This Row],[Personais Ativos Mês]]*Table15313[[#This Row],[Média Alunos Estimada Total Personal]]) -> 494.88 | V4: =Table15313[[#This Row],[Média Faturamento Estimada Personal]]*Q3 -> 0 | W4: =Table15313[[#This Row],[Faturamento Estimado]]*2% -> 0 | X4: =Table15313[[#This Row],[Média Alunos Estimada Total Personal]]-(Table15313[[#This Row],[Tx. % Real Alunos não ativados]]*Table15313[[#This Row],[Média Alunos Estimada Total Personal]]) -> 4.5 | Y4: 0.7 | Z4: =Table15313[[#This Row],[Ticket Médio Aluno Personal]]*Table15313[[#This Row],[Média Real Alunos Ativos Personal]] -> 1125 | AA4: =Table15313[[#This Row],[Média Real Alunos Ativos Personal]]*Table15313[[#This Row],[Personais Ativos Mês]] -> 139.185 | AB4: =Table15313[[#This Row],[Média Real por Personal]]*Q3 -> 0 | AC4: =Table15313[[#This Row],[Faturamento Real Bruto]]*2% -> 0 | AD4: =Table15313[[#This Row],[Faturamento Real Bruto]]+AB3 -> 0 | AE4: =Table15313[[#This Row],[Receita MUVX (2%)]]+AC3 -> 0 | AF4: =Table15313[[#This Row],[Investimento no Mês (Growth) // 5%]]+AF3 -> 1831.5415 | AG4: =Table15313[[#This Row],[Receita MUVX Acumulada]]/Table15313[[#This Row],[Investimento Acumulado]] -> 0 | AH4: =Table15313[[#This Row],[ROI]]+AH3 -> 0
A5: 46082 | B5: =B66*0.05 -> 50 | C5: =C66 -> 13.86 | D5: =Table15313[[#This Row],[Investimento no Mês (Growth) // 5%]]/Table15313[[#This Row],[CPL - Tráfego (cadastro)]] -> 3.6075036 | E5: =E66 -> 0.2 | F5: =Table15313[[#This Row],[Novos Cadastros LP]]*Table15313[[#This Row],[Tx. % Install]] -> 0.72150072 | G5: =G66 -> 0.5 | H5: =Table15313[[#This Row],[Novos Installs no App]]*Table15313[[#This Row],[Tx % Ativações]] -> 0.36075036 | I5: =I66 -> 0.3 | J5: =J66*20% -> 0 | K5: =K66 -> 0 | L5: =(Table15313[[#This Row],[Novos Personais Habilitados]]*Table15313[[#This Row],[Tx % de Conversão]])+(Table15313[[#This Row],[Cadastros Evento Presencial]]*Table15313[[#This Row],[Tx % Ativação Presencial]]) -> 0.10822511 | M5: =Table15313[[#This Row],[Novos Personais Ativados]]+M4 -> 31.038225 | N5: =Table15313[[#This Row],[Investimento no Mês (Growth) // 5%]]/Table15313[[#This Row],[Novos Personais Ativados]] -> 462 | O5: 0.03 | P5: =M4*Table15313[[#This Row],[Tx. % Churn]] -> 0.9279 | Q5: =Table15313[[#This Row],[Personais Totais]]-Table15313[[#This Row],[Qtde. Churn no Mês]] -> 30.110325 | R5: 15 | S5: =S4*1.005 -> 251.25 | T5: =Table15313[[#This Row],[Média Alunos Estimada Total Personal]]*Table15313[[#This Row],[Ticket Médio Aluno Personal]] -> 3768.75 | U5: =Table15313[[#This Row],[Personais Ativos Mês]]+(Table15313[[#This Row],[Personais Ativos Mês]]*Table15313[[#This Row],[Média Alunos Estimada Total Personal]]) -> 481.7652 | V5: =Table15313[[#This Row],[Média Faturamento Estimada Personal]]*Q4 -> 116567.44 | W5: =Table15313[[#This Row],[Faturamento Estimado]]*2% -> 2331.3487 | X5: =Table15313[[#This Row],[Média Alunos Estimada Total Personal]]-(Table15313[[#This Row],[Tx. % Real Alunos não ativados]]*Table15313[[#This Row],[Média Alunos Estimada Total Personal]]) -> 14.25 | Y5: 0.05 | Z5: =Table15313[[#This Row],[Ticket Médio Aluno Personal]]*Table15313[[#This Row],[Média Real Alunos Ativos Personal]] -> 3580.3125 | AA5: =Table15313[[#This Row],[Média Real Alunos Ativos Personal]]*Table15313[[#This Row],[Personais Ativos Mês]] -> 429.07213 | AB5: =Table15313[[#This Row],[Média Real por Personal]]*Q4 -> 110739.07 | AC5: =Table15313[[#This Row],[Faturamento Real Bruto]]*2% -> 2214.7813 | AD5: =AD4+Table15313[[#This Row],[Faturamento Real Bruto]] -> 110739.07 | AE5: =AE4+Table15313[[#This Row],[Receita MUVX (2%)]] -> 2214.7813 | AF5: =Table15313[[#This Row],[Investimento no Mês (Growth) // 5%]]+AF4 -> 1881.5415 | AG5: =Table15313[[#This Row],[Receita MUVX Acumulada]]/Table15313[[#This Row],[Investimento Acumulado]] -> 1.17711 | AH5: =Table15313[[#This Row],[ROI]]+AH4 -> 1.17711
A6: 46113 | B6: =B67*0.05 -> 50 | C6: =C67 -> 13.7214 | D6: =Table15313[[#This Row],[Investimento no Mês (Growth) // 5%]]/Table15313[[#This Row],[CPL - Tráfego (cadastro)]] -> 3.643943 | E6: =E67 -> 0.2 | F6: =Table15313[[#This Row],[Novos Cadastros LP]]*Table15313[[#This Row],[Tx. % Install]] -> 0.72878861 | G6: =G67 -> 0.5 | H6: =Table15313[[#This Row],[Novos Installs no App]]*Table15313[[#This Row],[Tx % Ativações]] -> 0.3643943 | I6: =I67 -> 0.3 | J6: =J67*20% -> 0 | K6: =K67 -> 0 | L6: =(Table15313[[#This Row],[Novos Personais Habilitados]]*Table15313[[#This Row],[Tx % de Conversão]])+(Table15313[[#This Row],[Cadastros Evento Presencial]]*Table15313[[#This Row],[Tx % Ativação Presencial]]) -> 0.10931829 | M6: =Table15313[[#This Row],[Novos Personais Ativados]]+M5 -> 31.147543 | N6: =Table15313[[#This Row],[Investimento no Mês (Growth) // 5%]]/Table15313[[#This Row],[Novos Personais Ativados]] -> 457.38 | O6: 0.02 | P6: =M5*Table15313[[#This Row],[Tx. % Churn]] -> 0.6207645 | Q6: =Table15313[[#This Row],[Personais Totais]]-Table15313[[#This Row],[Qtde. Churn no Mês]] -> 30.526779 | R6: 15 | S6: =S5*1.015 -> 255.01875 | T6: =Table15313[[#This Row],[Média Alunos Estimada Total Personal]]*Table15313[[#This Row],[Ticket Médio Aluno Personal]] -> 3825.2812 | U6: =Table15313[[#This Row],[Personais Ativos Mês]]+(Table15313[[#This Row],[Personais Ativos Mês]]*Table15313[[#This Row],[Média Alunos Estimada Total Personal]]) -> 488.42846 | V6: =Table15313[[#This Row],[Média Faturamento Estimada Personal]]*Q5 -> 115180.46 | W6: =Table15313[[#This Row],[Faturamento Estimado]]*2% -> 2303.6092 | X6: =Table15313[[#This Row],[Média Alunos Estimada Total Personal]]-(Table15313[[#This Row],[Tx. % Real Alunos não ativados]]*Table15313[[#This Row],[Média Alunos Estimada Total Personal]]) -> 14.25 | Y6: 0.05 | Z6: =Table15313[[#This Row],[Ticket Médio Aluno Personal]]*Table15313[[#This Row],[Média Real Alunos Ativos Personal]] -> 3634.0172 | AA6: =Table15313[[#This Row],[Média Real Alunos Ativos Personal]]*Table15313[[#This Row],[Personais Ativos Mês]] -> 435.0066 | AB6: =Table15313[[#This Row],[Média Real por Personal]]*Q5 -> 109421.44 | AC6: =Table15313[[#This Row],[Faturamento Real Bruto]]*2% -> 2188.4288 | AD6: =AD5+Table15313[[#This Row],[Faturamento Real Bruto]] -> 220160.5 | AE6: =AE5+Table15313[[#This Row],[Receita MUVX (2%)]] -> 4403.2101 | AF6: =Table15313[[#This Row],[Investimento no Mês (Growth) // 5%]]+AF5 -> 1931.5415 | AG6: =Table15313[[#This Row],[Receita MUVX Acumulada]]/Table15313[[#This Row],[Investimento Acumulado]] -> 2.2796353 | AH6: =Table15313[[#This Row],[ROI]]+AH5 -> 3.4567452
A7: 46143 | B7: =B68*0.05 -> 250 | C7: =C68 -> 13.584186 | D7: =Table15313[[#This Row],[Investimento no Mês (Growth) // 5%]]/Table15313[[#This Row],[CPL - Tráfego (cadastro)]] -> 18.403753 | E7: =E68 -> 0.2 | F7: =Table15313[[#This Row],[Novos Cadastros LP]]*Table15313[[#This Row],[Tx. % Install]] -> 3.6807505 | G7: =G68 -> 0.6 | H7: =Table15313[[#This Row],[Novos Installs no App]]*Table15313[[#This Row],[Tx % Ativações]] -> 2.2084503 | I7: =I68 -> 0.3 | J7: =J68*20% -> 0 | K7: =K68 -> 0 | L7: =(Table15313[[#This Row],[Novos Personais Habilitados]]*Table15313[[#This Row],[Tx % de Conversão]])+(Table15313[[#This Row],[Cadastros Evento Presencial]]*Table15313[[#This Row],[Tx % Ativação Presencial]]) -> 0.6625351 | M7: =Table15313[[#This Row],[Novos Personais Ativados]]+M6 -> 31.810078 | N7: =Table15313[[#This Row],[Investimento no Mês (Growth) // 5%]]/Table15313[[#This Row],[Novos Personais Ativados]] -> 377.3385 | O7: 0.02 | P7: =M6*Table15313[[#This Row],[Tx. % Churn]] -> 0.62295087 | Q7: =Table15313[[#This Row],[Personais Totais]]-Table15313[[#This Row],[Qtde. Churn no Mês]] -> 31.187128 | R7: 15 | S7: =S6*1.015 -> 258.84403 | T7: =Table15313[[#This Row],[Média Alunos Estimada Total Personal]]*Table15313[[#This Row],[Ticket Médio Aluno Personal]] -> 3882.6605 | U7: =Table15313[[#This Row],[Personais Ativos Mês]]+(Table15313[[#This Row],[Personais Ativos Mês]]*Table15313[[#This Row],[Média Alunos Estimada Total Personal]]) -> 498.99404 | V7: =Table15313[[#This Row],[Média Faturamento Estimada Personal]]*Q6 -> 118525.12 | W7: =Table15313[[#This Row],[Faturamento Estimado]]*2% -> 2370.5024 | X7: =Table15313[[#This Row],[Média Alunos Estimada Total Personal]]-(Table15313[[#This Row],[Tx. % Real Alunos não ativados]]*Table15313[[#This Row],[Média Alunos Estimada Total Personal]]) -> 14.25 | Y7: 0.05 | Z7: =Table15313[[#This Row],[Ticket Médio Aluno Personal]]*Table15313[[#This Row],[Média Real Alunos Ativos Personal]] -> 3688.5274 | AA7: =Table15313[[#This Row],[Média Real Alunos Ativos Personal]]*Table15313[[#This Row],[Personais Ativos Mês]] -> 444.41657 | AB7: =Table15313[[#This Row],[Média Real por Personal]]*Q6 -> 112598.86 | AC7: =Table15313[[#This Row],[Faturamento Real Bruto]]*2% -> 2251.9772 | AD7: =AD6+Table15313[[#This Row],[Faturamento Real Bruto]] -> 332759.37 | AE7: =AE6+Table15313[[#This Row],[Receita MUVX (2%)]] -> 6655.1873 | AF7: =Table15313[[#This Row],[Investimento no Mês (Growth) // 5%]]+AF6 -> 2181.5415 | AG7: =Table15313[[#This Row],[Receita MUVX Acumulada]]/Table15313[[#This Row],[Investimento Acumulado]] -> 3.0506811 | AH7: =Table15313[[#This Row],[ROI]]+AH6 -> 6.5074263
A8: 46174 | B8: =B69*0.05 -> 1500 | C8: =C69 -> 13.448344 | D8: =Table15313[[#This Row],[Investimento no Mês (Growth) // 5%]]/Table15313[[#This Row],[CPL - Tráfego (cadastro)]] -> 111.5379 | E8: 0.3 | F8: =Table15313[[#This Row],[Novos Cadastros LP]]*Table15313[[#This Row],[Tx. % Install]] -> 33.461369 | G8: =G69 -> 0.6 | H8: =Table15313[[#This Row],[Novos Installs no App]]*Table15313[[#This Row],[Tx % Ativações]] -> 20.076821 | I8: =I69 -> 0.3 | J8: =J69*20% -> 0 | K8: =K69 -> 0 | L8: =(Table15313[[#This Row],[Novos Personais Habilitados]]*Table15313[[#This Row],[Tx % de Conversão]])+(Table15313[[#This Row],[Cadastros Evento Presencial]]*Table15313[[#This Row],[Tx % Ativação Presencial]]) -> 6.0230463 | M8: =Table15313[[#This Row],[Novos Personais Ativados]]+M7 -> 37.833125 | N8: =Table15313[[#This Row],[Investimento no Mês (Growth) // 5%]]/Table15313[[#This Row],[Novos Personais Ativados]] -> 249.04341 | O8: 0.04 | P8: =M7*Table15313[[#This Row],[Tx. % Churn]] -> 1.2724031 | Q8: =Table15313[[#This Row],[Personais Totais]]-Table15313[[#This Row],[Qtde. Churn no Mês]] -> 36.560722 | R8: 15 | S8: =S7*1.015 -> 262.72669 | T8: =Table15313[[#This Row],[Média Alunos Estimada Total Personal]]*Table15313[[#This Row],[Ticket Médio Aluno Personal]] -> 3940.9004 | U8: =Table15313[[#This Row],[Personais Ativos Mês]]+(Table15313[[#This Row],[Personais Ativos Mês]]*Table15313[[#This Row],[Média Alunos Estimada Total Personal]]) -> 584.97155 | V8: =Table15313[[#This Row],[Média Faturamento Estimada Personal]]*Q7 -> 122905.36 | W8: =Table15313[[#This Row],[Faturamento Estimado]]*2% -> 2458.1073 | X8: =Table15313[[#This Row],[Média Alunos Estimada Total Personal]]-(Table15313[[#This Row],[Tx. % Real Alunos não ativados]]*Table15313[[#This Row],[Média Alunos Estimada Total Personal]]) -> 14.25 | Y8: 0.05 | Z8: =Table15313[[#This Row],[Ticket Médio Aluno Personal]]*Table15313[[#This Row],[Média Real Alunos Ativos Personal]] -> 3743.8554 | AA8: =Table15313[[#This Row],[Média Real Alunos Ativos Personal]]*Table15313[[#This Row],[Personais Ativos Mês]] -> 520.99028 | AB8: =Table15313[[#This Row],[Média Real por Personal]]*Q7 -> 116760.09 | AC8: =Table15313[[#This Row],[Faturamento Real Bruto]]*2% -> 2335.2019 | AD8: =AD7+Table15313[[#This Row],[Faturamento Real Bruto]] -> 449519.46 | AE8: =AE7+Table15313[[#This Row],[Receita MUVX (2%)]] -> 8990.3892 | AF8: =Table15313[[#This Row],[Investimento no Mês (Growth) // 5%]]+AF7 -> 3681.5415 | AG8: =Table15313[[#This Row],[Receita MUVX Acumulada]]/Table15313[[#This Row],[Investimento Acumulado]] -> 2.4420176 | AH8: =Table15313[[#This Row],[ROI]]+AH7 -> 8.9494439
A9: 46204 | B9: =B70*0.05 -> 5000 | C9: =C70 -> 13.313861 | D9: =Table15313[[#This Row],[Investimento no Mês (Growth) // 5%]]/Table15313[[#This Row],[CPL - Tráfego (cadastro)]] -> 375.54847 | E9: =E70 -> 0.3 | F9: =Table15313[[#This Row],[Novos Cadastros LP]]*Table15313[[#This Row],[Tx. % Install]] -> 112.66454 | G9: =G70 -> 0.6 | H9: =Table15313[[#This Row],[Novos Installs no App]]*Table15313[[#This Row],[Tx % Ativações]] -> 67.598724 | I9: =I70 -> 0.3 | J9: =J70*20% -> 0 | K9: =K70 -> 0.2 | L9: =(Table15313[[#This Row],[Novos Personais Habilitados]]*Table15313[[#This Row],[Tx % de Conversão]])+(Table15313[[#This Row],[Cadastros Evento Presencial]]*Table15313[[#This Row],[Tx % Ativação Presencial]]) -> 20.279617 | M9: =Table15313[[#This Row],[Novos Personais Ativados]]+M8 -> 58.112742 | N9: =Table15313[[#This Row],[Investimento no Mês (Growth) // 5%]]/Table15313[[#This Row],[Novos Personais Ativados]] -> 246.55298 | O9: 0.02 | P9: =M8*Table15313[[#This Row],[Tx. % Churn]] -> 0.7566625 | Q9: =Table15313[[#This Row],[Personais Totais]]-Table15313[[#This Row],[Qtde. Churn no Mês]] -> 57.35608 | R9: 15 | S9: =S8*1.015 -> 266.66759 | T9: =Table15313[[#This Row],[Média Alunos Estimada Total Personal]]*Table15313[[#This Row],[Ticket Médio Aluno Personal]] -> 4000.0139 | U9: =Table15313[[#This Row],[Personais Ativos Mês]]+(Table15313[[#This Row],[Personais Ativos Mês]]*Table15313[[#This Row],[Média Alunos Estimada Total Personal]]) -> 917.69727 | V9: =Table15313[[#This Row],[Média Faturamento Estimada Personal]]*Q8 -> 146243.39 | W9: =Table15313[[#This Row],[Faturamento Estimado]]*2% -> 2924.8679 | X9: =Table15313[[#This Row],[Média Alunos Estimada Total Personal]]-(Table15313[[#This Row],[Tx. % Real Alunos não ativados]]*Table15313[[#This Row],[Média Alunos Estimada Total Personal]]) -> 14.25 | Y9: 0.05 | Z9: =Table15313[[#This Row],[Ticket Médio Aluno Personal]]*Table15313[[#This Row],[Média Real Alunos Ativos Personal]] -> 3800.0132 | AA9: =Table15313[[#This Row],[Média Real Alunos Ativos Personal]]*Table15313[[#This Row],[Personais Ativos Mês]] -> 817.32414 | AB9: =Table15313[[#This Row],[Média Real por Personal]]*Q8 -> 138931.22 | AC9: =Table15313[[#This Row],[Faturamento Real Bruto]]*2% -> 2778.6245 | AD9: =AD8+Table15313[[#This Row],[Faturamento Real Bruto]] -> 588450.69 | AE9: =AE8+Table15313[[#This Row],[Receita MUVX (2%)]] -> 11769.014 | AF9: =Table15313[[#This Row],[Investimento no Mês (Growth) // 5%]]+AF8 -> 8681.5415 | AG9: =Table15313[[#This Row],[Receita MUVX Acumulada]]/Table15313[[#This Row],[Investimento Acumulado]] -> 1.3556364 | AH9: =Table15313[[#This Row],[ROI]]+AH8 -> 10.30508
A10: 46235 | B10: =B71*0.05 -> 5000 | C10: =C71 -> 13.180722 | D10: =Table15313[[#This Row],[Investimento no Mês (Growth) // 5%]]/Table15313[[#This Row],[CPL - Tráfego (cadastro)]] -> 379.34189 | E10: =E71 -> 0.3 | F10: =Table15313[[#This Row],[Novos Cadastros LP]]*Table15313[[#This Row],[Tx. % Install]] -> 113.80257 | G10: =G71 -> 0.6 | H10: =Table15313[[#This Row],[Novos Installs no App]]*Table15313[[#This Row],[Tx % Ativações]] -> 68.28154 | I10: =I71 -> 0.3 | J10: =J71*20% -> 0 | K10: =K71 -> 0 | L10: =(Table15313[[#This Row],[Novos Personais Habilitados]]*Table15313[[#This Row],[Tx % de Conversão]])+(Table15313[[#This Row],[Cadastros Evento Presencial]]*Table15313[[#This Row],[Tx % Ativação Presencial]]) -> 20.484462 | M10: =Table15313[[#This Row],[Novos Personais Ativados]]+M9 -> 78.597204 | N10: =Table15313[[#This Row],[Investimento no Mês (Growth) // 5%]]/Table15313[[#This Row],[Novos Personais Ativados]] -> 244.08745 | O10: 0.02 | P10: =M9*Table15313[[#This Row],[Tx. % Churn]] -> 1.1622548 | Q10: =Table15313[[#This Row],[Personais Totais]]-Table15313[[#This Row],[Qtde. Churn no Mês]] -> 77.434949 | R10: 15 | S10: =S9*1.015 -> 270.66761 | T10: =Table15313[[#This Row],[Média Alunos Estimada Total Personal]]*Table15313[[#This Row],[Ticket Médio Aluno Personal]] -> 4060.0141 | U10: =Table15313[[#This Row],[Personais Ativos Mês]]+(Table15313[[#This Row],[Personais Ativos Mês]]*Table15313[[#This Row],[Média Alunos Estimada Total Personal]]) -> 1238.9592 | V10: =Table15313[[#This Row],[Média Faturamento Estimada Personal]]*Q9 -> 232866.49 | W10: =Table15313[[#This Row],[Faturamento Estimado]]*2% -> 4657.3298 | X10: =Table15313[[#This Row],[Média Alunos Estimada Total Personal]]-(Table15313[[#This Row],[Tx. % Real Alunos não ativados]]*Table15313[[#This Row],[Média Alunos Estimada Total Personal]]) -> 14.25 | Y10: 0.05 | Z10: =Table15313[[#This Row],[Ticket Médio Aluno Personal]]*Table15313[[#This Row],[Média Real Alunos Ativos Personal]] -> 3857.0134 | AA10: =Table15313[[#This Row],[Média Real Alunos Ativos Personal]]*Table15313[[#This Row],[Personais Ativos Mês]] -> 1103.448 | AB10: =Table15313[[#This Row],[Média Real por Personal]]*Q9 -> 221223.17 | AC10: =Table15313[[#This Row],[Faturamento Real Bruto]]*2% -> 4424.4633 | AD10: =AD9+Table15313[[#This Row],[Faturamento Real Bruto]] -> 809673.85 | AE10: =AE9+Table15313[[#This Row],[Receita MUVX (2%)]] -> 16193.477 | AF10: =Table15313[[#This Row],[Investimento no Mês (Growth) // 5%]]+AF9 -> 13681.541 | AG10: =Table15313[[#This Row],[Receita MUVX Acumulada]]/Table15313[[#This Row],[Investimento Acumulado]] -> 1.1836003 | AH10: =Table15313[[#This Row],[ROI]]+AH9 -> 11.488681
A11: 46266 | B11: =B72*0.05 -> 5000 | C11: =C72 -> 13.048915 | D11: =Table15313[[#This Row],[Investimento no Mês (Growth) // 5%]]/Table15313[[#This Row],[CPL - Tráfego (cadastro)]] -> 383.17362 | E11: =E72 -> 0.3 | F11: =Table15313[[#This Row],[Novos Cadastros LP]]*Table15313[[#This Row],[Tx. % Install]] -> 114.95209 | G11: =G72 -> 0.6 | H11: =Table15313[[#This Row],[Novos Installs no App]]*Table15313[[#This Row],[Tx % Ativações]] -> 68.971252 | I11: =I72 -> 0.3 | J11: =J72*20% -> 0 | K11: =K72 -> 0 | L11: =(Table15313[[#This Row],[Novos Personais Habilitados]]*Table15313[[#This Row],[Tx % de Conversão]])+(Table15313[[#This Row],[Cadastros Evento Presencial]]*Table15313[[#This Row],[Tx % Ativação Presencial]]) -> 20.691376 | M11: =Table15313[[#This Row],[Novos Personais Ativados]]+M10 -> 99.28858 | N11: =Table15313[[#This Row],[Investimento no Mês (Growth) // 5%]]/Table15313[[#This Row],[Novos Personais Ativados]] -> 241.64657 | O11: 0.02 | P11: =M10*Table15313[[#This Row],[Tx. % Churn]] -> 1.5719441 | Q11: =Table15313[[#This Row],[Personais Totais]]-Table15313[[#This Row],[Qtde. Churn no Mês]] -> 97.716636 | R11: 15 | S11: =S10*1.015 -> 274.72762 | T11: =Table15313[[#This Row],[Média Alunos Estimada Total Personal]]*Table15313[[#This Row],[Ticket Médio Aluno Personal]] -> 4120.9143 | U11: =Table15313[[#This Row],[Personais Ativos Mês]]+(Table15313[[#This Row],[Personais Ativos Mês]]*Table15313[[#This Row],[Média Alunos Estimada Total Personal]]) -> 1563.4662 | V11: =Table15313[[#This Row],[Média Faturamento Estimada Personal]]*Q10 -> 319102.79 | W11: =Table15313[[#This Row],[Faturamento Estimado]]*2% -> 6382.0558 | X11: =Table15313[[#This Row],[Média Alunos Estimada Total Personal]]-(Table15313[[#This Row],[Tx. % Real Alunos não ativados]]*Table15313[[#This Row],[Média Alunos Estimada Total Personal]]) -> 14.25 | Y11: 0.05 | Z11: =Table15313[[#This Row],[Ticket Médio Aluno Personal]]*Table15313[[#This Row],[Média Real Alunos Ativos Personal]] -> 3914.8686 | AA11: =Table15313[[#This Row],[Média Real Alunos Ativos Personal]]*Table15313[[#This Row],[Personais Ativos Mês]] -> 1392.4621 | AB11: =Table15313[[#This Row],[Média Real por Personal]]*Q10 -> 303147.65 | AC11: =Table15313[[#This Row],[Faturamento Real Bruto]]*2% -> 6062.953 | AD11: =AD10+Table15313[[#This Row],[Faturamento Real Bruto]] -> 1112821.5 | AE11: =AE10+Table15313[[#This Row],[Receita MUVX (2%)]] -> 22256.43 | AF11: =Table15313[[#This Row],[Investimento no Mês (Growth) // 5%]]+AF10 -> 18681.541 | AG11: =Table15313[[#This Row],[Receita MUVX Acumulada]]/Table15313[[#This Row],[Investimento Acumulado]] -> 1.1913594 | AH11: =Table15313[[#This Row],[ROI]]+AH10 -> 12.68004
A12: 46296 | B12: =B73*0.05 -> 5000 | C12: =C73 -> 12.918426 | D12: =Table15313[[#This Row],[Investimento no Mês (Growth) // 5%]]/Table15313[[#This Row],[CPL - Tráfego (cadastro)]] -> 387.04406 | E12: =E73 -> 0.3 | F12: =Table15313[[#This Row],[Novos Cadastros LP]]*Table15313[[#This Row],[Tx. % Install]] -> 116.11322 | G12: =G73 -> 0.6 | H12: =Table15313[[#This Row],[Novos Installs no App]]*Table15313[[#This Row],[Tx % Ativações]] -> 69.667932 | I12: =I73 -> 0.3 | J12: =J73*20% -> 0 | K12: =K73 -> 0 | L12: =(Table15313[[#This Row],[Novos Personais Habilitados]]*Table15313[[#This Row],[Tx % de Conversão]])+(Table15313[[#This Row],[Cadastros Evento Presencial]]*Table15313[[#This Row],[Tx % Ativação Presencial]]) -> 20.900379 | M12: =Table15313[[#This Row],[Novos Personais Ativados]]+M11 -> 120.18896 | N12: =Table15313[[#This Row],[Investimento no Mês (Growth) // 5%]]/Table15313[[#This Row],[Novos Personais Ativados]] -> 239.23011 | O12: 0.03 | P12: =M11*Table15313[[#This Row],[Tx. % Churn]] -> 2.9786574 | Q12: =Table15313[[#This Row],[Personais Totais]]-Table15313[[#This Row],[Qtde. Churn no Mês]] -> 117.2103 | R12: 15 | S12: =S11*1.015 -> 278.84853 | T12: =Table15313[[#This Row],[Média Alunos Estimada Total Personal]]*Table15313[[#This Row],[Ticket Médio Aluno Personal]] -> 4182.728 | U12: =Table15313[[#This Row],[Personais Ativos Mês]]+(Table15313[[#This Row],[Personais Ativos Mês]]*Table15313[[#This Row],[Média Alunos Estimada Total Personal]]) -> 1875.3648 | V12: =Table15313[[#This Row],[Média Faturamento Estimada Personal]]*Q11 -> 408722.11 | W12: =Table15313[[#This Row],[Faturamento Estimado]]*2% -> 8174.4422 | X12: =Table15313[[#This Row],[Média Alunos Estimada Total Personal]]-(Table15313[[#This Row],[Tx. % Real Alunos não ativados]]*Table15313[[#This Row],[Média Alunos Estimada Total Personal]]) -> 14.25 | Y12: 0.05 | Z12: =Table15313[[#This Row],[Ticket Médio Aluno Personal]]*Table15313[[#This Row],[Média Real Alunos Ativos Personal]] -> 3973.5916 | AA12: =Table15313[[#This Row],[Média Real Alunos Ativos Personal]]*Table15313[[#This Row],[Personais Ativos Mês]] -> 1670.2468 | AB12: =Table15313[[#This Row],[Média Real por Personal]]*Q11 -> 388286 | AC12: =Table15313[[#This Row],[Faturamento Real Bruto]]*2% -> 7765.7201 | AD12: =AD11+Table15313[[#This Row],[Faturamento Real Bruto]] -> 1501107.5 | AE12: =AE11+Table15313[[#This Row],[Receita MUVX (2%)]] -> 30022.15 | AF12: =Table15313[[#This Row],[Investimento no Mês (Growth) // 5%]]+AF11 -> 23681.541 | AG12: =Table15313[[#This Row],[Receita MUVX Acumulada]]/Table15313[[#This Row],[Investimento Acumulado]] -> 1.2677448 | AH12: =Table15313[[#This Row],[ROI]]+AH11 -> 13.947785
A13: 46327 | B13: =B74*0.05 -> 5000 | C13: =C74 -> 12.789241 | D13: =Table15313[[#This Row],[Investimento no Mês (Growth) // 5%]]/Table15313[[#This Row],[CPL - Tráfego (cadastro)]] -> 390.9536 | E13: =E74 -> 0.3 | F13: =Table15313[[#This Row],[Novos Cadastros LP]]*Table15313[[#This Row],[Tx. % Install]] -> 117.28608 | G13: =G74 -> 0.6 | H13: =Table15313[[#This Row],[Novos Installs no App]]*Table15313[[#This Row],[Tx % Ativações]] -> 70.371648 | I13: =I74 -> 0.3 | J13: =J74*20% -> 0 | K13: =K74 -> 0 | L13: =(Table15313[[#This Row],[Novos Personais Habilitados]]*Table15313[[#This Row],[Tx % de Conversão]])+(Table15313[[#This Row],[Cadastros Evento Presencial]]*Table15313[[#This Row],[Tx % Ativação Presencial]]) -> 21.111494 | M13: =Table15313[[#This Row],[Novos Personais Ativados]]+M12 -> 141.30045 | N13: =Table15313[[#This Row],[Investimento no Mês (Growth) // 5%]]/Table15313[[#This Row],[Novos Personais Ativados]] -> 236.8378 | O13: 0.02 | P13: =M12*Table15313[[#This Row],[Tx. % Churn]] -> 2.4037792 | Q13: =Table15313[[#This Row],[Personais Totais]]-Table15313[[#This Row],[Qtde. Churn no Mês]] -> 138.89667 | R13: 15 | S13: =S12*1.015 -> 283.03126 | T13: =Table15313[[#This Row],[Média Alunos Estimada Total Personal]]*Table15313[[#This Row],[Ticket Médio Aluno Personal]] -> 4245.4689 | U13: =Table15313[[#This Row],[Personais Ativos Mês]]+(Table15313[[#This Row],[Personais Ativos Mês]]*Table15313[[#This Row],[Média Alunos Estimada Total Personal]]) -> 2222.3468 | V13: =Table15313[[#This Row],[Média Faturamento Estimada Personal]]*Q12 -> 497612.7 | W13: =Table15313[[#This Row],[Faturamento Estimado]]*2% -> 9952.2539 | X13: =Table15313[[#This Row],[Média Alunos Estimada Total Personal]]-(Table15313[[#This Row],[Tx. % Real Alunos não ativados]]*Table15313[[#This Row],[Média Alunos Estimada Total Personal]]) -> 14.25 | Y13: 0.05 | Z13: =Table15313[[#This Row],[Ticket Médio Aluno Personal]]*Table15313[[#This Row],[Média Real Alunos Ativos Personal]] -> 4033.1955 | AA13: =Table15313[[#This Row],[Média Real Alunos Ativos Personal]]*Table15313[[#This Row],[Personais Ativos Mês]] -> 1979.2776 | AB13: =Table15313[[#This Row],[Média Real por Personal]]*Q12 -> 472732.06 | AC13: =Table15313[[#This Row],[Faturamento Real Bruto]]*2% -> 9454.6412 | AD13: =AD12+Table15313[[#This Row],[Faturamento Real Bruto]] -> 1973839.6 | AE13: =AE12+Table15313[[#This Row],[Receita MUVX (2%)]] -> 39476.791 | AF13: =Table15313[[#This Row],[Investimento no Mês (Growth) // 5%]]+AF12 -> 28681.541 | AG13: =Table15313[[#This Row],[Receita MUVX Acumulada]]/Table15313[[#This Row],[Investimento Acumulado]] -> 1.3763832 | AH13: =Table15313[[#This Row],[ROI]]+AH12 -> 15.324168
A14: 46357 | B14: =B75*0.05 -> 5000 | C14: =C75 -> 12.661349 | D14: =Table15313[[#This Row],[Investimento no Mês (Growth) // 5%]]/Table15313[[#This Row],[CPL - Tráfego (cadastro)]] -> 394.90263 | E14: =E75 -> 0.3 | F14: =Table15313[[#This Row],[Novos Cadastros LP]]*Table15313[[#This Row],[Tx. % Install]] -> 118.47079 | G14: =G75 -> 0.6 | H14: =Table15313[[#This Row],[Novos Installs no App]]*Table15313[[#This Row],[Tx % Ativações]] -> 71.082473 | I14: =I75 -> 0.3 | J14: =J75*20% -> 0 | K14: =K75 -> 0 | L14: =(Table15313[[#This Row],[Novos Personais Habilitados]]*Table15313[[#This Row],[Tx % de Conversão]])+(Table15313[[#This Row],[Cadastros Evento Presencial]]*Table15313[[#This Row],[Tx % Ativação Presencial]]) -> 21.324742 | M14: =Table15313[[#This Row],[Novos Personais Ativados]]+M13 -> 162.6252 | N14: =Table15313[[#This Row],[Investimento no Mês (Growth) // 5%]]/Table15313[[#This Row],[Novos Personais Ativados]] -> 234.46943 | O14: 0.03 | P14: =M13*Table15313[[#This Row],[Tx. % Churn]] -> 4.2390136 | Q14: =Table15313[[#This Row],[Personais Totais]]-Table15313[[#This Row],[Qtde. Churn no Mês]] -> 158.38618 | R14: 15 | S14: =S13*1.015 -> 287.27673 | T14: =Table15313[[#This Row],[Média Alunos Estimada Total Personal]]*Table15313[[#This Row],[Ticket Médio Aluno Personal]] -> 4309.151 | U14: =Table15313[[#This Row],[Personais Ativos Mês]]+(Table15313[[#This Row],[Personais Ativos Mês]]*Table15313[[#This Row],[Média Alunos Estimada Total Personal]]) -> 2534.1789 | V14: =Table15313[[#This Row],[Média Faturamento Estimada Personal]]*Q13 -> 598526.74 | W14: =Table15313[[#This Row],[Faturamento Estimado]]*2% -> 11970.535 | X14: =Table15313[[#This Row],[Média Alunos Estimada Total Personal]]-(Table15313[[#This Row],[Tx. % Real Alunos não ativados]]*Table15313[[#This Row],[Média Alunos Estimada Total Personal]]) -> 14.25 | Y14: 0.05 | Z14: =Table15313[[#This Row],[Ticket Médio Aluno Personal]]*Table15313[[#This Row],[Média Real Alunos Ativos Personal]] -> 4093.6934 | AA14: =Table15313[[#This Row],[Média Real Alunos Ativos Personal]]*Table15313[[#This Row],[Personais Ativos Mês]] -> 2257.0031 | AB14: =Table15313[[#This Row],[Média Real por Personal]]*Q13 -> 568600.4 | AC14: =Table15313[[#This Row],[Faturamento Real Bruto]]*2% -> 11372.008 | AD14: =AD13+Table15313[[#This Row],[Faturamento Real Bruto]] -> 2542440 | AE14: =AE13+Table15313[[#This Row],[Receita MUVX (2%)]] -> 50848.799 | AF14: =Table15313[[#This Row],[Investimento no Mês (Growth) // 5%]]+AF13 -> 33681.541 | AG14: =Table15313[[#This Row],[Receita MUVX Acumulada]]/Table15313[[#This Row],[Investimento Acumulado]] -> 1.5096934 | AH14: =Table15313[[#This Row],[ROI]]+AH13 -> 16.833861
A15: 46388 | B15: =B76*0.05 -> 5000 | C15: =C76 -> 12.534736 | D15: =Table15313[[#This Row],[Investimento no Mês (Growth) // 5%]]/Table15313[[#This Row],[CPL - Tráfego (cadastro)]] -> 398.89154 | E15: =E76 -> 0.3 | F15: =Table15313[[#This Row],[Novos Cadastros LP]]*Table15313[[#This Row],[Tx. % Install]] -> 119.66746 | G15: =G76 -> 0.6 | H15: =Table15313[[#This Row],[Novos Installs no App]]*Table15313[[#This Row],[Tx % Ativações]] -> 71.800478 | I15: =I76 -> 0.3 | J15: =J76*20% -> 0 | K15: =K76 -> 0 | L15: =(Table15313[[#This Row],[Novos Personais Habilitados]]*Table15313[[#This Row],[Tx % de Conversão]])+(Table15313[[#This Row],[Cadastros Evento Presencial]]*Table15313[[#This Row],[Tx % Ativação Presencial]]) -> 21.540143 | M15: =Table15313[[#This Row],[Novos Personais Ativados]]+M14 -> 184.16534 | N15: =Table15313[[#This Row],[Investimento no Mês (Growth) // 5%]]/Table15313[[#This Row],[Novos Personais Ativados]] -> 232.12473 | O15: 0.03 | P15: =M14*Table15313[[#This Row],[Tx. % Churn]] -> 4.8787559 | Q15: =Table15313[[#This Row],[Personais Totais]]-Table15313[[#This Row],[Qtde. Churn no Mês]] -> 179.28658 | R15: 15 | S15: =S14*1.015 -> 291.58588 | T15: =Table15313[[#This Row],[Média Alunos Estimada Total Personal]]*Table15313[[#This Row],[Ticket Médio Aluno Personal]] -> 4373.7882 | U15: =Table15313[[#This Row],[Personais Ativos Mês]]+(Table15313[[#This Row],[Personais Ativos Mês]]*Table15313[[#This Row],[Média Alunos Estimada Total Personal]]) -> 2868.5853 | V15: =Table15313[[#This Row],[Média Faturamento Estimada Personal]]*Q14 -> 692747.62 | W15: =Table15313[[#This Row],[Faturamento Estimado]]*2% -> 13854.952 | X15: =Table15313[[#This Row],[Média Alunos Estimada Total Personal]]-(Table15313[[#This Row],[Tx. % Real Alunos não ativados]]*Table15313[[#This Row],[Média Alunos Estimada Total Personal]]) -> 14.25 | Y15: 0.05 | Z15: =Table15313[[#This Row],[Ticket Médio Aluno Personal]]*Table15313[[#This Row],[Média Real Alunos Ativos Personal]] -> 4155.0988 | AA15: =Table15313[[#This Row],[Média Real Alunos Ativos Personal]]*Table15313[[#This Row],[Personais Ativos Mês]] -> 2554.8338 | AB15: =Table15313[[#This Row],[Média Real por Personal]]*Q14 -> 658110.24 | AC15: =Table15313[[#This Row],[Faturamento Real Bruto]]*2% -> 13162.205 | AD15: =AD14+Table15313[[#This Row],[Faturamento Real Bruto]] -> 3200550.2 | AE15: =AE14+Table15313[[#This Row],[Receita MUVX (2%)]] -> 64011.004 | AF15: =Table15313[[#This Row],[Investimento no Mês (Growth) // 5%]]+AF14 -> 38681.541 | AG15: =Table15313[[#This Row],[Receita MUVX Acumulada]]/Table15313[[#This Row],[Investimento Acumulado]] -> 1.6548204 | AH15: =Table15313[[#This Row],[ROI]]+AH14 -> 18.488682
A16: 46419 | B16: =B77*0.05 -> 5000 | C16: =C77 -> 12.409388 | D16: =Table15313[[#This Row],[Investimento no Mês (Growth) // 5%]]/Table15313[[#This Row],[CPL - Tráfego (cadastro)]] -> 402.92075 | E16: =E77 -> 0.3 | F16: =Table15313[[#This Row],[Novos Cadastros LP]]*Table15313[[#This Row],[Tx. % Install]] -> 120.87622 | G16: =G77 -> 0.6 | H16: =Table15313[[#This Row],[Novos Installs no App]]*Table15313[[#This Row],[Tx % Ativações]] -> 72.525735 | I16: =I77 -> 0.3 | J16: =J77*20% -> 0 | K16: =K77 -> 0 | L16: =(Table15313[[#This Row],[Novos Personais Habilitados]]*Table15313[[#This Row],[Tx % de Conversão]])+(Table15313[[#This Row],[Cadastros Evento Presencial]]*Table15313[[#This Row],[Tx % Ativação Presencial]]) -> 21.75772 | M16: =Table15313[[#This Row],[Novos Personais Ativados]]+M15 -> 205.92306 | N16: =Table15313[[#This Row],[Investimento no Mês (Growth) // 5%]]/Table15313[[#This Row],[Novos Personais Ativados]] -> 229.80349 | O16: 0.06 | P16: =M15*Table15313[[#This Row],[Tx. % Churn]] -> 11.04992 | Q16: =Table15313[[#This Row],[Personais Totais]]-Table15313[[#This Row],[Qtde. Churn no Mês]] -> 194.87314 | R16: 15 | S16: =S15*1.015 -> 295.95967 | T16: =Table15313[[#This Row],[Média Alunos Estimada Total Personal]]*Table15313[[#This Row],[Ticket Médio Aluno Personal]] -> 4439.3951 | U16: =Table15313[[#This Row],[Personais Ativos Mês]]+(Table15313[[#This Row],[Personais Ativos Mês]]*Table15313[[#This Row],[Média Alunos Estimada Total Personal]]) -> 3117.9702 | V16: =Table15313[[#This Row],[Média Faturamento Estimada Personal]]*Q15 -> 795923.97 | W16: =Table15313[[#This Row],[Faturamento Estimado]]*2% -> 15918.479 | X16: =Table15313[[#This Row],[Média Alunos Estimada Total Personal]]-(Table15313[[#This Row],[Tx. % Real Alunos não ativados]]*Table15313[[#This Row],[Média Alunos Estimada Total Personal]]) -> 14.25 | Y16: 0.05 | Z16: =Table15313[[#This Row],[Ticket Médio Aluno Personal]]*Table15313[[#This Row],[Média Real Alunos Ativos Personal]] -> 4217.4253 | AA16: =Table15313[[#This Row],[Média Real Alunos Ativos Personal]]*Table15313[[#This Row],[Personais Ativos Mês]] -> 2776.9422 | AB16: =Table15313[[#This Row],[Média Real por Personal]]*Q15 -> 756127.77 | AC16: =Table15313[[#This Row],[Faturamento Real Bruto]]*2% -> 15122.555 | AD16: =AD15+Table15313[[#This Row],[Faturamento Real Bruto]] -> 3956678 | AE16: =AE15+Table15313[[#This Row],[Receita MUVX (2%)]] -> 79133.56 | AF16: =Table15313[[#This Row],[Investimento no Mês (Growth) // 5%]]+AF15 -> 43681.541 | AG16: =Table15313[[#This Row],[Receita MUVX Acumulada]]/Table15313[[#This Row],[Investimento Acumulado]] -> 1.8116018 | AH16: =Table15313[[#This Row],[ROI]]+AH15 -> 20.300284
B17: =SUBTOTAL(109,B3:B16) -> 43681.541 | C17: =SUBTOTAL(101,C3:C16) -> 13.105041 | D17: =SUBTOTAL(109,D3:D16) -> 4411.5457 | E17: =AVERAGE(E3:E16) -> 0.25428571 | F17: =Table15313[[#This Row],[Novos Cadastros LP]]*Table15313[[#This Row],[Tx. % Install]] -> 1121.7931 | G17: =G78 -> 0.53571429 | H17: =Table15313[[#This Row],[Novos Installs no App]]*Table15313[[#This Row],[Tx % Ativações]] -> 600.96057 | I17: =I78 -> 0.32857143 | L17: =SUBTOTAL(109,L3:L16) -> 205.92306 | M17: =AVERAGE(M3:M16) -> 86.640036 | N17: =SUBTOTAL(101,N3:N16) -> #DIV/0! | O17: =AVERAGE(O3:O16) -> 0.025714286 | P17: =SUBTOTAL(109,P3:P16) -> 32.485006 | Q17: =Q16 -> 194.87314 | R17: =AVERAGE(R3:R16) -> 15 | S17: =Table15313[[#This Row],[Média Faturamento Estimada Personal]]/Table15313[[#This Row],[Média Alunos Estimada Total Personal]] -> 251.90031 | T17: =SUBTOTAL(101,T3:T16) -> 3778.5047 | U17: =Table15313[[#This Row],[Personais Ativos Mês]]+(Table15313[[#This Row],[Personais Ativos Mês]]*Table15313[[#This Row],[Média Alunos Estimada Total Personal]]) -> 3117.9702 | V17: =SUBTOTAL(109,V3:V16) -> 4164924.2 | W17: =Table15313[[#This Row],[Faturamento Estimado]]*2% -> 83298.484 | Z17: =AVERAGE(Z4:Z16) -> 3678.2009 | AB17: =SUBTOTAL(109,AB3:AB16) -> 3956678 | AC17: =SUBTOTAL(109,AC3:AC16) -> 79133.56
G18: =G79 -> 0 | I18: =I79 -> 0
C19: % sob TAM Nacional | D19: =D17/130000 -> 0.033934967 | F19: =Table15313[[#This Row],[Novos Cadastros LP]]*Table15313[[#This Row],[Tx. % Install]] -> 0 | G19: =G80 -> 0 | H19: =Table15313[[#This Row],[Novos Installs no App]]*Table15313[[#This Row],[Tx % Ativações]] -> 0 | I19: =I80 -> 0 | P19: % sob TAM Nacional | Q19: =Q17/130000 -> 0.0014990241
C21: Top | E21: Install | G21: Ativação | I21: Conversão | N21: Cenário sem perdas operacionais | X21: Cenário com perdas operacionais
A22: Mês | B22: Investimento no Mês (Growth) // 15% | C22: CPL (cadastro) | D22: Novos Cadastros LP | E22: Tx. % Install | F22: Novos Installs no App | G22: Tx % Ativações | H22: Novos Personais Habilitados | I22: Tx % de Conversão | J22: Cadastros Evento Presencial | K22: Tx % Ativação Presencial | L22: Novos Personais Ativados | M22: Personais Totais | N22: CAC (ativação) | O22: Tx. % Churn | P22: Qtde. Churn no Mês | Q22: Personais Ativos Mês | R22: Média Alunos Estimada Total Personal | S22: Ticket Médio Aluno Personal | T22: Média Faturamento Estimada Personal | U22: Total Usuários Estimado | V22: Faturamento Estimado | W22: Receita MUVX Estimada (2%) | X22: Média Real Alunos Ativos Personal | Y22: Tx. % Real Alunos não ativados | Z22: Média Real por Personal | AA22: Total Real Usuários | AB22: Faturamento Real Bruto | AC22: Receita MUVX (2%) | AD22: Faturamento Real Acumulado | AE22: Receita MUVX Acumulada | AF22: Investimento Acumulado | AG22: ROI | AH22: ROI Acumulado
A23: 46023 | B23: =B64*0.15 -> 4700.739 | C23: =C64 -> 12 | D23: =Table153714[[#This Row],[Investimento no Mês (Growth) // 15%]]/Table153714[[#This Row],[CPL (cadastro)]] -> 391.72825 | E23: =E64 -> 0.06 | F23: =Table153714[[#This Row],[Novos Cadastros LP]]*Table153714[[#This Row],[Tx. % Install]] -> 23.503695 | G23: =G64 -> 0 | H23: =Table153714[[#This Row],[Novos Installs no App]]*Table153714[[#This Row],[Tx % Ativações]] -> 0 | I23: =I64 -> 0.7 | J23: =J64*50% -> 0 | K23: =K64 -> 0 | L23: =(Table153714[[#This Row],[Novos Personais Habilitados]]*Table153714[[#This Row],[Tx % de Conversão]])+(Table153714[[#This Row],[Cadastros Evento Presencial]]*Table153714[[#This Row],[Tx % Ativação Presencial]]) -> 0 | M23: =Table153714[[#This Row],[Novos Personais Ativados]] -> 0 | N23: =Table153714[[#This Row],[Investimento no Mês (Growth) // 15%]]/Table153714[[#This Row],[Novos Personais Ativados]] -> #DIV/0! | O23: 0 | P23: =Table153714[[#This Row],[Personais Totais]]*Table153714[[#This Row],[Tx. % Churn]] -> 0 | Q23: =Table153714[[#This Row],[Personais Totais]]-Table153714[[#This Row],[Qtde. Churn no Mês]] -> 0 | R23: 15 | S23: 0 | T23: 0 | U23: =Table153714[[#This Row],[Personais Ativos Mês]]+(Table153714[[#This Row],[Personais Ativos Mês]]*Table153714[[#This Row],[Média Alunos Estimada Total Personal]]) -> 0 | V23: 0 | W23: 0 | X23: =Table153714[[#This Row],[Média Alunos Estimada Total Personal]]-(Table153714[[#This Row],[Tx. % Real Alunos não ativados]]*Table153714[[#This Row],[Média Alunos Estimada Total Personal]]) -> 9.75 | Y23: 0.35 | Z23: =AB23/Q23 -> #DIV/0! | AA23: =Table153714[[#This Row],[Média Real Alunos Ativos Personal]]*Table153714[[#This Row],[Personais Ativos Mês]] -> 0 | AB23: 0 | AC23: 0 | AD23: =Table153714[[#This Row],[Faturamento Real Bruto]] -> 0 | AE23: 0 | AF23: =Table153714[[#This Row],[Investimento no Mês (Growth) // 15%]] -> 4700.739 | AG23: 0 | AH23: 0
A24: 46054 | B24: =B65*0.15 -> 793.8855 | C24: =C65 -> 14 | D24: 1031 | E24: =E65 -> 0.2 | F24: =Table153714[[#This Row],[Novos Cadastros LP]]*Table153714[[#This Row],[Tx. % Install]] -> 206.2 | G24: =G65 -> 0.5 | H24: =Table153714[[#This Row],[Novos Installs no App]]*Table153714[[#This Row],[Tx % Ativações]] -> 103.1 | I24: =I65 -> 0.3 | J24: =J65*50% -> 0 | K24: =K65 -> 0 | L24: =(Table153714[[#This Row],[Novos Personais Habilitados]]*Table153714[[#This Row],[Tx % de Conversão]])+(Table153714[[#This Row],[Cadastros Evento Presencial]]*Table153714[[#This Row],[Tx % Ativação Presencial]]) -> 30.93 | M24: =Table153714[[#This Row],[Novos Personais Ativados]]+M23 -> 30.93 | N24: =Table153714[[#This Row],[Investimento no Mês (Growth) // 15%]]/Table153714[[#This Row],[Novos Personais Ativados]] -> 25.667168 | O24: 0.02 | P24: =M23*Table153714[[#This Row],[Tx. % Churn]] -> 0 | Q24: =Table153714[[#This Row],[Personais Totais]]-Table153714[[#This Row],[Qtde. Churn no Mês]] -> 30.93 | R24: 15 | S24: 700 | T24: =Table153714[[#This Row],[Média Alunos Estimada Total Personal]]*Table153714[[#This Row],[Ticket Médio Aluno Personal]] -> 10500 | U24: =Table153714[[#This Row],[Personais Ativos Mês]]+(Table153714[[#This Row],[Personais Ativos Mês]]*Table153714[[#This Row],[Média Alunos Estimada Total Personal]]) -> 494.88 | V24: =Table153714[[#This Row],[Média Faturamento Estimada Personal]]*Q23 -> 0 | W24: =Table153714[[#This Row],[Faturamento Estimado]]*2% -> 0 | X24: =Table153714[[#This Row],[Média Alunos Estimada Total Personal]]-(Table153714[[#This Row],[Tx. % Real Alunos não ativados]]*Table153714[[#This Row],[Média Alunos Estimada Total Personal]]) -> 4.5 | Y24: 0.7 | Z24: =Table153714[[#This Row],[Ticket Médio Aluno Personal]]*Table153714[[#This Row],[Média Real Alunos Ativos Personal]] -> 3150 | AA24: =Table153714[[#This Row],[Média Real Alunos Ativos Personal]]*Table153714[[#This Row],[Personais Ativos Mês]] -> 139.185 | AB24: =Table153714[[#This Row],[Média Real por Personal]]*Q23 -> 0 | AC24: =Table153714[[#This Row],[Faturamento Real Bruto]]*2% -> 0 | AD24: =Table153714[[#This Row],[Faturamento Real Bruto]]+AB23 -> 0 | AE24: =Table153714[[#This Row],[Receita MUVX (2%)]]+AC23 -> 0 | AF24: =Table153714[[#This Row],[Investimento no Mês (Growth) // 15%]]+AF23 -> 5494.6245 | AG24: =Table153714[[#This Row],[Receita MUVX Acumulada]]/Table153714[[#This Row],[Investimento Acumulado]] -> 0 | AH24: =Table153714[[#This Row],[ROI]]+AH23 -> 0
A25: 46082 | B25: =B66*0.15 -> 150 | C25: =C66 -> 13.86 | D25: =Table153714[[#This Row],[Investimento no Mês (Growth) // 15%]]/Table153714[[#This Row],[CPL (cadastro)]] -> 10.822511 | E25: =E66 -> 0.2 | F25: =Table153714[[#This Row],[Novos Cadastros LP]]*Table153714[[#This Row],[Tx. % Install]] -> 2.1645022 | G25: =G66 -> 0.5 | H25: =Table153714[[#This Row],[Novos Installs no App]]*Table153714[[#This Row],[Tx % Ativações]] -> 1.0822511 | I25: =I66 -> 0.3 | J25: =J66*50% -> 0 | K25: =K66 -> 0 | L25: =(Table153714[[#This Row],[Novos Personais Habilitados]]*Table153714[[#This Row],[Tx % de Conversão]])+(Table153714[[#This Row],[Cadastros Evento Presencial]]*Table153714[[#This Row],[Tx % Ativação Presencial]]) -> 0.32467532 | M25: =Table153714[[#This Row],[Novos Personais Ativados]]+M24 -> 31.254675 | N25: =Table153714[[#This Row],[Investimento no Mês (Growth) // 15%]]/Table153714[[#This Row],[Novos Personais Ativados]] -> 462 | O25: 0.03 | P25: =M24*Table153714[[#This Row],[Tx. % Churn]] -> 0.9279 | Q25: =Table153714[[#This Row],[Personais Totais]]-Table153714[[#This Row],[Qtde. Churn no Mês]] -> 30.326775 | R25: 15 | S25: =S24*1.005 -> 703.5 | T25: =Table153714[[#This Row],[Média Alunos Estimada Total Personal]]*Table153714[[#This Row],[Ticket Médio Aluno Personal]] -> 10552.5 | U25: =Table153714[[#This Row],[Personais Ativos Mês]]+(Table153714[[#This Row],[Personais Ativos Mês]]*Table153714[[#This Row],[Média Alunos Estimada Total Personal]]) -> 485.22841 | V25: =Table153714[[#This Row],[Média Faturamento Estimada Personal]]*Q24 -> 326388.82 | W25: =Table153714[[#This Row],[Faturamento Estimado]]*2% -> 6527.7765 | X25: =Table153714[[#This Row],[Média Alunos Estimada Total Personal]]-(Table153714[[#This Row],[Tx. % Real Alunos não ativados]]*Table153714[[#This Row],[Média Alunos Estimada Total Personal]]) -> 14.25 | Y25: 0.05 | Z25: =Table153714[[#This Row],[Ticket Médio Aluno Personal]]*Table153714[[#This Row],[Média Real Alunos Ativos Personal]] -> 10024.875 | AA25: =Table153714[[#This Row],[Média Real Alunos Ativos Personal]]*Table153714[[#This Row],[Personais Ativos Mês]] -> 432.15655 | AB25: =Table153714[[#This Row],[Média Real por Personal]]*Q24 -> 310069.38 | AC25: =Table153714[[#This Row],[Faturamento Real Bruto]]*2% -> 6201.3877 | AD25: =AD24+Table153714[[#This Row],[Faturamento Real Bruto]] -> 310069.38 | AE25: =AE24+Table153714[[#This Row],[Receita MUVX (2%)]] -> 6201.3877 | AF25: =Table153714[[#This Row],[Investimento no Mês (Growth) // 15%]]+AF24 -> 5644.6245 | AG25: =Table153714[[#This Row],[Receita MUVX Acumulada]]/Table153714[[#This Row],[Investimento Acumulado]] -> 1.098636 | AH25: =Table153714[[#This Row],[ROI]]+AH24 -> 1.098636
A26: 46113 | B26: =B67*0.15 -> 150 | C26: =C67 -> 13.7214 | D26: =Table153714[[#This Row],[Investimento no Mês (Growth) // 15%]]/Table153714[[#This Row],[CPL (cadastro)]] -> 10.931829 | E26: =E67 -> 0.2 | F26: =Table153714[[#This Row],[Novos Cadastros LP]]*Table153714[[#This Row],[Tx. % Install]] -> 2.1863658 | G26: =G67 -> 0.5 | H26: =Table153714[[#This Row],[Novos Installs no App]]*Table153714[[#This Row],[Tx % Ativações]] -> 1.0931829 | I26: =I67 -> 0.3 | J26: =J67*50% -> 0 | K26: =K67 -> 0 | L26: =(Table153714[[#This Row],[Novos Personais Habilitados]]*Table153714[[#This Row],[Tx % de Conversão]])+(Table153714[[#This Row],[Cadastros Evento Presencial]]*Table153714[[#This Row],[Tx % Ativação Presencial]]) -> 0.32795487 | M26: =Table153714[[#This Row],[Novos Personais Ativados]]+M25 -> 31.58263 | N26: =Table153714[[#This Row],[Investimento no Mês (Growth) // 15%]]/Table153714[[#This Row],[Novos Personais Ativados]] -> 457.38 | O26: 0.02 | P26: =M25*Table153714[[#This Row],[Tx. % Churn]] -> 0.62509351 | Q26: =Table153714[[#This Row],[Personais Totais]]-Table153714[[#This Row],[Qtde. Churn no Mês]] -> 30.957537 | R26: 15 | S26: =S25*1.015 -> 714.0525 | T26: =Table153714[[#This Row],[Média Alunos Estimada Total Personal]]*Table153714[[#This Row],[Ticket Médio Aluno Personal]] -> 10710.787 | U26: =Table153714[[#This Row],[Personais Ativos Mês]]+(Table153714[[#This Row],[Personais Ativos Mês]]*Table153714[[#This Row],[Média Alunos Estimada Total Personal]]) -> 495.32059 | V26: =Table153714[[#This Row],[Média Faturamento Estimada Personal]]*Q25 -> 324823.65 | W26: =Table153714[[#This Row],[Faturamento Estimado]]*2% -> 6496.4729 | X26: =Table153714[[#This Row],[Média Alunos Estimada Total Personal]]-(Table153714[[#This Row],[Tx. % Real Alunos não ativados]]*Table153714[[#This Row],[Média Alunos Estimada Total Personal]]) -> 14.25 | Y26: 0.05 | Z26: =Table153714[[#This Row],[Ticket Médio Aluno Personal]]*Table153714[[#This Row],[Média Real Alunos Ativos Personal]] -> 10175.248 | AA26: =Table153714[[#This Row],[Média Real Alunos Ativos Personal]]*Table153714[[#This Row],[Personais Ativos Mês]] -> 441.1449 | AB26: =Table153714[[#This Row],[Média Real por Personal]]*Q25 -> 308582.46 | AC26: =Table153714[[#This Row],[Faturamento Real Bruto]]*2% -> 6171.6493 | AD26: =AD25+Table153714[[#This Row],[Faturamento Real Bruto]] -> 618651.85 | AE26: =AE25+Table153714[[#This Row],[Receita MUVX (2%)]] -> 12373.037 | AF26: =Table153714[[#This Row],[Investimento no Mês (Growth) // 15%]]+AF25 -> 5794.6245 | AG26: =Table153714[[#This Row],[Receita MUVX Acumulada]]/Table153714[[#This Row],[Investimento Acumulado]] -> 2.1352612 | AH26: =Table153714[[#This Row],[ROI]]+AH25 -> 3.2338972
A27: 46143 | B27: =B68*0.15 -> 750 | C27: =C68 -> 13.584186 | D27: =Table153714[[#This Row],[Investimento no Mês (Growth) // 15%]]/Table153714[[#This Row],[CPL (cadastro)]] -> 55.211258 | E27: =E68 -> 0.2 | F27: =Table153714[[#This Row],[Novos Cadastros LP]]*Table153714[[#This Row],[Tx. % Install]] -> 11.042252 | G27: =G68 -> 0.6 | H27: =Table153714[[#This Row],[Novos Installs no App]]*Table153714[[#This Row],[Tx % Ativações]] -> 6.625351 | I27: =I68 -> 0.3 | J27: =J68*50% -> 0 | K27: =K68 -> 0 | L27: =(Table153714[[#This Row],[Novos Personais Habilitados]]*Table153714[[#This Row],[Tx % de Conversão]])+(Table153714[[#This Row],[Cadastros Evento Presencial]]*Table153714[[#This Row],[Tx % Ativação Presencial]]) -> 1.9876053 | M27: =Table153714[[#This Row],[Novos Personais Ativados]]+M26 -> 33.570235 | N27: =Table153714[[#This Row],[Investimento no Mês (Growth) // 15%]]/Table153714[[#This Row],[Novos Personais Ativados]] -> 377.3385 | O27: 0.02 | P27: =M26*Table153714[[#This Row],[Tx. % Churn]] -> 0.6316526 | Q27: =Table153714[[#This Row],[Personais Totais]]-Table153714[[#This Row],[Qtde. Churn no Mês]] -> 32.938583 | R27: 15 | S27: =S26*1.015 -> 724.76329 | T27: =Table153714[[#This Row],[Média Alunos Estimada Total Personal]]*Table153714[[#This Row],[Ticket Médio Aluno Personal]] -> 10871.449 | U27: =Table153714[[#This Row],[Personais Ativos Mês]]+(Table153714[[#This Row],[Personais Ativos Mês]]*Table153714[[#This Row],[Média Alunos Estimada Total Personal]]) -> 527.01733 | V27: =Table153714[[#This Row],[Média Faturamento Estimada Personal]]*Q26 -> 336553.29 | W27: =Table153714[[#This Row],[Faturamento Estimado]]*2% -> 6731.0658 | X27: =Table153714[[#This Row],[Média Alunos Estimada Total Personal]]-(Table153714[[#This Row],[Tx. % Real Alunos não ativados]]*Table153714[[#This Row],[Média Alunos Estimada Total Personal]]) -> 14.25 | Y27: 0.05 | Z27: =Table153714[[#This Row],[Ticket Médio Aluno Personal]]*Table153714[[#This Row],[Média Real Alunos Ativos Personal]] -> 10327.877 | AA27: =Table153714[[#This Row],[Média Real Alunos Ativos Personal]]*Table153714[[#This Row],[Personais Ativos Mês]] -> 469.37481 | AB27: =Table153714[[#This Row],[Média Real por Personal]]*Q26 -> 319725.63 | AC27: =Table153714[[#This Row],[Faturamento Real Bruto]]*2% -> 6394.5125 | AD27: =AD26+Table153714[[#This Row],[Faturamento Real Bruto]] -> 938377.47 | AE27: =AE26+Table153714[[#This Row],[Receita MUVX (2%)]] -> 18767.549 | AF27: =Table153714[[#This Row],[Investimento no Mês (Growth) // 15%]]+AF26 -> 6544.6245 | AG27: =Table153714[[#This Row],[Receita MUVX Acumulada]]/Table153714[[#This Row],[Investimento Acumulado]] -> 2.8676282 | AH27: =Table153714[[#This Row],[ROI]]+AH26 -> 6.1015254
A28: 46174 | B28: =B69*0.15 -> 4500 | C28: =C69 -> 13.448344 | D28: =Table153714[[#This Row],[Investimento no Mês (Growth) // 15%]]/Table153714[[#This Row],[CPL (cadastro)]] -> 334.61369 | E28: 0.3 | F28: =Table153714[[#This Row],[Novos Cadastros LP]]*Table153714[[#This Row],[Tx. % Install]] -> 100.38411 | G28: =G69 -> 0.6 | H28: =Table153714[[#This Row],[Novos Installs no App]]*Table153714[[#This Row],[Tx % Ativações]] -> 60.230463 | I28: =I69 -> 0.3 | J28: =J69*50% -> 0 | K28: =K69 -> 0 | L28: =(Table153714[[#This Row],[Novos Personais Habilitados]]*Table153714[[#This Row],[Tx % de Conversão]])+(Table153714[[#This Row],[Cadastros Evento Presencial]]*Table153714[[#This Row],[Tx % Ativação Presencial]]) -> 18.069139 | M28: =Table153714[[#This Row],[Novos Personais Ativados]]+M27 -> 51.639375 | N28: =Table153714[[#This Row],[Investimento no Mês (Growth) // 15%]]/Table153714[[#This Row],[Novos Personais Ativados]] -> 249.04341 | O28: 0.04 | P28: =M27*Table153714[[#This Row],[Tx. % Churn]] -> 1.3428094 | Q28: =Table153714[[#This Row],[Personais Totais]]-Table153714[[#This Row],[Qtde. Churn no Mês]] -> 50.296565 | R28: 15 | S28: =S27*1.015 -> 735.63474 | T28: =Table153714[[#This Row],[Média Alunos Estimada Total Personal]]*Table153714[[#This Row],[Ticket Médio Aluno Personal]] -> 11034.521 | U28: =Table153714[[#This Row],[Personais Ativos Mês]]+(Table153714[[#This Row],[Personais Ativos Mês]]*Table153714[[#This Row],[Média Alunos Estimada Total Personal]]) -> 804.74504 | V28: =Table153714[[#This Row],[Média Faturamento Estimada Personal]]*Q27 -> 363461.49 | W28: =Table153714[[#This Row],[Faturamento Estimado]]*2% -> 7269.2297 | X28: =Table153714[[#This Row],[Média Alunos Estimada Total Personal]]-(Table153714[[#This Row],[Tx. % Real Alunos não ativados]]*Table153714[[#This Row],[Média Alunos Estimada Total Personal]]) -> 14.25 | Y28: 0.05 | Z28: =Table153714[[#This Row],[Ticket Médio Aluno Personal]]*Table153714[[#This Row],[Média Real Alunos Ativos Personal]] -> 10482.795 | AA28: =Table153714[[#This Row],[Média Real Alunos Ativos Personal]]*Table153714[[#This Row],[Personais Ativos Mês]] -> 716.72605 | AB28: =Table153714[[#This Row],[Média Real por Personal]]*Q27 -> 345288.41 | AC28: =Table153714[[#This Row],[Faturamento Real Bruto]]*2% -> 6905.7682 | AD28: =AD27+Table153714[[#This Row],[Faturamento Real Bruto]] -> 1283665.9 | AE28: =AE27+Table153714[[#This Row],[Receita MUVX (2%)]] -> 25673.318 | AF28: =Table153714[[#This Row],[Investimento no Mês (Growth) // 15%]]+AF27 -> 11044.624 | AG28: =Table153714[[#This Row],[Receita MUVX Acumulada]]/Table153714[[#This Row],[Investimento Acumulado]] -> 2.324508 | AH28: =Table153714[[#This Row],[ROI]]+AH27 -> 8.4260333
A29: 46204 | B29: =B70*0.15 -> 15000 | C29: =C70 -> 13.313861 | D29: =Table153714[[#This Row],[Investimento no Mês (Growth) // 15%]]/Table153714[[#This Row],[CPL (cadastro)]] -> 1126.6454 | E29: =E70 -> 0.3 | F29: =Table153714[[#This Row],[Novos Cadastros LP]]*Table153714[[#This Row],[Tx. % Install]] -> 337.99362 | G29: =G70 -> 0.6 | H29: =Table153714[[#This Row],[Novos Installs no App]]*Table153714[[#This Row],[Tx % Ativações]] -> 202.79617 | I29: =I70 -> 0.3 | J29: =J70*50% -> 0 | K29: =K70 -> 0.2 | L29: =(Table153714[[#This Row],[Novos Personais Habilitados]]*Table153714[[#This Row],[Tx % de Conversão]])+(Table153714[[#This Row],[Cadastros Evento Presencial]]*Table153714[[#This Row],[Tx % Ativação Presencial]]) -> 60.838852 | M29: =Table153714[[#This Row],[Novos Personais Ativados]]+M28 -> 112.47823 | N29: =Table153714[[#This Row],[Investimento no Mês (Growth) // 15%]]/Table153714[[#This Row],[Novos Personais Ativados]] -> 246.55298 | O29: 0.02 | P29: =M28*Table153714[[#This Row],[Tx. % Churn]] -> 1.0327875 | Q29: =Table153714[[#This Row],[Personais Totais]]-Table153714[[#This Row],[Qtde. Churn no Mês]] -> 111.44544 | R29: 15 | S29: =S28*1.015 -> 746.66926 | T29: =Table153714[[#This Row],[Média Alunos Estimada Total Personal]]*Table153714[[#This Row],[Ticket Médio Aluno Personal]] -> 11200.039 | U29: =Table153714[[#This Row],[Personais Ativos Mês]]+(Table153714[[#This Row],[Personais Ativos Mês]]*Table153714[[#This Row],[Média Alunos Estimada Total Personal]]) -> 1783.127 | V29: =Table153714[[#This Row],[Média Faturamento Estimada Personal]]*Q28 -> 563323.48 | W29: =Table153714[[#This Row],[Faturamento Estimado]]*2% -> 11266.47 | X29: =Table153714[[#This Row],[Média Alunos Estimada Total Personal]]-(Table153714[[#This Row],[Tx. % Real Alunos não ativados]]*Table153714[[#This Row],[Média Alunos Estimada Total Personal]]) -> 14.25 | Y29: 0.05 | Z29: =Table153714[[#This Row],[Ticket Médio Aluno Personal]]*Table153714[[#This Row],[Média Real Alunos Ativos Personal]] -> 10640.037 | AA29: =Table153714[[#This Row],[Média Real Alunos Ativos Personal]]*Table153714[[#This Row],[Personais Ativos Mês]] -> 1588.0975 | AB29: =Table153714[[#This Row],[Média Real por Personal]]*Q28 -> 535157.31 | AC29: =Table153714[[#This Row],[Faturamento Real Bruto]]*2% -> 10703.146 | AD29: =AD28+Table153714[[#This Row],[Faturamento Real Bruto]] -> 1818823.2 | AE29: =AE28+Table153714[[#This Row],[Receita MUVX (2%)]] -> 36376.464 | AF29: =Table153714[[#This Row],[Investimento no Mês (Growth) // 15%]]+AF28 -> 26044.624 | AG29: =Table153714[[#This Row],[Receita MUVX Acumulada]]/Table153714[[#This Row],[Investimento Acumulado]] -> 1.3966976 | AH29: =Table153714[[#This Row],[ROI]]+AH28 -> 9.8227309
A30: 46235 | B30: =B71*0.15 -> 15000 | C30: =C71 -> 13.180722 | D30: =Table153714[[#This Row],[Investimento no Mês (Growth) // 15%]]/Table153714[[#This Row],[CPL (cadastro)]] -> 1138.0257 | E30: =E71 -> 0.3 | F30: =Table153714[[#This Row],[Novos Cadastros LP]]*Table153714[[#This Row],[Tx. % Install]] -> 341.4077 | G30: =G71 -> 0.6 | H30: =Table153714[[#This Row],[Novos Installs no App]]*Table153714[[#This Row],[Tx % Ativações]] -> 204.84462 | I30: =I71 -> 0.3 | J30: =J71*50% -> 0 | K30: =K71 -> 0 | L30: =(Table153714[[#This Row],[Novos Personais Habilitados]]*Table153714[[#This Row],[Tx % de Conversão]])+(Table153714[[#This Row],[Cadastros Evento Presencial]]*Table153714[[#This Row],[Tx % Ativação Presencial]]) -> 61.453386 | M30: =Table153714[[#This Row],[Novos Personais Ativados]]+M29 -> 173.93161 | N30: =Table153714[[#This Row],[Investimento no Mês (Growth) // 15%]]/Table153714[[#This Row],[Novos Personais Ativados]] -> 244.08745 | O30: 0.02 | P30: =M29*Table153714[[#This Row],[Tx. % Churn]] -> 2.2495645 | Q30: =Table153714[[#This Row],[Personais Totais]]-Table153714[[#This Row],[Qtde. Churn no Mês]] -> 171.68205 | R30: 15 | S30: =S29*1.015 -> 757.8693 | T30: =Table153714[[#This Row],[Média Alunos Estimada Total Personal]]*Table153714[[#This Row],[Ticket Médio Aluno Personal]] -> 11368.039 | U30: =Table153714[[#This Row],[Personais Ativos Mês]]+(Table153714[[#This Row],[Personais Ativos Mês]]*Table153714[[#This Row],[Média Alunos Estimada Total Personal]]) -> 2746.9128 | V30: =Table153714[[#This Row],[Média Faturamento Estimada Personal]]*Q29 -> 1266916.1 | W30: =Table153714[[#This Row],[Faturamento Estimado]]*2% -> 25338.323 | X30: =Table153714[[#This Row],[Média Alunos Estimada Total Personal]]-(Table153714[[#This Row],[Tx. % Real Alunos não ativados]]*Table153714[[#This Row],[Média Alunos Estimada Total Personal]]) -> 14.25 | Y30: 0.05 | Z30: =Table153714[[#This Row],[Ticket Médio Aluno Personal]]*Table153714[[#This Row],[Média Real Alunos Ativos Personal]] -> 10799.637 | AA30: =Table153714[[#This Row],[Média Real Alunos Ativos Personal]]*Table153714[[#This Row],[Personais Ativos Mês]] -> 2446.4692 | AB30: =Table153714[[#This Row],[Média Real por Personal]]*Q29 -> 1203570.3 | AC30: =Table153714[[#This Row],[Faturamento Real Bruto]]*2% -> 24071.407 | AD30: =AD29+Table153714[[#This Row],[Faturamento Real Bruto]] -> 3022393.5 | AE30: =AE29+Table153714[[#This Row],[Receita MUVX (2%)]] -> 60447.871 | AF30: =Table153714[[#This Row],[Investimento no Mês (Growth) // 15%]]+AF29 -> 41044.624 | AG30: =Table153714[[#This Row],[Receita MUVX Acumulada]]/Table153714[[#This Row],[Investimento Acumulado]] -> 1.4727354 | AH30: =Table153714[[#This Row],[ROI]]+AH29 -> 11.295466
A31: 46266 | B31: =B72*0.15 -> 15000 | C31: =C72 -> 13.048915 | D31: =Table153714[[#This Row],[Investimento no Mês (Growth) // 15%]]/Table153714[[#This Row],[CPL (cadastro)]] -> 1149.5209 | E31: =E72 -> 0.3 | F31: =Table153714[[#This Row],[Novos Cadastros LP]]*Table153714[[#This Row],[Tx. % Install]] -> 344.85626 | G31: =G72 -> 0.6 | H31: =Table153714[[#This Row],[Novos Installs no App]]*Table153714[[#This Row],[Tx % Ativações]] -> 206.91376 | I31: =I72 -> 0.3 | J31: =J72*50% -> 0 | K31: =K72 -> 0 | L31: =(Table153714[[#This Row],[Novos Personais Habilitados]]*Table153714[[#This Row],[Tx % de Conversão]])+(Table153714[[#This Row],[Cadastros Evento Presencial]]*Table153714[[#This Row],[Tx % Ativação Presencial]]) -> 62.074127 | M31: =Table153714[[#This Row],[Novos Personais Ativados]]+M30 -> 236.00574 | N31: =Table153714[[#This Row],[Investimento no Mês (Growth) // 15%]]/Table153714[[#This Row],[Novos Personais Ativados]] -> 241.64657 | O31: 0.02 | P31: =M30*Table153714[[#This Row],[Tx. % Churn]] -> 3.4786322 | Q31: =Table153714[[#This Row],[Personais Totais]]-Table153714[[#This Row],[Qtde. Churn no Mês]] -> 232.52711 | R31: 15 | S31: =S30*1.015 -> 769.23734 | T31: =Table153714[[#This Row],[Média Alunos Estimada Total Personal]]*Table153714[[#This Row],[Ticket Médio Aluno Personal]] -> 11538.56 | U31: =Table153714[[#This Row],[Personais Ativos Mês]]+(Table153714[[#This Row],[Personais Ativos Mês]]*Table153714[[#This Row],[Média Alunos Estimada Total Personal]]) -> 3720.4337 | V31: =Table153714[[#This Row],[Média Faturamento Estimada Personal]]*Q30 -> 1980963.6 | W31: =Table153714[[#This Row],[Faturamento Estimado]]*2% -> 39619.272 | X31: =Table153714[[#This Row],[Média Alunos Estimada Total Personal]]-(Table153714[[#This Row],[Tx. % Real Alunos não ativados]]*Table153714[[#This Row],[Média Alunos Estimada Total Personal]]) -> 14.25 | Y31: 0.05 | Z31: =Table153714[[#This Row],[Ticket Médio Aluno Personal]]*Table153714[[#This Row],[Média Real Alunos Ativos Personal]] -> 10961.632 | AA31: =Table153714[[#This Row],[Média Real Alunos Ativos Personal]]*Table153714[[#This Row],[Personais Ativos Mês]] -> 3313.5113 | AB31: =Table153714[[#This Row],[Média Real por Personal]]*Q30 -> 1881915.4 | AC31: =Table153714[[#This Row],[Faturamento Real Bruto]]*2% -> 37638.309 | AD31: =AD30+Table153714[[#This Row],[Faturamento Real Bruto]] -> 4904309 | AE31: =AE30+Table153714[[#This Row],[Receita MUVX (2%)]] -> 98086.179 | AF31: =Table153714[[#This Row],[Investimento no Mês (Growth) // 15%]]+AF30 -> 56044.624 | AG31: =Table153714[[#This Row],[Receita MUVX Acumulada]]/Table153714[[#This Row],[Investimento Acumulado]] -> 1.7501443 | AH31: =Table153714[[#This Row],[ROI]]+AH30 -> 13.045611
A32: 46296 | B32: =B73*0.15 -> 15000 | C32: =C73 -> 12.918426 | D32: =Table153714[[#This Row],[Investimento no Mês (Growth) // 15%]]/Table153714[[#This Row],[CPL (cadastro)]] -> 1161.1322 | E32: =E73 -> 0.3 | F32: =Table153714[[#This Row],[Novos Cadastros LP]]*Table153714[[#This Row],[Tx. % Install]] -> 348.33966 | G32: =G73 -> 0.6 | H32: =Table153714[[#This Row],[Novos Installs no App]]*Table153714[[#This Row],[Tx % Ativações]] -> 209.00379 | I32: =I73 -> 0.3 | J32: =J73*50% -> 0 | K32: =K73 -> 0 | L32: =(Table153714[[#This Row],[Novos Personais Habilitados]]*Table153714[[#This Row],[Tx % de Conversão]])+(Table153714[[#This Row],[Cadastros Evento Presencial]]*Table153714[[#This Row],[Tx % Ativação Presencial]]) -> 62.701138 | M32: =Table153714[[#This Row],[Novos Personais Ativados]]+M31 -> 298.70688 | N32: =Table153714[[#This Row],[Investimento no Mês (Growth) // 15%]]/Table153714[[#This Row],[Novos Personais Ativados]] -> 239.23011 | O32: 0.03 | P32: =M31*Table153714[[#This Row],[Tx. % Churn]] -> 7.0801722 | Q32: =Table153714[[#This Row],[Personais Totais]]-Table153714[[#This Row],[Qtde. Churn no Mês]] -> 291.62671 | R32: 15 | S32: =S31*1.015 -> 780.7759 | T32: =Table153714[[#This Row],[Média Alunos Estimada Total Personal]]*Table153714[[#This Row],[Ticket Médio Aluno Personal]] -> 11711.638 | U32: =Table153714[[#This Row],[Personais Ativos Mês]]+(Table153714[[#This Row],[Personais Ativos Mês]]*Table153714[[#This Row],[Média Alunos Estimada Total Personal]]) -> 4666.0273 | V32: =Table153714[[#This Row],[Média Faturamento Estimada Personal]]*Q31 -> 2723273.4 | W32: =Table153714[[#This Row],[Faturamento Estimado]]*2% -> 54465.468 | X32: =Table153714[[#This Row],[Média Alunos Estimada Total Personal]]-(Table153714[[#This Row],[Tx. % Real Alunos não ativados]]*Table153714[[#This Row],[Média Alunos Estimada Total Personal]]) -> 14.25 | Y32: 0.05 | Z32: =Table153714[[#This Row],[Ticket Médio Aluno Personal]]*Table153714[[#This Row],[Média Real Alunos Ativos Personal]] -> 11126.057 | AA32: =Table153714[[#This Row],[Média Real Alunos Ativos Personal]]*Table153714[[#This Row],[Personais Ativos Mês]] -> 4155.6806 | AB32: =Table153714[[#This Row],[Média Real por Personal]]*Q31 -> 2587109.7 | AC32: =Table153714[[#This Row],[Faturamento Real Bruto]]*2% -> 51742.195 | AD32: =AD31+Table153714[[#This Row],[Faturamento Real Bruto]] -> 7491418.7 | AE32: =AE31+Table153714[[#This Row],[Receita MUVX (2%)]] -> 149828.37 | AF32: =Table153714[[#This Row],[Investimento no Mês (Growth) // 15%]]+AF31 -> 71044.625 | AG32: =Table153714[[#This Row],[Receita MUVX Acumulada]]/Table153714[[#This Row],[Investimento Acumulado]] -> 2.1089333 | AH32: =Table153714[[#This Row],[ROI]]+AH31 -> 15.154544
A33: 46327 | B33: =B74*0.15 -> 15000 | C33: =C74 -> 12.789241 | D33: =Table153714[[#This Row],[Investimento no Mês (Growth) // 15%]]/Table153714[[#This Row],[CPL (cadastro)]] -> 1172.8608 | E33: =E74 -> 0.3 | F33: =Table153714[[#This Row],[Novos Cadastros LP]]*Table153714[[#This Row],[Tx. % Install]] -> 351.85824 | G33: =G74 -> 0.6 | H33: =Table153714[[#This Row],[Novos Installs no App]]*Table153714[[#This Row],[Tx % Ativações]] -> 211.11494 | I33: =I74 -> 0.3 | J33: =J74*50% -> 0 | K33: =K74 -> 0 | L33: =(Table153714[[#This Row],[Novos Personais Habilitados]]*Table153714[[#This Row],[Tx % de Conversão]])+(Table153714[[#This Row],[Cadastros Evento Presencial]]*Table153714[[#This Row],[Tx % Ativação Presencial]]) -> 63.334483 | M33: =Table153714[[#This Row],[Novos Personais Ativados]]+M32 -> 362.04136 | N33: =Table153714[[#This Row],[Investimento no Mês (Growth) // 15%]]/Table153714[[#This Row],[Novos Personais Ativados]] -> 236.8378 | O33: 0.02 | P33: =M32*Table153714[[#This Row],[Tx. % Churn]] -> 5.9741376 | Q33: =Table153714[[#This Row],[Personais Totais]]-Table153714[[#This Row],[Qtde. Churn no Mês]] -> 356.06722 | R33: 15 | S33: =S32*1.015 -> 792.48753 | T33: =Table153714[[#This Row],[Média Alunos Estimada Total Personal]]*Table153714[[#This Row],[Ticket Médio Aluno Personal]] -> 11887.313 | U33: =Table153714[[#This Row],[Personais Ativos Mês]]+(Table153714[[#This Row],[Personais Ativos Mês]]*Table153714[[#This Row],[Média Alunos Estimada Total Personal]]) -> 5697.0756 | V33: =Table153714[[#This Row],[Média Faturamento Estimada Personal]]*Q32 -> 3466657.9 | W33: =Table153714[[#This Row],[Faturamento Estimado]]*2% -> 69333.159 | X33: =Table153714[[#This Row],[Média Alunos Estimada Total Personal]]-(Table153714[[#This Row],[Tx. % Real Alunos não ativados]]*Table153714[[#This Row],[Média Alunos Estimada Total Personal]]) -> 14.25 | Y33: 0.05 | Z33: =Table153714[[#This Row],[Ticket Médio Aluno Personal]]*Table153714[[#This Row],[Média Real Alunos Ativos Personal]] -> 11292.947 | AA33: =Table153714[[#This Row],[Média Real Alunos Ativos Personal]]*Table153714[[#This Row],[Personais Ativos Mês]] -> 5073.9579 | AB33: =Table153714[[#This Row],[Média Real por Personal]]*Q32 -> 3293325 | AC33: =Table153714[[#This Row],[Faturamento Real Bruto]]*2% -> 65866.501 | AD33: =AD32+Table153714[[#This Row],[Faturamento Real Bruto]] -> 10784744 | AE33: =AE32+Table153714[[#This Row],[Receita MUVX (2%)]] -> 215694.87 | AF33: =Table153714[[#This Row],[Investimento no Mês (Growth) // 15%]]+AF32 -> 86044.625 | AG33: =Table153714[[#This Row],[Receita MUVX Acumulada]]/Table153714[[#This Row],[Investimento Acumulado]] -> 2.5067792 | AH33: =Table153714[[#This Row],[ROI]]+AH32 -> 17.661323
A34: 46357 | B34: =B75*0.15 -> 15000 | C34: =C75 -> 12.661349 | D34: =Table153714[[#This Row],[Investimento no Mês (Growth) // 15%]]/Table153714[[#This Row],[CPL (cadastro)]] -> 1184.7079 | E34: =E75 -> 0.3 | F34: =Table153714[[#This Row],[Novos Cadastros LP]]*Table153714[[#This Row],[Tx. % Install]] -> 355.41236 | G34: =G75 -> 0.6 | H34: =Table153714[[#This Row],[Novos Installs no App]]*Table153714[[#This Row],[Tx % Ativações]] -> 213.24742 | I34: =I75 -> 0.3 | J34: =J75*50% -> 0 | K34: =K75 -> 0 | L34: =(Table153714[[#This Row],[Novos Personais Habilitados]]*Table153714[[#This Row],[Tx % de Conversão]])+(Table153714[[#This Row],[Cadastros Evento Presencial]]*Table153714[[#This Row],[Tx % Ativação Presencial]]) -> 63.974226 | M34: =Table153714[[#This Row],[Novos Personais Ativados]]+M33 -> 426.01559 | N34: =Table153714[[#This Row],[Investimento no Mês (Growth) // 15%]]/Table153714[[#This Row],[Novos Personais Ativados]] -> 234.46943 | O34: 0.03 | P34: =M33*Table153714[[#This Row],[Tx. % Churn]] -> 10.861241 | Q34: =Table153714[[#This Row],[Personais Totais]]-Table153714[[#This Row],[Qtde. Churn no Mês]] -> 415.15435 | R34: 15 | S34: =S33*1.015 -> 804.37485 | T34: =Table153714[[#This Row],[Média Alunos Estimada Total Personal]]*Table153714[[#This Row],[Ticket Médio Aluno Personal]] -> 12065.623 | U34: =Table153714[[#This Row],[Personais Ativos Mês]]+(Table153714[[#This Row],[Personais Ativos Mês]]*Table153714[[#This Row],[Média Alunos Estimada Total Personal]]) -> 6642.4695 | V34: =Table153714[[#This Row],[Média Faturamento Estimada Personal]]*Q33 -> 4296172.8 | W34: =Table153714[[#This Row],[Faturamento Estimado]]*2% -> 85923.456 | X34: =Table153714[[#This Row],[Média Alunos Estimada Total Personal]]-(Table153714[[#This Row],[Tx. % Real Alunos não ativados]]*Table153714[[#This Row],[Média Alunos Estimada Total Personal]]) -> 14.25 | Y34: 0.05 | Z34: =Table153714[[#This Row],[Ticket Médio Aluno Personal]]*Table153714[[#This Row],[Média Real Alunos Ativos Personal]] -> 11462.342 | AA34: =Table153714[[#This Row],[Média Real Alunos Ativos Personal]]*Table153714[[#This Row],[Personais Ativos Mês]] -> 5915.9494 | AB34: =Table153714[[#This Row],[Média Real por Personal]]*Q33 -> 4081364.1 | AC34: =Table153714[[#This Row],[Faturamento Real Bruto]]*2% -> 81627.283 | AD34: =AD33+Table153714[[#This Row],[Faturamento Real Bruto]] -> 14866108 | AE34: =AE33+Table153714[[#This Row],[Receita MUVX (2%)]] -> 297322.16 | AF34: =Table153714[[#This Row],[Investimento no Mês (Growth) // 15%]]+AF33 -> 101044.62 | AG34: =Table153714[[#This Row],[Receita MUVX Acumulada]]/Table153714[[#This Row],[Investimento Acumulado]] -> 2.9424837 | AH34: =Table153714[[#This Row],[ROI]]+AH33 -> 20.603807
A35: 46388 | B35: =B76*0.15 -> 15000 | C35: =C76 -> 12.534736 | D35: =Table153714[[#This Row],[Investimento no Mês (Growth) // 15%]]/Table153714[[#This Row],[CPL (cadastro)]] -> 1196.6746 | E35: =E76 -> 0.3 | F35: =Table153714[[#This Row],[Novos Cadastros LP]]*Table153714[[#This Row],[Tx. % Install]] -> 359.00239 | G35: =G76 -> 0.6 | H35: =Table153714[[#This Row],[Novos Installs no App]]*Table153714[[#This Row],[Tx % Ativações]] -> 215.40143 | I35: =I76 -> 0.3 | J35: =J76*50% -> 0 | K35: =K76 -> 0 | L35: =(Table153714[[#This Row],[Novos Personais Habilitados]]*Table153714[[#This Row],[Tx % de Conversão]])+(Table153714[[#This Row],[Cadastros Evento Presencial]]*Table153714[[#This Row],[Tx % Ativação Presencial]]) -> 64.62043 | M35: =Table153714[[#This Row],[Novos Personais Ativados]]+M34 -> 490.63602 | N35: =Table153714[[#This Row],[Investimento no Mês (Growth) // 15%]]/Table153714[[#This Row],[Novos Personais Ativados]] -> 232.12473 | O35: 0.03 | P35: =M34*Table153714[[#This Row],[Tx. % Churn]] -> 12.780468 | Q35: =Table153714[[#This Row],[Personais Totais]]-Table153714[[#This Row],[Qtde. Churn no Mês]] -> 477.85555 | R35: 15 | S35: =S34*1.015 -> 816.44047 | T35: =Table153714[[#This Row],[Média Alunos Estimada Total Personal]]*Table153714[[#This Row],[Ticket Médio Aluno Personal]] -> 12246.607 | U35: =Table153714[[#This Row],[Personais Ativos Mês]]+(Table153714[[#This Row],[Personais Ativos Mês]]*Table153714[[#This Row],[Média Alunos Estimada Total Personal]]) -> 7645.6888 | V35: =Table153714[[#This Row],[Média Faturamento Estimada Personal]]*Q34 -> 5084232.1 | W35: =Table153714[[#This Row],[Faturamento Estimado]]*2% -> 101684.64 | X35: =Table153714[[#This Row],[Média Alunos Estimada Total Personal]]-(Table153714[[#This Row],[Tx. % Real Alunos não ativados]]*Table153714[[#This Row],[Média Alunos Estimada Total Personal]]) -> 14.25 | Y35: 0.05 | Z35: =Table153714[[#This Row],[Ticket Médio Aluno Personal]]*Table153714[[#This Row],[Média Real Alunos Ativos Personal]] -> 11634.277 | AA35: =Table153714[[#This Row],[Média Real Alunos Ativos Personal]]*Table153714[[#This Row],[Personais Ativos Mês]] -> 6809.4416 | AB35: =Table153714[[#This Row],[Média Real por Personal]]*Q34 -> 4830020.5 | AC35: =Table153714[[#This Row],[Faturamento Real Bruto]]*2% -> 96600.411 | AD35: =AD34+Table153714[[#This Row],[Faturamento Real Bruto]] -> 19696128 | AE35: =AE34+Table153714[[#This Row],[Receita MUVX (2%)]] -> 393922.57 | AF35: =Table153714[[#This Row],[Investimento no Mês (Growth) // 15%]]+AF34 -> 116044.62 | AG35: =Table153714[[#This Row],[Receita MUVX Acumulada]]/Table153714[[#This Row],[Investimento Acumulado]] -> 3.3945783 | AH35: =Table153714[[#This Row],[ROI]]+AH34 -> 23.998385
A36: 46419 | B36: =B77*0.15 -> 15000 | C36: =C77 -> 12.409388 | D36: =Table153714[[#This Row],[Investimento no Mês (Growth) // 15%]]/Table153714[[#This Row],[CPL (cadastro)]] -> 1208.7622 | E36: =E77 -> 0.3 | F36: =Table153714[[#This Row],[Novos Cadastros LP]]*Table153714[[#This Row],[Tx. % Install]] -> 362.62867 | G36: =G77 -> 0.6 | H36: =Table153714[[#This Row],[Novos Installs no App]]*Table153714[[#This Row],[Tx % Ativações]] -> 217.5772 | I36: =I77 -> 0.3 | J36: =J77*50% -> 0 | K36: =K77 -> 0 | L36: =(Table153714[[#This Row],[Novos Personais Habilitados]]*Table153714[[#This Row],[Tx % de Conversão]])+(Table153714[[#This Row],[Cadastros Evento Presencial]]*Table153714[[#This Row],[Tx % Ativação Presencial]]) -> 65.273161 | M36: =Table153714[[#This Row],[Novos Personais Ativados]]+M35 -> 555.90918 | N36: =Table153714[[#This Row],[Investimento no Mês (Growth) // 15%]]/Table153714[[#This Row],[Novos Personais Ativados]] -> 229.80349 | O36: 0.06 | P36: =M35*Table153714[[#This Row],[Tx. % Churn]] -> 29.438161 | Q36: =Table153714[[#This Row],[Personais Totais]]-Table153714[[#This Row],[Qtde. Churn no Mês]] -> 526.47102 | R36: 15 | S36: =S35*1.015 -> 828.68708 | T36: =Table153714[[#This Row],[Média Alunos Estimada Total Personal]]*Table153714[[#This Row],[Ticket Médio Aluno Personal]] -> 12430.306 | U36: =Table153714[[#This Row],[Personais Ativos Mês]]+(Table153714[[#This Row],[Personais Ativos Mês]]*Table153714[[#This Row],[Média Alunos Estimada Total Personal]]) -> 8423.5363 | V36: =Table153714[[#This Row],[Média Faturamento Estimada Personal]]*Q35 -> 5939890.8 | W36: =Table153714[[#This Row],[Faturamento Estimado]]*2% -> 118797.82 | X36: =Table153714[[#This Row],[Média Alunos Estimada Total Personal]]-(Table153714[[#This Row],[Tx. % Real Alunos não ativados]]*Table153714[[#This Row],[Média Alunos Estimada Total Personal]]) -> 14.25 | Y36: 0.05 | Z36: =Table153714[[#This Row],[Ticket Médio Aluno Personal]]*Table153714[[#This Row],[Média Real Alunos Ativos Personal]] -> 11808.791 | AA36: =Table153714[[#This Row],[Média Real Alunos Ativos Personal]]*Table153714[[#This Row],[Personais Ativos Mês]] -> 7502.212 | AB36: =Table153714[[#This Row],[Média Real por Personal]]*Q35 -> 5642896.2 | AC36: =Table153714[[#This Row],[Faturamento Real Bruto]]*2% -> 112857.92 | AD36: =AD35+Table153714[[#This Row],[Faturamento Real Bruto]] -> 25339025 | AE36: =AE35+Table153714[[#This Row],[Receita MUVX (2%)]] -> 506780.49 | AF36: =Table153714[[#This Row],[Investimento no Mês (Growth) // 15%]]+AF35 -> 131044.62 | AG36: =Table153714[[#This Row],[Receita MUVX Acumulada]]/Table153714[[#This Row],[Investimento Acumulado]] -> 3.867236 | AH36: =Table153714[[#This Row],[ROI]]+AH35 -> 27.865621
B37: =SUBTOTAL(109,B23:B36) -> 131044.62 | C37: =SUBTOTAL(101,C23:C36) -> 13.105041 | D37: =SUBTOTAL(109,D23:D36) -> 11172.637 | E37: =AVERAGE(E23:E36) -> 0.25428571 | F37: =Table153714[[#This Row],[Novos Cadastros LP]]*Table153714[[#This Row],[Tx. % Install]] -> 2841.042 | G37: =G78 -> 0.53571429 | H37: =Table153714[[#This Row],[Novos Installs no App]]*Table153714[[#This Row],[Tx % Ativações]] -> 1521.9868 | I37: =I78 -> 0.32857143 | J37: =J78*50% -> 0 | K37: =K78 -> 0 | L37: =SUBTOTAL(109,L23:L36) -> 555.90918 | M37: =AVERAGE(M23:M36) -> 202.47868 | N37: =SUBTOTAL(101,N23:N36) -> #DIV/0! | O37: =AVERAGE(O23:O36) -> 0.025714286 | P37: =SUBTOTAL(109,P23:P36) -> 76.422619 | Q37: =Q36 -> 526.47102 | R37: =AVERAGE(R23:R36) -> 15 | S37: =Table153714[[#This Row],[Média Faturamento Estimada Personal]]/Table153714[[#This Row],[Média Alunos Estimada Total Personal]] -> 705.32087 | T37: =SUBTOTAL(101,T23:T36) -> 10579.813 | U37: =Table153714[[#This Row],[Personais Ativos Mês]]+(Table153714[[#This Row],[Personais Ativos Mês]]*Table153714[[#This Row],[Média Alunos Estimada Total Personal]]) -> 8423.5363 | V37: =SUBTOTAL(109,V23:V36) -> 26672658 | W37: =Table153714[[#This Row],[Faturamento Estimado]]*2% -> 533453.15 | Z37: =AVERAGE(Z24:Z36) -> 10298.963 | AB37: =SUBTOTAL(109,AB23:AB36) -> 25339025 | AC37: =SUBTOTAL(109,AC23:AC36) -> 506780.49
F38: =Table153714[[#This Row],[Novos Cadastros LP]]*Table153714[[#This Row],[Tx. % Install]] -> 0 | G38: =G79 -> 0 | H38: =Table153714[[#This Row],[Novos Installs no App]]*Table153714[[#This Row],[Tx % Ativações]] -> 0 | I38: =I79 -> 0 | J38: =J79*50% -> 0 | K38: =K79 -> 0
C39: % sob TAM Nacional | D39: =D37/130000 -> 0.085943363 | F39: =Table153714[[#This Row],[Novos Cadastros LP]]*Table153714[[#This Row],[Tx. % Install]] -> 0 | G39: =G80 -> 0 | H39: =Table153714[[#This Row],[Novos Installs no App]]*Table153714[[#This Row],[Tx % Ativações]] -> 0 | I39: =I80 -> 0 | J39: =J80*50% -> 0 | K39: =K80 -> 0 | P39: % sob TAM Nacional | Q39: =Q37/130000 -> 0.0040497771
C41: Top | E41: Install | G41: Ativação | I41: Conversão | N41: Cenário sem perdas operacionais | X41: Cenário com perdas operacionais
A42: Mês | B42: Investimento no Mês (Growth) // 80% | C42: CPL (cadastro) | D42: Novos Cadastros LP | E42: Tx. % Install | F42: Novos Installs no App | G42: Tx % Ativações | H42: Novos Personais Habilitados | I42: Tx % de Conversão | J42: Cadastros Evento Presencial | K42: Tx % Ativação Presencial | L42: Novos Personais Ativados | M42: Personais Totais | N42: CAC (ativação) | O42: Tx. % Churn | P42: Qtde. Churn no Mês | Q42: Personais Ativos Mês | R42: Média Alunos Estimada Total Personal | S42: Ticket Médio Aluno Personal | T42: Média Faturamento Estimada Personal | U42: Total Usuários Estimado | V42: Faturamento Estimado | W42: Receita MUVX Estimada (2%) | X42: Média Real Alunos Ativos Personal | Y42: Tx. % Real Alunos não ativados | Z42: Média Real por Personal | AA42: Total Real Usuários | AB42: Faturamento Real Bruto | AC42: Receita MUVX (2%) | AD42: Faturamento Real Acumulado | AE42: Receita MUVX Acumulada | AF42: Investimento Acumulado | AG42: ROI | AH42: ROI Acumulado
A43: 46023 | B43: =B64*0.8 -> 25070.608 | C43: =C64 -> 12 | D43: =Table153815[[#This Row],[Investimento no Mês (Growth) // 80%]]/Table153815[[#This Row],[CPL (cadastro)]] -> 2089.2173 | E43: =E64 -> 0.06 | F43: =Table153815[[#This Row],[Novos Cadastros LP]]*Table153815[[#This Row],[Tx. % Install]] -> 125.35304 | G43: =G64 -> 0 | H43: =Table153815[[#This Row],[Novos Installs no App]]*Table153815[[#This Row],[Tx % Ativações]] -> 0 | I43: =I64 -> 0.7 | J43: =J64*30% -> 0 | K43: =K64 -> 0 | L43: =(Table153815[[#This Row],[Novos Personais Habilitados]]*(Table153815[[#This Row],[Tx % de Conversão]])+Table153815[[#This Row],[Cadastros Evento Presencial]]*Table153815[[#This Row],[Tx % Ativação Presencial]]) -> 0 | M43: =Table153815[[#This Row],[Novos Personais Ativados]] -> 0 | N43: =Table153815[[#This Row],[Investimento no Mês (Growth) // 80%]]/Table153815[[#This Row],[Novos Personais Ativados]] -> #DIV/0! | O43: 0 | P43: =Table153815[[#This Row],[Personais Totais]]*Table153815[[#This Row],[Tx. % Churn]] -> 0 | Q43: =Table153815[[#This Row],[Personais Totais]]-Table153815[[#This Row],[Qtde. Churn no Mês]] -> 0 | R43: 15 | S43: 0 | T43: 0 | U43: =Table153815[[#This Row],[Personais Ativos Mês]]+(Table153815[[#This Row],[Personais Ativos Mês]]*Table153815[[#This Row],[Média Alunos Estimada Total Personal]]) -> 0 | V43: 0 | W43: 0 | X43: =Table153815[[#This Row],[Média Alunos Estimada Total Personal]]-(Table153815[[#This Row],[Tx. % Real Alunos não ativados]]*Table153815[[#This Row],[Média Alunos Estimada Total Personal]]) -> 9.75 | Y43: 0.35 | Z43: =AB43/Q43 -> #DIV/0! | AA43: =Table153815[[#This Row],[Média Real Alunos Ativos Personal]]*Table153815[[#This Row],[Personais Ativos Mês]] -> 0 | AB43: 0 | AC43: 0 | AD43: =Table153815[[#This Row],[Faturamento Real Bruto]] -> 0 | AE43: 0 | AF43: =Table153815[[#This Row],[Investimento no Mês (Growth) // 80%]] -> 25070.608 | AG43: 0 | AH43: 0
A44: 46054 | B44: =B65*0.8 -> 4234.056 | C44: =C65 -> 14 | D44: 516 | E44: =E65 -> 0.2 | F44: =Table153815[[#This Row],[Novos Cadastros LP]]*Table153815[[#This Row],[Tx. % Install]] -> 103.2 | G44: =G65 -> 0.5 | H44: =Table153815[[#This Row],[Novos Installs no App]]*Table153815[[#This Row],[Tx % Ativações]] -> 51.6 | I44: =I65 -> 0.3 | J44: =J65*30% -> 0 | K44: =K65 -> 0 | L44: =(Table153815[[#This Row],[Novos Personais Habilitados]]*(Table153815[[#This Row],[Tx % de Conversão]])+Table153815[[#This Row],[Cadastros Evento Presencial]]*Table153815[[#This Row],[Tx % Ativação Presencial]]) -> 15.48 | M44: =Table153815[[#This Row],[Novos Personais Ativados]]+M43 -> 15.48 | N44: =Table153815[[#This Row],[Investimento no Mês (Growth) // 80%]]/Table153815[[#This Row],[Novos Personais Ativados]] -> 273.51783 | O44: 0.02 | P44: =M43*Table153815[[#This Row],[Tx. % Churn]] -> 0 | Q44: =Table153815[[#This Row],[Personais Totais]]-Table153815[[#This Row],[Qtde. Churn no Mês]] -> 15.48 | R44: 15 | S44: 1350 | T44: =Table153815[[#This Row],[Média Alunos Estimada Total Personal]]*Table153815[[#This Row],[Ticket Médio Aluno Personal]] -> 20250 | U44: =Table153815[[#This Row],[Personais Ativos Mês]]+(Table153815[[#This Row],[Personais Ativos Mês]]*Table153815[[#This Row],[Média Alunos Estimada Total Personal]]) -> 247.68 | V44: =Table153815[[#This Row],[Média Faturamento Estimada Personal]]*Q43 -> 0 | W44: =Table153815[[#This Row],[Faturamento Estimado]]*2% -> 0 | X44: =Table153815[[#This Row],[Média Alunos Estimada Total Personal]]-(Table153815[[#This Row],[Tx. % Real Alunos não ativados]]*Table153815[[#This Row],[Média Alunos Estimada Total Personal]]) -> 4.5 | Y44: 0.7 | Z44: =Table153815[[#This Row],[Ticket Médio Aluno Personal]]*Table153815[[#This Row],[Média Real Alunos Ativos Personal]] -> 6075 | AA44: =Table153815[[#This Row],[Média Real Alunos Ativos Personal]]*Table153815[[#This Row],[Personais Ativos Mês]] -> 69.66 | AB44: =Table153815[[#This Row],[Média Real por Personal]]*Q43 -> 0 | AC44: =Table153815[[#This Row],[Faturamento Real Bruto]]*2% -> 0 | AD44: =Table153815[[#This Row],[Faturamento Real Bruto]]+AB43 -> 0 | AE44: =Table153815[[#This Row],[Receita MUVX (2%)]]+AC43 -> 0 | AF44: =Table153815[[#This Row],[Investimento no Mês (Growth) // 80%]]+AF43 -> 29304.664 | AG44: =Table153815[[#This Row],[Receita MUVX Acumulada]]/Table153815[[#This Row],[Investimento Acumulado]] -> 0 | AH44: =Table153815[[#This Row],[ROI]]+AH43 -> 0
A45: 46082 | B45: =B66*0.8 -> 800 | C45: =C66 -> 13.86 | D45: =Table153815[[#This Row],[Investimento no Mês (Growth) // 80%]]/Table153815[[#This Row],[CPL (cadastro)]] -> 57.720058 | E45: =E66 -> 0.2 | F45: =Table153815[[#This Row],[Novos Cadastros LP]]*Table153815[[#This Row],[Tx. % Install]] -> 11.544012 | G45: =G66 -> 0.5 | H45: =Table153815[[#This Row],[Novos Installs no App]]*Table153815[[#This Row],[Tx % Ativações]] -> 5.7720058 | I45: =I66 -> 0.3 | J45: =J66*30% -> 0 | K45: =K66 -> 0 | L45: =(Table153815[[#This Row],[Novos Personais Habilitados]]*(Table153815[[#This Row],[Tx % de Conversão]])+Table153815[[#This Row],[Cadastros Evento Presencial]]*Table153815[[#This Row],[Tx % Ativação Presencial]]) -> 1.7316017 | M45: =Table153815[[#This Row],[Novos Personais Ativados]]+M44 -> 17.211602 | N45: =Table153815[[#This Row],[Investimento no Mês (Growth) // 80%]]/Table153815[[#This Row],[Novos Personais Ativados]] -> 462 | O45: 0.03 | P45: =M44*Table153815[[#This Row],[Tx. % Churn]] -> 0.4644 | Q45: =Table153815[[#This Row],[Personais Totais]]-Table153815[[#This Row],[Qtde. Churn no Mês]] -> 16.747202 | R45: 15 | S45: =S44*1.005 -> 1356.75 | T45: =Table153815[[#This Row],[Média Alunos Estimada Total Personal]]*Table153815[[#This Row],[Ticket Médio Aluno Personal]] -> 20351.25 | U45: =Table153815[[#This Row],[Personais Ativos Mês]]+(Table153815[[#This Row],[Personais Ativos Mês]]*Table153815[[#This Row],[Média Alunos Estimada Total Personal]]) -> 267.95523 | V45: =Table153815[[#This Row],[Média Faturamento Estimada Personal]]*Q44 -> 315037.35 | W45: =Table153815[[#This Row],[Faturamento Estimado]]*2% -> 6300.747 | X45: =Table153815[[#This Row],[Média Alunos Estimada Total Personal]]-(Table153815[[#This Row],[Tx. % Real Alunos não ativados]]*Table153815[[#This Row],[Média Alunos Estimada Total Personal]]) -> 14.25 | Y45: 0.05 | Z45: =Table153815[[#This Row],[Ticket Médio Aluno Personal]]*Table153815[[#This Row],[Média Real Alunos Ativos Personal]] -> 19333.687 | AA45: =Table153815[[#This Row],[Média Real Alunos Ativos Personal]]*Table153815[[#This Row],[Personais Ativos Mês]] -> 238.64762 | AB45: =Table153815[[#This Row],[Média Real por Personal]]*Q44 -> 299285.48 | AC45: =Table153815[[#This Row],[Faturamento Real Bruto]]*2% -> 5985.7096 | AD45: =AD44+Table153815[[#This Row],[Faturamento Real Bruto]] -> 299285.48 | AE45: =AE44+Table153815[[#This Row],[Receita MUVX (2%)]] -> 5985.7096 | AF45: =Table153815[[#This Row],[Investimento no Mês (Growth) // 80%]]+AF44 -> 30104.664 | AG45: =Table153815[[#This Row],[Receita MUVX Acumulada]]/Table153815[[#This Row],[Investimento Acumulado]] -> 0.19882998 | AH45: =Table153815[[#This Row],[ROI]]+AH44 -> 0.19882998
A46: 46113 | B46: =B67*0.8 -> 800 | C46: =C67 -> 13.7214 | D46: =Table153815[[#This Row],[Investimento no Mês (Growth) // 80%]]/Table153815[[#This Row],[CPL (cadastro)]] -> 58.303089 | E46: =E67 -> 0.2 | F46: =Table153815[[#This Row],[Novos Cadastros LP]]*Table153815[[#This Row],[Tx. % Install]] -> 11.660618 | G46: =G67 -> 0.5 | H46: =Table153815[[#This Row],[Novos Installs no App]]*Table153815[[#This Row],[Tx % Ativações]] -> 5.8303089 | I46: =I67 -> 0.3 | J46: =J67*30% -> 0 | K46: =K67 -> 0 | L46: =(Table153815[[#This Row],[Novos Personais Habilitados]]*(Table153815[[#This Row],[Tx % de Conversão]])+Table153815[[#This Row],[Cadastros Evento Presencial]]*Table153815[[#This Row],[Tx % Ativação Presencial]]) -> 1.7490927 | M46: =Table153815[[#This Row],[Novos Personais Ativados]]+M45 -> 18.960694 | N46: =Table153815[[#This Row],[Investimento no Mês (Growth) // 80%]]/Table153815[[#This Row],[Novos Personais Ativados]] -> 457.38 | O46: 0.02 | P46: =M45*Table153815[[#This Row],[Tx. % Churn]] -> 0.34423203 | Q46: =Table153815[[#This Row],[Personais Totais]]-Table153815[[#This Row],[Qtde. Churn no Mês]] -> 18.616462 | R46: 15 | S46: =S45*1.015 -> 1377.1012 | T46: =Table153815[[#This Row],[Média Alunos Estimada Total Personal]]*Table153815[[#This Row],[Ticket Médio Aluno Personal]] -> 20656.519 | U46: =Table153815[[#This Row],[Personais Ativos Mês]]+(Table153815[[#This Row],[Personais Ativos Mês]]*Table153815[[#This Row],[Média Alunos Estimada Total Personal]]) -> 297.8634 | V46: =Table153815[[#This Row],[Média Faturamento Estimada Personal]]*Q45 -> 345938.89 | W46: =Table153815[[#This Row],[Faturamento Estimado]]*2% -> 6918.7777 | X46: =Table153815[[#This Row],[Média Alunos Estimada Total Personal]]-(Table153815[[#This Row],[Tx. % Real Alunos não ativados]]*Table153815[[#This Row],[Média Alunos Estimada Total Personal]]) -> 14.25 | Y46: 0.05 | Z46: =Table153815[[#This Row],[Ticket Médio Aluno Personal]]*Table153815[[#This Row],[Média Real Alunos Ativos Personal]] -> 19623.693 | AA46: =Table153815[[#This Row],[Média Real Alunos Ativos Personal]]*Table153815[[#This Row],[Personais Ativos Mês]] -> 265.28459 | AB46: =Table153815[[#This Row],[Média Real por Personal]]*Q45 -> 328641.94 | AC46: =Table153815[[#This Row],[Faturamento Real Bruto]]*2% -> 6572.8388 | AD46: =AD45+Table153815[[#This Row],[Faturamento Real Bruto]] -> 627927.42 | AE46: =AE45+Table153815[[#This Row],[Receita MUVX (2%)]] -> 12558.548 | AF46: =Table153815[[#This Row],[Investimento no Mês (Growth) // 80%]]+AF45 -> 30904.664 | AG46: =Table153815[[#This Row],[Receita MUVX Acumulada]]/Table153815[[#This Row],[Investimento Acumulado]] -> 0.40636418 | AH46: =Table153815[[#This Row],[ROI]]+AH45 -> 0.60519416
A47: 46143 | B47: =B68*0.8 -> 4000 | C47: =C68 -> 13.584186 | D47: =Table153815[[#This Row],[Investimento no Mês (Growth) // 80%]]/Table153815[[#This Row],[CPL (cadastro)]] -> 294.46004 | E47: =E68 -> 0.2 | F47: =Table153815[[#This Row],[Novos Cadastros LP]]*Table153815[[#This Row],[Tx. % Install]] -> 58.892009 | G47: =G68 -> 0.6 | H47: =Table153815[[#This Row],[Novos Installs no App]]*Table153815[[#This Row],[Tx % Ativações]] -> 35.335205 | I47: =I68 -> 0.3 | J47: =J68*30% -> 0 | K47: =K68 -> 0 | L47: =(Table153815[[#This Row],[Novos Personais Habilitados]]*(Table153815[[#This Row],[Tx % de Conversão]])+Table153815[[#This Row],[Cadastros Evento Presencial]]*Table153815[[#This Row],[Tx % Ativação Presencial]]) -> 10.600562 | M47: =Table153815[[#This Row],[Novos Personais Ativados]]+M46 -> 29.561256 | N47: =Table153815[[#This Row],[Investimento no Mês (Growth) // 80%]]/Table153815[[#This Row],[Novos Personais Ativados]] -> 377.3385 | O47: 0.02 | P47: =M46*Table153815[[#This Row],[Tx. % Churn]] -> 0.37921389 | Q47: =Table153815[[#This Row],[Personais Totais]]-Table153815[[#This Row],[Qtde. Churn no Mês]] -> 29.182042 | R47: 15 | S47: =S46*1.015 -> 1397.7578 | T47: =Table153815[[#This Row],[Média Alunos Estimada Total Personal]]*Table153815[[#This Row],[Ticket Médio Aluno Personal]] -> 20966.367 | U47: =Table153815[[#This Row],[Personais Ativos Mês]]+(Table153815[[#This Row],[Personais Ativos Mês]]*Table153815[[#This Row],[Média Alunos Estimada Total Personal]]) -> 466.91267 | V47: =Table153815[[#This Row],[Média Faturamento Estimada Personal]]*Q46 -> 390319.57 | W47: =Table153815[[#This Row],[Faturamento Estimado]]*2% -> 7806.3915 | X47: =Table153815[[#This Row],[Média Alunos Estimada Total Personal]]-(Table153815[[#This Row],[Tx. % Real Alunos não ativados]]*Table153815[[#This Row],[Média Alunos Estimada Total Personal]]) -> 14.25 | Y47: 0.05 | Z47: =Table153815[[#This Row],[Ticket Médio Aluno Personal]]*Table153815[[#This Row],[Média Real Alunos Ativos Personal]] -> 19918.048 | AA47: =Table153815[[#This Row],[Média Real Alunos Ativos Personal]]*Table153815[[#This Row],[Personais Ativos Mês]] -> 415.8441 | AB47: =Table153815[[#This Row],[Média Real por Personal]]*Q46 -> 370803.59 | AC47: =Table153815[[#This Row],[Faturamento Real Bruto]]*2% -> 7416.0719 | AD47: =AD46+Table153815[[#This Row],[Faturamento Real Bruto]] -> 998731.02 | AE47: =AE46+Table153815[[#This Row],[Receita MUVX (2%)]] -> 19974.62 | AF47: =Table153815[[#This Row],[Investimento no Mês (Growth) // 80%]]+AF46 -> 34904.664 | AG47: =Table153815[[#This Row],[Receita MUVX Acumulada]]/Table153815[[#This Row],[Investimento Acumulado]] -> 0.57226222 | AH47: =Table153815[[#This Row],[ROI]]+AH46 -> 1.1774564
A48: 46174 | B48: =B69*0.8 -> 24000 | C48: =C69 -> 13.448344 | D48: =Table153815[[#This Row],[Investimento no Mês (Growth) // 80%]]/Table153815[[#This Row],[CPL (cadastro)]] -> 1784.6063 | E48: 0.3 | F48: =Table153815[[#This Row],[Novos Cadastros LP]]*Table153815[[#This Row],[Tx. % Install]] -> 535.3819 | G48: =G69 -> 0.6 | H48: =Table153815[[#This Row],[Novos Installs no App]]*Table153815[[#This Row],[Tx % Ativações]] -> 321.22914 | I48: =I69 -> 0.3 | J48: =J69*30% -> 0 | K48: =K69 -> 0 | L48: =(Table153815[[#This Row],[Novos Personais Habilitados]]*(Table153815[[#This Row],[Tx % de Conversão]])+Table153815[[#This Row],[Cadastros Evento Presencial]]*Table153815[[#This Row],[Tx % Ativação Presencial]]) -> 96.368741 | M48: =Table153815[[#This Row],[Novos Personais Ativados]]+M47 -> 125.93 | N48: =Table153815[[#This Row],[Investimento no Mês (Growth) // 80%]]/Table153815[[#This Row],[Novos Personais Ativados]] -> 249.04341 | O48: 0.04 | P48: =M47*Table153815[[#This Row],[Tx. % Churn]] -> 1.1824502 | Q48: =Table153815[[#This Row],[Personais Totais]]-Table153815[[#This Row],[Qtde. Churn no Mês]] -> 124.74755 | R48: 15 | S48: =S47*1.015 -> 1418.7241 | T48: =Table153815[[#This Row],[Média Alunos Estimada Total Personal]]*Table153815[[#This Row],[Ticket Médio Aluno Personal]] -> 21280.862 | U48: =Table153815[[#This Row],[Personais Ativos Mês]]+(Table153815[[#This Row],[Personais Ativos Mês]]*Table153815[[#This Row],[Média Alunos Estimada Total Personal]]) -> 1995.9608 | V48: =Table153815[[#This Row],[Média Faturamento Estimada Personal]]*Q47 -> 621019.01 | W48: =Table153815[[#This Row],[Faturamento Estimado]]*2% -> 12420.38 | X48: =Table153815[[#This Row],[Média Alunos Estimada Total Personal]]-(Table153815[[#This Row],[Tx. % Real Alunos não ativados]]*Table153815[[#This Row],[Média Alunos Estimada Total Personal]]) -> 14.25 | Y48: 0.05 | Z48: =Table153815[[#This Row],[Ticket Médio Aluno Personal]]*Table153815[[#This Row],[Média Real Alunos Ativos Personal]] -> 20216.819 | AA48: =Table153815[[#This Row],[Média Real Alunos Ativos Personal]]*Table153815[[#This Row],[Personais Ativos Mês]] -> 1777.6525 | AB48: =Table153815[[#This Row],[Média Real por Personal]]*Q47 -> 589968.06 | AC48: =Table153815[[#This Row],[Faturamento Real Bruto]]*2% -> 11799.361 | AD48: =AD47+Table153815[[#This Row],[Faturamento Real Bruto]] -> 1588699.1 | AE48: =AE47+Table153815[[#This Row],[Receita MUVX (2%)]] -> 31773.982 | AF48: =Table153815[[#This Row],[Investimento no Mês (Growth) // 80%]]+AF47 -> 58904.664 | AG48: =Table153815[[#This Row],[Receita MUVX Acumulada]]/Table153815[[#This Row],[Investimento Acumulado]] -> 0.53941368 | AH48: =Table153815[[#This Row],[ROI]]+AH47 -> 1.7168701
A49: 46204 | B49: =B70*0.8 -> 80000 | C49: =C70 -> 13.313861 | D49: =Table153815[[#This Row],[Investimento no Mês (Growth) // 80%]]/Table153815[[#This Row],[CPL (cadastro)]] -> 6008.7755 | E49: =E70 -> 0.3 | F49: =Table153815[[#This Row],[Novos Cadastros LP]]*Table153815[[#This Row],[Tx. % Install]] -> 1802.6327 | G49: =G70 -> 0.6 | H49: =Table153815[[#This Row],[Novos Installs no App]]*Table153815[[#This Row],[Tx % Ativações]] -> 1081.5796 | I49: =I70 -> 0.3 | J49: =J70*30% -> 0 | K49: =K70 -> 0.2 | L49: =(Table153815[[#This Row],[Novos Personais Habilitados]]*(Table153815[[#This Row],[Tx % de Conversão]])+Table153815[[#This Row],[Cadastros Evento Presencial]]*Table153815[[#This Row],[Tx % Ativação Presencial]]) -> 324.47388 | M49: =Table153815[[#This Row],[Novos Personais Ativados]]+M48 -> 450.40387 | N49: =Table153815[[#This Row],[Investimento no Mês (Growth) // 80%]]/Table153815[[#This Row],[Novos Personais Ativados]] -> 246.55298 | O49: 0.02 | P49: =M48*Table153815[[#This Row],[Tx. % Churn]] -> 2.5185999 | Q49: =Table153815[[#This Row],[Personais Totais]]-Table153815[[#This Row],[Qtde. Churn no Mês]] -> 447.88527 | R49: 15 | S49: =S48*1.015 -> 1440.005 | T49: =Table153815[[#This Row],[Média Alunos Estimada Total Personal]]*Table153815[[#This Row],[Ticket Médio Aluno Personal]] -> 21600.075 | U49: =Table153815[[#This Row],[Personais Ativos Mês]]+(Table153815[[#This Row],[Personais Ativos Mês]]*Table153815[[#This Row],[Média Alunos Estimada Total Personal]]) -> 7166.1644 | V49: =Table153815[[#This Row],[Média Faturamento Estimada Personal]]*Q48 -> 2694556.4 | W49: =Table153815[[#This Row],[Faturamento Estimado]]*2% -> 53891.127 | X49: =Table153815[[#This Row],[Média Alunos Estimada Total Personal]]-(Table153815[[#This Row],[Tx. % Real Alunos não ativados]]*Table153815[[#This Row],[Média Alunos Estimada Total Personal]]) -> 14.25 | Y49: 0.05 | Z49: =Table153815[[#This Row],[Ticket Médio Aluno Personal]]*Table153815[[#This Row],[Média Real Alunos Ativos Personal]] -> 20520.071 | AA49: =Table153815[[#This Row],[Média Real Alunos Ativos Personal]]*Table153815[[#This Row],[Personais Ativos Mês]] -> 6382.3652 | AB49: =Table153815[[#This Row],[Média Real por Personal]]*Q48 -> 2559828.6 | AC49: =Table153815[[#This Row],[Faturamento Real Bruto]]*2% -> 51196.571 | AD49: =AD48+Table153815[[#This Row],[Faturamento Real Bruto]] -> 4148527.6 | AE49: =AE48+Table153815[[#This Row],[Receita MUVX (2%)]] -> 82970.553 | AF49: =Table153815[[#This Row],[Investimento no Mês (Growth) // 80%]]+AF48 -> 138904.66 | AG49: =Table153815[[#This Row],[Receita MUVX Acumulada]]/Table153815[[#This Row],[Investimento Acumulado]] -> 0.59732013 | AH49: =Table153815[[#This Row],[ROI]]+AH48 -> 2.3141902
A50: 46235 | B50: =B71*0.8 -> 80000 | C50: =C71 -> 13.180722 | D50: =Table153815[[#This Row],[Investimento no Mês (Growth) // 80%]]/Table153815[[#This Row],[CPL (cadastro)]] -> 6069.4702 | E50: =E71 -> 0.3 | F50: =Table153815[[#This Row],[Novos Cadastros LP]]*Table153815[[#This Row],[Tx. % Install]] -> 1820.8411 | G50: =G71 -> 0.6 | H50: =Table153815[[#This Row],[Novos Installs no App]]*Table153815[[#This Row],[Tx % Ativações]] -> 1092.5046 | I50: =I71 -> 0.3 | J50: =J71*30% -> 0 | K50: =K71 -> 0 | L50: =(Table153815[[#This Row],[Novos Personais Habilitados]]*(Table153815[[#This Row],[Tx % de Conversão]])+Table153815[[#This Row],[Cadastros Evento Presencial]]*Table153815[[#This Row],[Tx % Ativação Presencial]]) -> 327.75139 | M50: =Table153815[[#This Row],[Novos Personais Ativados]]+M49 -> 778.15527 | N50: =Table153815[[#This Row],[Investimento no Mês (Growth) // 80%]]/Table153815[[#This Row],[Novos Personais Ativados]] -> 244.08745 | O50: 0.02 | P50: =M49*Table153815[[#This Row],[Tx. % Churn]] -> 9.0080775 | Q50: =Table153815[[#This Row],[Personais Totais]]-Table153815[[#This Row],[Qtde. Churn no Mês]] -> 769.14719 | R50: 15 | S50: =S49*1.015 -> 1461.6051 | T50: =Table153815[[#This Row],[Média Alunos Estimada Total Personal]]*Table153815[[#This Row],[Ticket Médio Aluno Personal]] -> 21924.076 | U50: =Table153815[[#This Row],[Personais Ativos Mês]]+(Table153815[[#This Row],[Personais Ativos Mês]]*Table153815[[#This Row],[Média Alunos Estimada Total Personal]]) -> 12306.355 | V50: =Table153815[[#This Row],[Média Faturamento Estimada Personal]]*Q49 -> 9819470.8 | W50: =Table153815[[#This Row],[Faturamento Estimado]]*2% -> 196389.42 | X50: =Table153815[[#This Row],[Média Alunos Estimada Total Personal]]-(Table153815[[#This Row],[Tx. % Real Alunos não ativados]]*Table153815[[#This Row],[Média Alunos Estimada Total Personal]]) -> 14.25 | Y50: 0.05 | Z50: =Table153815[[#This Row],[Ticket Médio Aluno Personal]]*Table153815[[#This Row],[Média Real Alunos Ativos Personal]] -> 20827.872 | AA50: =Table153815[[#This Row],[Média Real Alunos Ativos Personal]]*Table153815[[#This Row],[Personais Ativos Mês]] -> 10960.347 | AB50: =Table153815[[#This Row],[Média Real por Personal]]*Q49 -> 9328497.3 | AC50: =Table153815[[#This Row],[Faturamento Real Bruto]]*2% -> 186569.95 | AD50: =AD49+Table153815[[#This Row],[Faturamento Real Bruto]] -> 13477025 | AE50: =AE49+Table153815[[#This Row],[Receita MUVX (2%)]] -> 269540.5 | AF50: =Table153815[[#This Row],[Investimento no Mês (Growth) // 80%]]+AF49 -> 218904.66 | AG50: =Table153815[[#This Row],[Receita MUVX Acumulada]]/Table153815[[#This Row],[Investimento Acumulado]] -> 1.2313146 | AH50: =Table153815[[#This Row],[ROI]]+AH49 -> 3.5455047
A51: 46266 | B51: =B72*0.8 -> 80000 | C51: =C72 -> 13.048915 | D51: =Table153815[[#This Row],[Investimento no Mês (Growth) // 80%]]/Table153815[[#This Row],[CPL (cadastro)]] -> 6130.778 | E51: =E72 -> 0.3 | F51: =Table153815[[#This Row],[Novos Cadastros LP]]*Table153815[[#This Row],[Tx. % Install]] -> 1839.2334 | G51: =G72 -> 0.6 | H51: =Table153815[[#This Row],[Novos Installs no App]]*Table153815[[#This Row],[Tx % Ativações]] -> 1103.54 | I51: =I72 -> 0.3 | J51: =J72*30% -> 0 | K51: =K72 -> 0 | L51: =(Table153815[[#This Row],[Novos Personais Habilitados]]*(Table153815[[#This Row],[Tx % de Conversão]])+Table153815[[#This Row],[Cadastros Evento Presencial]]*Table153815[[#This Row],[Tx % Ativação Presencial]]) -> 331.06201 | M51: =Table153815[[#This Row],[Novos Personais Ativados]]+M50 -> 1109.2173 | N51: =Table153815[[#This Row],[Investimento no Mês (Growth) // 80%]]/Table153815[[#This Row],[Novos Personais Ativados]] -> 241.64657 | O51: 0.02 | P51: =M50*Table153815[[#This Row],[Tx. % Churn]] -> 15.563105 | Q51: =Table153815[[#This Row],[Personais Totais]]-Table153815[[#This Row],[Qtde. Churn no Mês]] -> 1093.6542 | R51: 15 | S51: =S50*1.015 -> 1483.5291 | T51: =Table153815[[#This Row],[Média Alunos Estimada Total Personal]]*Table153815[[#This Row],[Ticket Médio Aluno Personal]] -> 22252.937 | U51: =Table153815[[#This Row],[Personais Ativos Mês]]+(Table153815[[#This Row],[Personais Ativos Mês]]*Table153815[[#This Row],[Média Alunos Estimada Total Personal]]) -> 17498.467 | V51: =Table153815[[#This Row],[Média Faturamento Estimada Personal]]*Q50 -> 17115784 | W51: =Table153815[[#This Row],[Faturamento Estimado]]*2% -> 342315.68 | X51: =Table153815[[#This Row],[Média Alunos Estimada Total Personal]]-(Table153815[[#This Row],[Tx. % Real Alunos não ativados]]*Table153815[[#This Row],[Média Alunos Estimada Total Personal]]) -> 14.25 | Y51: 0.05 | Z51: =Table153815[[#This Row],[Ticket Médio Aluno Personal]]*Table153815[[#This Row],[Média Real Alunos Ativos Personal]] -> 21140.29 | AA51: =Table153815[[#This Row],[Média Real Alunos Ativos Personal]]*Table153815[[#This Row],[Personais Ativos Mês]] -> 15584.572 | AB51: =Table153815[[#This Row],[Média Real por Personal]]*Q50 -> 16259995 | AC51: =Table153815[[#This Row],[Faturamento Real Bruto]]*2% -> 325199.9 | AD51: =AD50+Table153815[[#This Row],[Faturamento Real Bruto]] -> 29737020 | AE51: =AE50+Table153815[[#This Row],[Receita MUVX (2%)]] -> 594740.4 | AF51: =Table153815[[#This Row],[Investimento no Mês (Growth) // 80%]]+AF50 -> 298904.66 | AG51: =Table153815[[#This Row],[Receita MUVX Acumulada]]/Table153815[[#This Row],[Investimento Acumulado]] -> 1.9897327 | AH51: =Table153815[[#This Row],[ROI]]+AH50 -> 5.5352375
A52: 46296 | B52: =B73*0.8 -> 80000 | C52: =C73 -> 12.918426 | D52: =Table153815[[#This Row],[Investimento no Mês (Growth) // 80%]]/Table153815[[#This Row],[CPL (cadastro)]] -> 6192.705 | E52: =E73 -> 0.3 | F52: =Table153815[[#This Row],[Novos Cadastros LP]]*Table153815[[#This Row],[Tx. % Install]] -> 1857.8115 | G52: =G73 -> 0.6 | H52: =Table153815[[#This Row],[Novos Installs no App]]*Table153815[[#This Row],[Tx % Ativações]] -> 1114.6869 | I52: =I73 -> 0.3 | J52: =J73*30% -> 0 | K52: =K73 -> 0 | L52: =(Table153815[[#This Row],[Novos Personais Habilitados]]*(Table153815[[#This Row],[Tx % de Conversão]])+Table153815[[#This Row],[Cadastros Evento Presencial]]*Table153815[[#This Row],[Tx % Ativação Presencial]]) -> 334.40607 | M52: =Table153815[[#This Row],[Novos Personais Ativados]]+M51 -> 1443.6233 | N52: =Table153815[[#This Row],[Investimento no Mês (Growth) // 80%]]/Table153815[[#This Row],[Novos Personais Ativados]] -> 239.23011 | O52: 0.03 | P52: =M51*Table153815[[#This Row],[Tx. % Churn]] -> 33.276518 | Q52: =Table153815[[#This Row],[Personais Totais]]-Table153815[[#This Row],[Qtde. Churn no Mês]] -> 1410.3468 | R52: 15 | S52: =S51*1.015 -> 1505.7821 | T52: =Table153815[[#This Row],[Média Alunos Estimada Total Personal]]*Table153815[[#This Row],[Ticket Médio Aluno Personal]] -> 22586.731 | U52: =Table153815[[#This Row],[Personais Ativos Mês]]+(Table153815[[#This Row],[Personais Ativos Mês]]*Table153815[[#This Row],[Média Alunos Estimada Total Personal]]) -> 22565.549 | V52: =Table153815[[#This Row],[Média Faturamento Estimada Personal]]*Q51 -> 24702073 | W52: =Table153815[[#This Row],[Faturamento Estimado]]*2% -> 494041.46 | X52: =Table153815[[#This Row],[Média Alunos Estimada Total Personal]]-(Table153815[[#This Row],[Tx. % Real Alunos não ativados]]*Table153815[[#This Row],[Média Alunos Estimada Total Personal]]) -> 14.25 | Y52: 0.05 | Z52: =Table153815[[#This Row],[Ticket Médio Aluno Personal]]*Table153815[[#This Row],[Média Real Alunos Ativos Personal]] -> 21457.395 | AA52: =Table153815[[#This Row],[Média Real Alunos Ativos Personal]]*Table153815[[#This Row],[Personais Ativos Mês]] -> 20097.442 | AB52: =Table153815[[#This Row],[Média Real por Personal]]*Q51 -> 23466969 | AC52: =Table153815[[#This Row],[Faturamento Real Bruto]]*2% -> 469339.38 | AD52: =AD51+Table153815[[#This Row],[Faturamento Real Bruto]] -> 53203989 | AE52: =AE51+Table153815[[#This Row],[Receita MUVX (2%)]] -> 1064079.8 | AF52: =Table153815[[#This Row],[Investimento no Mês (Growth) // 80%]]+AF51 -> 378904.66 | AG52: =Table153815[[#This Row],[Receita MUVX Acumulada]]/Table153815[[#This Row],[Investimento Acumulado]] -> 2.8083048 | AH52: =Table153815[[#This Row],[ROI]]+AH51 -> 8.3435423
A53: 46327 | B53: =B74*0.8 -> 80000 | C53: =C74 -> 12.789241 | D53: =Table153815[[#This Row],[Investimento no Mês (Growth) // 80%]]/Table153815[[#This Row],[CPL (cadastro)]] -> 6255.2576 | E53: =E74 -> 0.3 | F53: =Table153815[[#This Row],[Novos Cadastros LP]]*Table153815[[#This Row],[Tx. % Install]] -> 1876.5773 | G53: =G74 -> 0.6 | H53: =Table153815[[#This Row],[Novos Installs no App]]*Table153815[[#This Row],[Tx % Ativações]] -> 1125.9464 | I53: =I74 -> 0.3 | J53: =J74*30% -> 0 | K53: =K74 -> 0 | L53: =(Table153815[[#This Row],[Novos Personais Habilitados]]*(Table153815[[#This Row],[Tx % de Conversão]])+Table153815[[#This Row],[Cadastros Evento Presencial]]*Table153815[[#This Row],[Tx % Ativação Presencial]]) -> 337.78391 | M53: =Table153815[[#This Row],[Novos Personais Ativados]]+M52 -> 1781.4073 | N53: =Table153815[[#This Row],[Investimento no Mês (Growth) // 80%]]/Table153815[[#This Row],[Novos Personais Ativados]] -> 236.8378 | O53: 0.02 | P53: =M52*Table153815[[#This Row],[Tx. % Churn]] -> 28.872467 | Q53: =Table153815[[#This Row],[Personais Totais]]-Table153815[[#This Row],[Qtde. Churn no Mês]] -> 1752.5348 | R53: 15 | S53: =S52*1.015 -> 1528.3688 | T53: =Table153815[[#This Row],[Média Alunos Estimada Total Personal]]*Table153815[[#This Row],[Ticket Médio Aluno Personal]] -> 22925.532 | U53: =Table153815[[#This Row],[Personais Ativos Mês]]+(Table153815[[#This Row],[Personais Ativos Mês]]*Table153815[[#This Row],[Média Alunos Estimada Total Personal]]) -> 28040.557 | V53: =Table153815[[#This Row],[Média Faturamento Estimada Personal]]*Q52 -> 32332952 | W53: =Table153815[[#This Row],[Faturamento Estimado]]*2% -> 646659.03 | X53: =Table153815[[#This Row],[Média Alunos Estimada Total Personal]]-(Table153815[[#This Row],[Tx. % Real Alunos não ativados]]*Table153815[[#This Row],[Média Alunos Estimada Total Personal]]) -> 14.25 | Y53: 0.05 | Z53: =Table153815[[#This Row],[Ticket Médio Aluno Personal]]*Table153815[[#This Row],[Média Real Alunos Ativos Personal]] -> 21779.256 | AA53: =Table153815[[#This Row],[Média Real Alunos Ativos Personal]]*Table153815[[#This Row],[Personais Ativos Mês]] -> 24973.621 | AB53: =Table153815[[#This Row],[Média Real por Personal]]*Q52 -> 30716304 | AC53: =Table153815[[#This Row],[Faturamento Real Bruto]]*2% -> 614326.08 | AD53: =AD52+Table153815[[#This Row],[Faturamento Real Bruto]] -> 83920293 | AE53: =AE52+Table153815[[#This Row],[Receita MUVX (2%)]] -> 1678405.9 | AF53: =Table153815[[#This Row],[Investimento no Mês (Growth) // 80%]]+AF52 -> 458904.66 | AG53: =Table153815[[#This Row],[Receita MUVX Acumulada]]/Table153815[[#This Row],[Investimento Acumulado]] -> 3.6574173 | AH53: =Table153815[[#This Row],[ROI]]+AH52 -> 12.00096
A54: 46357 | B54: =B75*0.8 -> 80000 | C54: =C75 -> 12.661349 | D54: =Table153815[[#This Row],[Investimento no Mês (Growth) // 80%]]/Table153815[[#This Row],[CPL (cadastro)]] -> 6318.442 | E54: =E75 -> 0.3 | F54: =Table153815[[#This Row],[Novos Cadastros LP]]*Table153815[[#This Row],[Tx. % Install]] -> 1895.5326 | G54: =G75 -> 0.6 | H54: =Table153815[[#This Row],[Novos Installs no App]]*Table153815[[#This Row],[Tx % Ativações]] -> 1137.3196 | I54: =I75 -> 0.3 | J54: =J75*30% -> 0 | K54: =K75 -> 0 | L54: =(Table153815[[#This Row],[Novos Personais Habilitados]]*(Table153815[[#This Row],[Tx % de Conversão]])+Table153815[[#This Row],[Cadastros Evento Presencial]]*Table153815[[#This Row],[Tx % Ativação Presencial]]) -> 341.19587 | M54: =Table153815[[#This Row],[Novos Personais Ativados]]+M53 -> 2122.6031 | N54: =Table153815[[#This Row],[Investimento no Mês (Growth) // 80%]]/Table153815[[#This Row],[Novos Personais Ativados]] -> 234.46943 | O54: 0.03 | P54: =M53*Table153815[[#This Row],[Tx. % Churn]] -> 53.442218 | Q54: =Table153815[[#This Row],[Personais Totais]]-Table153815[[#This Row],[Qtde. Churn no Mês]] -> 2069.1609 | R54: 15 | S54: =S53*1.015 -> 1551.2943 | T54: =Table153815[[#This Row],[Média Alunos Estimada Total Personal]]*Table153815[[#This Row],[Ticket Médio Aluno Personal]] -> 23269.415 | U54: =Table153815[[#This Row],[Personais Ativos Mês]]+(Table153815[[#This Row],[Personais Ativos Mês]]*Table153815[[#This Row],[Média Alunos Estimada Total Personal]]) -> 33106.575 | V54: =Table153815[[#This Row],[Média Faturamento Estimada Personal]]*Q53 -> 40780460 | W54: =Table153815[[#This Row],[Faturamento Estimado]]*2% -> 815609.2 | X54: =Table153815[[#This Row],[Média Alunos Estimada Total Personal]]-(Table153815[[#This Row],[Tx. % Real Alunos não ativados]]*Table153815[[#This Row],[Média Alunos Estimada Total Personal]]) -> 14.25 | Y54: 0.05 | Z54: =Table153815[[#This Row],[Ticket Médio Aluno Personal]]*Table153815[[#This Row],[Média Real Alunos Ativos Personal]] -> 22105.944 | AA54: =Table153815[[#This Row],[Média Real Alunos Ativos Personal]]*Table153815[[#This Row],[Personais Ativos Mês]] -> 29485.543 | AB54: =Table153815[[#This Row],[Média Real por Personal]]*Q53 -> 38741437 | AC54: =Table153815[[#This Row],[Faturamento Real Bruto]]*2% -> 774828.74 | AD54: =AD53+Table153815[[#This Row],[Faturamento Real Bruto]] -> 1.2266173e+08 | AE54: =AE53+Table153815[[#This Row],[Receita MUVX (2%)]] -> 2453234.6 | AF54: =Table153815[[#This Row],[Investimento no Mês (Growth) // 80%]]+AF53 -> 538904.66 | AG54: =Table153815[[#This Row],[Receita MUVX Acumulada]]/Table153815[[#This Row],[Investimento Acumulado]] -> 4.5522608 | AH54: =Table153815[[#This Row],[ROI]]+AH53 -> 16.55322
A55: 46388 | B55: =B76*0.8 -> 80000 | C55: =C76 -> 12.534736 | D55: =Table153815[[#This Row],[Investimento no Mês (Growth) // 80%]]/Table153815[[#This Row],[CPL (cadastro)]] -> 6382.2647 | E55: =E76 -> 0.3 | F55: =Table153815[[#This Row],[Novos Cadastros LP]]*Table153815[[#This Row],[Tx. % Install]] -> 1914.6794 | G55: =G76 -> 0.6 | H55: =Table153815[[#This Row],[Novos Installs no App]]*Table153815[[#This Row],[Tx % Ativações]] -> 1148.8076 | I55: =I76 -> 0.3 | J55: =J76*30% -> 0 | K55: =K76 -> 0 | L55: =(Table153815[[#This Row],[Novos Personais Habilitados]]*(Table153815[[#This Row],[Tx % de Conversão]])+Table153815[[#This Row],[Cadastros Evento Presencial]]*Table153815[[#This Row],[Tx % Ativação Presencial]]) -> 344.64229 | M55: =Table153815[[#This Row],[Novos Personais Ativados]]+M54 -> 2467.2454 | N55: =Table153815[[#This Row],[Investimento no Mês (Growth) // 80%]]/Table153815[[#This Row],[Novos Personais Ativados]] -> 232.12473 | O55: 0.03 | P55: =M54*Table153815[[#This Row],[Tx. % Churn]] -> 63.678094 | Q55: =Table153815[[#This Row],[Personais Totais]]-Table153815[[#This Row],[Qtde. Churn no Mês]] -> 2403.5673 | R55: 15 | S55: =S54*1.015 -> 1574.5638 | T55: =Table153815[[#This Row],[Média Alunos Estimada Total Personal]]*Table153815[[#This Row],[Ticket Médio Aluno Personal]] -> 23618.456 | U55: =Table153815[[#This Row],[Personais Ativos Mês]]+(Table153815[[#This Row],[Personais Ativos Mês]]*Table153815[[#This Row],[Média Alunos Estimada Total Personal]]) -> 38457.077 | V55: =Table153815[[#This Row],[Média Faturamento Estimada Personal]]*Q54 -> 48870387 | W55: =Table153815[[#This Row],[Faturamento Estimado]]*2% -> 977407.74 | X55: =Table153815[[#This Row],[Média Alunos Estimada Total Personal]]-(Table153815[[#This Row],[Tx. % Real Alunos não ativados]]*Table153815[[#This Row],[Média Alunos Estimada Total Personal]]) -> 14.25 | Y55: 0.05 | Z55: =Table153815[[#This Row],[Ticket Médio Aluno Personal]]*Table153815[[#This Row],[Média Real Alunos Ativos Personal]] -> 22437.534 | AA55: =Table153815[[#This Row],[Média Real Alunos Ativos Personal]]*Table153815[[#This Row],[Personais Ativos Mês]] -> 34250.834 | AB55: =Table153815[[#This Row],[Média Real por Personal]]*Q54 -> 46426868 | AC55: =Table153815[[#This Row],[Faturamento Real Bruto]]*2% -> 928537.35 | AD55: =AD54+Table153815[[#This Row],[Faturamento Real Bruto]] -> 1.690886e+08 | AE55: =AE54+Table153815[[#This Row],[Receita MUVX (2%)]] -> 3381772 | AF55: =Table153815[[#This Row],[Investimento no Mês (Growth) // 80%]]+AF54 -> 618904.66 | AG55: =Table153815[[#This Row],[Receita MUVX Acumulada]]/Table153815[[#This Row],[Investimento Acumulado]] -> 5.4641242 | AH55: =Table153815[[#This Row],[ROI]]+AH54 -> 22.017345
A56: 46419 | B56: =B77*0.8 -> 80000 | C56: =C77 -> 12.409388 | D56: =Table153815[[#This Row],[Investimento no Mês (Growth) // 80%]]/Table153815[[#This Row],[CPL (cadastro)]] -> 6446.732 | E56: =E77 -> 0.3 | F56: =Table153815[[#This Row],[Novos Cadastros LP]]*Table153815[[#This Row],[Tx. % Install]] -> 1934.0196 | G56: =G77 -> 0.6 | H56: =Table153815[[#This Row],[Novos Installs no App]]*Table153815[[#This Row],[Tx % Ativações]] -> 1160.4118 | I56: =I77 -> 0.3 | J56: =J77*30% -> 0 | K56: =K77 -> 0 | L56: =(Table153815[[#This Row],[Novos Personais Habilitados]]*(Table153815[[#This Row],[Tx % de Conversão]])+Table153815[[#This Row],[Cadastros Evento Presencial]]*Table153815[[#This Row],[Tx % Ativação Presencial]]) -> 348.12353 | M56: =Table153815[[#This Row],[Novos Personais Ativados]]+M55 -> 2815.3689 | N56: =Table153815[[#This Row],[Investimento no Mês (Growth) // 80%]]/Table153815[[#This Row],[Novos Personais Ativados]] -> 229.80349 | O56: 0.06 | P56: =M55*Table153815[[#This Row],[Tx. % Churn]] -> 148.03473 | Q56: =Table153815[[#This Row],[Personais Totais]]-Table153815[[#This Row],[Qtde. Churn no Mês]] -> 2667.3342 | R56: 15 | S56: =S55*1.015 -> 1598.1822 | T56: =Table153815[[#This Row],[Média Alunos Estimada Total Personal]]*Table153815[[#This Row],[Ticket Médio Aluno Personal]] -> 23972.733 | U56: =Table153815[[#This Row],[Personais Ativos Mês]]+(Table153815[[#This Row],[Personais Ativos Mês]]*Table153815[[#This Row],[Média Alunos Estimada Total Personal]]) -> 42677.348 | V56: =Table153815[[#This Row],[Média Faturamento Estimada Personal]]*Q55 -> 57620079 | W56: =Table153815[[#This Row],[Faturamento Estimado]]*2% -> 1152401.6 | X56: =Table153815[[#This Row],[Média Alunos Estimada Total Personal]]-(Table153815[[#This Row],[Tx. % Real Alunos não ativados]]*Table153815[[#This Row],[Média Alunos Estimada Total Personal]]) -> 14.25 | Y56: 0.05 | Z56: =Table153815[[#This Row],[Ticket Médio Aluno Personal]]*Table153815[[#This Row],[Média Real Alunos Ativos Personal]] -> 22774.097 | AA56: =Table153815[[#This Row],[Média Real Alunos Ativos Personal]]*Table153815[[#This Row],[Personais Ativos Mês]] -> 38009.513 | AB56: =Table153815[[#This Row],[Média Real por Personal]]*Q55 -> 54739075 | AC56: =Table153815[[#This Row],[Faturamento Real Bruto]]*2% -> 1094781.5 | AD56: =AD55+Table153815[[#This Row],[Faturamento Real Bruto]] -> 2.2382767e+08 | AE56: =AE55+Table153815[[#This Row],[Receita MUVX (2%)]] -> 4476553.4 | AF56: =Table153815[[#This Row],[Investimento no Mês (Growth) // 80%]]+AF55 -> 698904.66 | AG56: =Table153815[[#This Row],[Receita MUVX Acumulada]]/Table153815[[#This Row],[Investimento Acumulado]] -> 6.4050988 | AH56: =Table153815[[#This Row],[ROI]]+AH55 -> 28.422443
B57: =SUBTOTAL(109,B43:B56) -> 698904.66 | C57: =SUBTOTAL(101,C43:C56) -> 13.105041 | D57: =SUBTOTAL(109,D43:D56) -> 54604.732 | E57: =AVERAGE(E43:E56) -> 0.25428571 | F57: =Table153815[[#This Row],[Novos Cadastros LP]]*Table153815[[#This Row],[Tx. % Install]] -> 13885.203 | G57: =G78 -> 0.53571429 | H57: =Table153815[[#This Row],[Novos Installs no App]]*Table153815[[#This Row],[Tx % Ativações]] -> 7438.5017 | I57: =I78 -> 0.32857143 | J57: =J78*30% -> 0 | K57: =K78 -> 0 | L57: =SUBTOTAL(109,L43:L56) -> 2815.3689 | M57: =AVERAGE(M43:M56) -> 941.08343 | N57: =SUBTOTAL(101,N43:N56) -> #DIV/0! | O57: =AVERAGE(O43:O56) -> 0.025714286 | P57: =SUBTOTAL(109,P43:P56) -> 356.7641 | Q57: =Q56 -> 2667.3342 | R57: =AVERAGE(R43:R56) -> 15 | S57: =Table153815[[#This Row],[Média Faturamento Estimada Personal]]/Table153815[[#This Row],[Média Alunos Estimada Total Personal]] -> 1360.2617 | T57: =SUBTOTAL(101,T43:T56) -> 20403.925 | U57: =Table153815[[#This Row],[Personais Ativos Mês]]+(Table153815[[#This Row],[Personais Ativos Mês]]*Table153815[[#This Row],[Média Alunos Estimada Total Personal]]) -> 42677.348 | V57: =SUBTOTAL(109,V43:V56) -> 2.3560808e+08 | W57: =Table153815[[#This Row],[Faturamento Estimado]]*2% -> 4712161.5 | Z57: =AVERAGE(Z44:Z56) -> 19862.285 | AB57: =SUBTOTAL(109,AB43:AB56) -> 2.2382767e+08 | AC57: =SUBTOTAL(109,AC43:AC56) -> 4476553.4
F58: =Table153815[[#This Row],[Novos Cadastros LP]]*Table153815[[#This Row],[Tx. % Install]] -> 0 | G58: =G79 -> 0 | H58: =Table153815[[#This Row],[Novos Installs no App]]*Table153815[[#This Row],[Tx % Ativações]] -> 0 | I58: =I79 -> 0 | J58: =J79*30% -> 0 | K58: =K79 -> 0
C59: % sob TAM Nacional | D59: =D57/130000 -> 0.4200364 | F59: =Table153815[[#This Row],[Novos Cadastros LP]]*Table153815[[#This Row],[Tx. % Install]] -> 0 | G59: =G80 -> 0 | H59: =Table153815[[#This Row],[Novos Installs no App]]*Table153815[[#This Row],[Tx % Ativações]] -> 0 | I59: =I80 -> 0 | J59: =J80*30% -> 0 | K59: =K80 -> 0 | P59: % sob TAM Nacional | Q59: =Q57/130000 -> 0.020517956
C62: Top | E62: Install/Cadastro | G62: Ativação | I62: Conversão | N62: Cenário sem perdas operacionais | X62: Cenário com perdas operacionais
A63: Mês | B63: Investimento no Mês Total (Growth - Tráfego) | C63: CPL - Tráfego (cadastro) | D63: Novos Cadastros LP | E63: Tx. % Install | F63: Novos Installs no App | G63: Tx % Ativações | H63: Novos Personais Habilitados | I63: Tx % de Conversão | J63: Cadastros Evento Presencial | K63: Tx % Ativação Presencial | L63: Novos Personais Ativados | M63: Tx % Conversão Geral | N63: Personais Totais | O63: CAC (ativação) | P63: Tx. % Churn | Q63: Qtde. Churn no Mês | R63: Personais Ativos Mês | S63: Média Alunos Estimada Total Personal | T63: Ticket Médio Aluno Personal | U63: Média Ponderada Estimada Personal | V63: Total Usuários Estimado | W63: Faturamento Estimado | X63: Receita MUVX Estimada (2%) | Y63: Média Real Alunos Ativos Personal | Z63: Tx. % Real Alunos não ativados | AA63: Média Ponderada Real por Personal | AB63: Total Real Usuários | AC63: Faturamento Real Bruto | AD63: Receita MUVX (2%) | AE63: Receita MUVX Premium (R$189,90) | AF63: Receita MUVX (Tarifa Alunos R$3,99) | AG63: Faturamento Real Acumulado | AH63: Receita MUVX Acumulada | AI63: Investimento Acumulado | AJ63: ROI | AK63: ROI Acumulado
A64: 46023 | B64: {=INDEX(Fluxo_Caixa_Mensal!$H$90:$S$90, ROW(B64)-ROW($B$64)+1)} -> 31338.26 | C64: 12 | D64: 1845 | E64: 0.06 | F64: =F3+F23+F43 -> 156.6913 | G64: 0 | H64: =H3+H23+H43 -> 0 | I64: 0.7 | J64: 0 | K64: 0 | L64: =L3+L23+L43 -> 0 | M64: =L64/D64 -> 0 | N64: =M3+M23+M43 -> 0 | O64: =IFERROR(AVERAGE(N3,N23,N43),0) -> 0 | P64: =AVERAGE(O3,O23,O43) -> 0 | Q64: =P3+P23+P43 -> 0 | R64: =Q3+Q23+Q43 -> 0 | S64: =R43 -> 15 | T64: =AVERAGE(S3,S23,S43) -> 0 | U64: =IFERROR((M3*T3 + M23*T23 + M43*T43)/(M3 + M23 + M43),"0" ) -> 0 | V64: =U3+U23+U43 -> 0 | W64: =V3+V23+V43 -> 0 | X64: =W3+W23+W43 -> 0 | Y64: =AVERAGE(X3,X23,X43) -> 9.75 | Z64: =AVERAGE(Y3,Y23,Y43) -> 0.35 | AA64: =IFERROR((M3*Z3 + M23*Z23 + M43*Z43)/(M3 + M23 + M43),"0" ) -> 0 | AB64: =AA3+AA23+AA43 -> 0 | AC64: =AB3+AB23+AB43 -> 0 | AD64: =AC3+AC23+AC43 -> 0 | AG64: =AD3+AD23+AD43 -> 0 | AH64: =AE3+AE23+AE43 -> 0 | AI64: =AF3+AF23+AF43 -> 31338.26
A65: 46054 | B65: {=INDEX(Fluxo_Caixa_Mensal!$H$90:$S$90, ROW(B65)-ROW($B$64)+1)} -> 5292.57 | C65: 14 | D65: =D4+D24+D44 -> 2578 | E65: 0.2 | F65: =F4+F24+F44 -> 515.6 | G65: 0.5 | H65: =H4+H24+H44 -> 257.8 | I65: 0.3 | J65: 0 | K65: 0 | L65: =L4+L24+L44 -> 77.34 | M65: =L65/D65 -> 0.03 | N65: =M4+M24+M44 -> 77.34 | O65: =AVERAGE(N4,N24,N44) -> 102.58024 | P65: =AVERAGE(O4,O24,O44) -> 0.02 | Q65: =P4+P24+P44 -> 0 | R65: =Q4+Q24+Q44 -> 77.34 | S65: =R44 -> 15 | T65: =AVERAGE(S4,S24,S44) -> 766.66667 | U65: =IFERROR((M4*T4 + M24*T24 + M44*T44)/(M4 + M24 + M44),"0" ) -> 9752.0365 | V65: =U4+U24+U44 -> 1237.44 | W65: =V4+V24+V44 -> 0 | X65: =W4+W24+W44 -> 0 | Y65: =AVERAGE(X4,X24,X44) -> 4.5 | Z65: =AVERAGE(Y4,Y24,Y44) -> 0.7 | AA65: =IFERROR((M4*Z4 + M24*Z24 + M44*Z44)/(M4 + M24 + M44),"0" ) -> 2925.6109 | AB65: =AA4+AA24+AA44 -> 348.03 | AC65: =AB4+AB24+AB44 -> 0 | AD65: =AC4+AC24+AC44 -> 0 | AG65: =AD4+AD24+AD44 -> 0 | AH65: =AE4+AE24+AE44 -> 0 | AI65: =AF4+AF24+AF44 -> 36630.83
A66: 46082 | B66: {=INDEX(Fluxo_Caixa_Mensal!$H$90:$S$90, ROW(B66)-ROW($B$64)+1)} -> 1000 | C66: =C65*0.99 -> 13.86 | D66: =D5+D25+D45 -> 72.150072 | E66: 0.2 | F66: =F5+F25+F45 -> 14.430014 | G66: 0.5 | H66: =H5+H25+H45 -> 7.2150072 | I66: 0.3 | J66: 0 | K66: 0 | L66: =L5+L25+L45 -> 2.1645022 | M66: =L66/D66 -> 0.03 | N66: =M5+M25+M45 -> 79.504502 | O66: =AVERAGE(N5,N25,N45) -> 462 | P66: =AVERAGE(O5,O25,O45) -> 0.03 | Q66: =P5+P25+P45 -> 2.3202 | R66: =Q5+Q25+Q45 -> 77.184302 | S66: =R45 -> 15 | T66: =AVERAGE(S5,S25,S45) -> 770.5 | U66: =IFERROR((M5*T5 + M25*T25 + M45*T45)/(M5 + M25 + M45),"0" ) -> 10025.443 | V66: =U5+U25+U45 -> 1234.9488 | W66: =V5+V25+V45 -> 757993.61 | X66: =W5+W25+W45 -> 15159.872 | Y66: =AVERAGE(X5,X25,X45) -> 14.25 | Z66: =AVERAGE(Y5,Y25,Y45) -> 0.05 | AA66: =IFERROR((M5*Z5 + M25*Z25 + M45*Z45)/(M5 + M25 + M45),"0" ) -> 9524.1712 | AB66: =AA5+AA25+AA45 -> 1099.8763 | AC66: =AB5+AB25+AB45 -> 720093.93 | AD66: =AC5+AC25+AC45 -> 14401.879 | AE66: =((((Q45+Q25)/R66))*R66)*189.9 -> 8939.3482 | AF66: =AB66*3.99 -> 4388.5065 | AG66: =AD5+AD25+AD45 -> 720093.93 | AH66: =AE5+AE25+AE45 -> 14401.879 | AI66: =AF5+AF25+AF45 -> 37630.83
A67: 46113 | B67: {=INDEX(Fluxo_Caixa_Mensal!$H$90:$S$90, ROW(B67)-ROW($B$64)+1)} -> 1000 | C67: =C66*0.99 -> 13.7214 | D67: =D6+D26+D46 -> 72.878861 | E67: 0.2 | F67: =F6+F26+F46 -> 14.575772 | G67: 0.5 | H67: =H6+H26+H46 -> 7.2878861 | I67: 0.3 | J67: 0 | K67: 0 | L67: =L6+L26+L46 -> 2.1863658 | M67: =L67/D67 -> 0.03 | N67: =M6+M26+M46 -> 81.690868 | O67: =AVERAGE(N6,N26,N46) -> 457.38 | P67: =AVERAGE(O6,O26,O46) -> 0.02 | Q67: =P6+P26+P46 -> 1.59009 | R67: =Q6+Q26+Q46 -> 80.100778 | S67: =R46 -> 15 | T67: =AVERAGE(S6,S26,S46) -> 782.0575 | U67: =IFERROR((M6*T6 + M26*T26 + M46*T46)/(M6 + M26 + M46),"0" ) -> 10393.878 | V67: =U6+U26+U46 -> 1281.6124 | W67: =V6+V26+V46 -> 785942.99 | X67: =W6+W26+W46 -> 15718.86 | Y67: =AVERAGE(X6,X26,X46) -> 14.25 | Z67: =AVERAGE(Y6,Y26,Y46) -> 0.05 | AA67: =IFERROR((M6*Z6 + M26*Z26 + M46*Z46)/(M6 + M26 + M46),"0" ) -> 9874.1838 | AB67: =AA6+AA26+AA46 -> 1141.4361 | AC67: =AB6+AB26+AB46 -> 746645.84 | AD67: =AC6+AC26+AC46 -> 14932.917 | AE67: =((((Q46+Q26)/R67))*R67)*189.9 -> 9414.1024 | AF67: =AB67*3.99 -> 4554.33 | AG67: =AD6+AD26+AD46 -> 1466739.8 | AH67: =AE6+AE26+AE46 -> 29334.796 | AI67: =AF6+AF26+AF46 -> 38630.83
A68: 46143 | B68: {=INDEX(Fluxo_Caixa_Mensal!$H$90:$S$90, ROW(B68)-ROW($B$64)+1)} -> 5000 | C68: =C67*0.99 -> 13.584186 | D68: =D7+D27+D47 -> 368.07505 | E68: 0.2 | F68: =F7+F27+F47 -> 73.615011 | G68: 0.6 | H68: =H7+H27+H47 -> 44.169007 | I68: 0.3 | J68: 0 | K68: 0 | L68: =L7+L27+L47 -> 13.250702 | M68: =L68/D68 -> 0.036 | N68: =M7+M27+M47 -> 94.94157 | O68: =AVERAGE(N7,N27,N47) -> 377.3385 | P68: =AVERAGE(O7,O27,O47) -> 0.02 | Q68: =P7+P27+P47 -> 1.6338174 | R68: =Q7+Q27+Q47 -> 93.307753 | S68: =R47 -> 15 | T68: =AVERAGE(S7,S27,S47) -> 793.78836 | U68: =IFERROR((M7*T7 + M27*T27 + M47*T47)/(M7 + M27 + M47),"0" ) -> 11673.042 | V68: =U7+U27+U47 -> 1492.924 | W68: =V7+V27+V47 -> 845397.98 | X68: =W7+W27+W47 -> 16907.96 | Y68: =AVERAGE(X7,X27,X47) -> 14.25 | Z68: =AVERAGE(Y7,Y27,Y47) -> 0.05 | AA68: =IFERROR((M7*Z7 + M27*Z27 + M47*Z47)/(M7 + M27 + M47),"0" ) -> 11089.39 | AB68: =AA7+AA27+AA47 -> 1329.6355 | AC68: =AB7+AB27+AB47 -> 803128.08 | AD68: =AC7+AC27+AC47 -> 16062.562 | AE68: =((((Q47+Q27)/R68))*R68)*189.9 -> 11796.707 | AF68: =AB68*3.99 -> 5305.2455 | AG68: =AD7+AD27+AD47 -> 2269867.9 | AH68: =AE7+AE27+AE47 -> 45397.357 | AI68: =AF7+AF27+AF47 -> 43630.83
A69: 46174 | B69: {=INDEX(Fluxo_Caixa_Mensal!$H$90:$S$90, ROW(B69)-ROW($B$64)+1)} -> 30000 | C69: =C68*0.99 -> 13.448344 | D69: =D8+D28+D48 -> 2230.7579 | E69: 0.4 | F69: =F8+F28+F48 -> 669.22737 | G69: 0.6 | H69: =H8+H28+H48 -> 401.53642 | I69: 0.3 | J69: 0 | K69: 0 | L69: =L8+L28+L48 -> 120.46093 | M69: =(L69)/(D69+J69) -> 0.054 | N69: =M8+M28+M48 -> 215.4025 | O69: =AVERAGE(N8,N28,N48) -> 249.04341 | P69: =AVERAGE(O8,O28,O48) -> 0.04 | Q69: =P8+P28+P48 -> 3.7976628 | R69: =Q8+Q28+Q48 -> 211.60483 | S69: =R48 -> 15 | T69: =AVERAGE(S8,S28,S48) -> 805.69519 | U69: =IFERROR((M8*T8 + M28*T28 + M48*T48)/(M8 + M28 + M48),"0" ) -> 15778.885 | V69: =U8+U28+U48 -> 3385.6773 | W69: =V8+V28+V48 -> 1107385.9 | X69: =W8+W28+W48 -> 22147.717 | Y69: =AVERAGE(X8,X28,X48) -> 14.25 | Z69: =AVERAGE(Y8,Y28,Y48) -> 0.05 | AA69: =IFERROR((M8*Z8 + M28*Z28 + M48*Z48)/(M8 + M28 + M48),"0" ) -> 14989.941 | AB69: =AA8+AA28+AA48 -> 3015.3689 | AC69: =AB8+AB28+AB48 -> 1052016.6 | AD69: =AC8+AC28+AC48 -> 21040.331 | AE69: =((((Q48+Q28)/R69))*R69)*189.9 -> 33240.877 | AF69: =AB69*3.99 -> 12031.322 | AG69: =AD8+AD28+AD48 -> 3321884.4 | AH69: =AE8+AE28+AE48 -> 66437.689 | AI69: =AF8+AF28+AF48 -> 73630.83
A70: 46204 | B70: {=INDEX(Fluxo_Caixa_Mensal!$H$90:$S$90, ROW(B70)-ROW($B$64)+1)} -> 100000 | C70: =C69*0.99 -> 13.313861 | D70: =D9+D29+D49 -> 7510.9694 | E70: 0.3 | F70: =F9+F29+F49 -> 2253.2908 | G70: 0.6 | H70: =H9+H29+H49 -> 1351.9745 | I70: 0.3 | J70: 0 | K70: 0.2 | L70: =L9+L29+L49 -> 405.59235 | M70: =L70/D70 -> 0.054 | N70: =M9+M29+M49 -> 620.99484 | O70: =AVERAGE(N9,N29,N49) -> 246.55298 | P70: =AVERAGE(O9,O29,O49) -> 0.02 | Q70: =P9+P29+P49 -> 4.3080499 | R70: =Q9+Q29+Q49 -> 616.68679 | S70: =R49 -> 15 | T70: =AVERAGE(S9,S29,S49) -> 817.78062 | U70: =IFERROR((M9*T9 + M29*T29 + M49*T49)/(M9 + M29 + M49),"0" ) -> 18069.344 | V70: =U9+U29+U49 -> 9866.9887 | W70: =V9+V29+V49 -> 3404123.2 | X70: =W9+W29+W49 -> 68082.465 | Y70: =AVERAGE(X9,X29,X49) -> 14.25 | Z70: =AVERAGE(Y9,Y29,Y49) -> 0.05 | AA70: =IFERROR((M9*Z9 + M29*Z29 + M49*Z49)/(M9 + M29 + M49),"0" ) -> 17165.877 | AB70: =AA9+AA29+AA49 -> 8787.7868 | AC70: =AB9+AB29+AB49 -> 3233917.1 | AD70: =AC9+AC29+AC49 -> 64678.342 | AE70: =((((Q49+Q29)/R70))*R70)*189.9 -> 106216.9 | AF70: =AB70*3.99 -> 35063.269 | AG70: =AD9+AD29+AD49 -> 6555801.5 | AH70: =AE9+AE29+AE49 -> 131116.03 | AI70: =AF9+AF29+AF49 -> 173630.83
A71: 46235 | B71: {=INDEX(Fluxo_Caixa_Mensal!$H$90:$S$90, ROW(B71)-ROW($B$64)+1)} -> 100000 | C71: =C70*0.99 -> 13.180722 | D71: =D10+D30+D50 -> 7586.8378 | E71: 0.3 | F71: =F10+F30+F50 -> 2276.0513 | G71: 0.6 | H71: =H10+H30+H50 -> 1365.6308 | I71: 0.3 | J71: 0 | K71: 0 | L71: =L10+L30+L50 -> 409.68924 | M71: =L71/D71 -> 0.054 | N71: =M10+M30+M50 -> 1030.6841 | O71: =AVERAGE(N10,N30,N50) -> 244.08745 | P71: =AVERAGE(O10,O30,O50) -> 0.02 | Q71: =P10+P30+P50 -> 12.419897 | R71: =Q10+Q30+Q50 -> 1018.2642 | S71: =R50 -> 15 | T71: =AVERAGE(S10,S30,S50) -> 830.04732 | U71: =IFERROR((M10*T10 + M30*T30 + M50*T50)/(M10 + M30 + M50),"0" ) -> 18780.442 | V71: =U10+U30+U50 -> 16292.227 | W71: =V10+V30+V50 -> 11319253 | X71: =W10+W30+W50 -> 226385.07 | Y71: =AVERAGE(X10,X30,X50) -> 14.25 | Z71: =AVERAGE(Y10,Y30,Y50) -> 0.05 | AA71: =IFERROR((M10*Z10 + M30*Z30 + M50*Z50)/(M10 + M30 + M50),"0" ) -> 17841.42 | AB71: =AA10+AA30+AA50 -> 14510.265 | AC71: =AB10+AB30+AB50 -> 10753291 | AD71: =AC10+AC30+AC50 -> 215065.82 | AE71: =((((Q50+Q30)/R71))*R71)*189.9 -> 178663.47 | AF71: =AB71*3.99 -> 57895.956 | AG71: =AD10+AD30+AD50 -> 17309092 | AH71: =AE10+AE30+AE50 -> 346181.85 | AI71: =AF10+AF30+AF50 -> 273630.83
A72: 46266 | B72: {=INDEX(Fluxo_Caixa_Mensal!$H$90:$S$90, ROW(B72)-ROW($B$64)+1)} -> 100000 | C72: =C71*0.99 -> 13.048915 | D72: =D11+D31+D51 -> 7663.4725 | E72: 0.3 | F72: =F11+F31+F51 -> 2299.0417 | G72: 0.6 | H72: =H11+H31+H51 -> 1379.425 | I72: 0.3 | J72: 0 | K72: 0 | L72: =L11+L31+L51 -> 413.82751 | M72: =L72/D72 -> 0.054 | N72: =M11+M31+M51 -> 1444.5116 | O72: =AVERAGE(N11,N31,N51) -> 241.64657 | P72: =AVERAGE(O11,O31,O51) -> 0.02 | Q72: =P11+P31+P51 -> 20.613682 | R72: =Q11+Q31+Q51 -> 1423.8979 | S72: =R51 -> 15 | T72: =AVERAGE(S11,S31,S51) -> 842.49803 | U72: =IFERROR((M11*T11 + M31*T31 + M51*T51)/(M11 + M31 + M51),"0" ) -> 19256.106 | V72: =U11+U31+U51 -> 22782.367 | W72: =V11+V31+V51 -> 19415850 | X72: =W11+W31+W51 -> 388317.01 | Y72: =AVERAGE(X11,X31,X51) -> 14.25 | Z72: =AVERAGE(Y11,Y31,Y51) -> 0.05 | AA72: =IFERROR((M11*Z11 + M31*Z31 + M51*Z51)/(M11 + M31 + M51),"0" ) -> 18293.301 | AB72: =AA11+AA31+AA51 -> 20290.545 | AC72: =AB11+AB31+AB51 -> 18445058 | AD72: =AC11+AC31+AC51 -> 368901.16 | AE72: =((((Q51+Q31)/R72))*R72)*189.9 -> 251841.82 | AF72: =AB72*3.99 -> 80959.276 | AG72: =AD11+AD31+AD51 -> 35754150 | AH72: =AE11+AE31+AE51 -> 715083.01 | AI72: =AF11+AF31+AF51 -> 373630.83
A73: 46296 | B73: {=INDEX(Fluxo_Caixa_Mensal!$H$90:$S$90, ROW(B73)-ROW($B$64)+1)} -> 100000 | C73: =C72*0.99 -> 12.918426 | D73: =D12+D32+D52 -> 7740.8813 | E73: 0.3 | F73: =F12+F32+F52 -> 2322.2644 | G73: 0.6 | H73: =H12+H32+H52 -> 1393.3586 | I73: 0.3 | J73: 0 | K73: 0 | L73: =L12+L32+L52 -> 418.00759 | M73: =L73/D73 -> 0.054 | N73: =M12+M32+M52 -> 1862.5192 | O73: =AVERAGE(N12,N32,N52) -> 239.23011 | P73: =AVERAGE(O12,O32,O52) -> 0.03 | Q73: =P12+P32+P52 -> 43.335348 | R73: =Q12+Q32+Q52 -> 1819.1838 | S73: =R52 -> 15 | T73: =AVERAGE(S12,S32,S52) -> 855.13551 | U73: =IFERROR((M12*T12 + M32*T32 + M52*T52)/(M12 + M32 + M52),"0" ) -> 19654.991 | V73: =U12+U32+U52 -> 29106.941 | W73: =V12+V32+V52 -> 27834068 | X73: =W12+W32+W52 -> 556681.37 | Y73: =AVERAGE(X12,X32,X52) -> 14.25 | Z73: =AVERAGE(Y12,Y32,Y52) -> 0.05 | AA73: =IFERROR((M12*Z12 + M32*Z32 + M52*Z52)/(M12 + M32 + M52),"0" ) -> 18672.241 | AB73: =AA12+AA32+AA52 -> 25923.37 | AC73: =AB12+AB32+AB52 -> 26442365 | AD73: =AC12+AC32+AC52 -> 528847.3 | AE73: =((((Q52+Q32)/R73))*R73)*189.9 -> 323204.77 | AF73: =AB73*3.99 -> 103434.25 | AG73: =AD12+AD32+AD52 -> 62196515 | AH73: =AE12+AE32+AE52 -> 1243930.3 | AI73: =AF12+AF32+AF52 -> 473630.83
A74: 46327 | B74: {=INDEX(Fluxo_Caixa_Mensal!$H$90:$S$90, ROW(B74)-ROW($B$64)+1)} -> 100000 | C74: =C73*0.99 -> 12.789241 | D74: =D13+D33+D53 -> 7819.072 | E74: 0.3 | F74: =F13+F33+F53 -> 2345.7216 | G74: 0.6 | H74: =H13+H33+H53 -> 1407.433 | I74: 0.3 | J74: 0 | K74: 0 | L74: =L13+L33+L53 -> 422.22989 | M74: =L74/D74 -> 0.054 | N74: =M13+M33+M53 -> 2284.7491 | O74: =AVERAGE(N13,N33,N53) -> 236.8378 | P74: =AVERAGE(O13,O33,O53) -> 0.02 | Q74: =P13+P33+P53 -> 37.250384 | R74: =Q13+Q33+Q53 -> 2247.4987 | S74: =R53 -> 15 | T74: =AVERAGE(S13,S33,S53) -> 867.96254 | U74: =IFERROR((M13*T13 + M33*T33 + M53*T53)/(M13 + M33 + M53),"0" ) -> 20021.146 | V74: =U13+U33+U53 -> 35959.979 | W74: =V13+V33+V53 -> 36297222 | X74: =W13+W33+W53 -> 725944.45 | Y74: =AVERAGE(X13,X33,X53) -> 14.25 | Z74: =AVERAGE(Y13,Y33,Y53) -> 0.05 | AA74: =IFERROR((M13*Z13 + M33*Z33 + M53*Z53)/(M13 + M33 + M53),"0" ) -> 19020.089 | AB74: =AA13+AA33+AA53 -> 32026.856 | AC74: =AB13+AB33+AB53 -> 34482361 | AD74: =AC13+AC33+AC53 -> 689647.23 | AE74: =((((Q53+Q33)/R74))*R74)*189.9 -> 400423.52 | AF74: =AB74*3.99 -> 127787.16 | AG74: =AD13+AD33+AD53 -> 96678877 | AH74: =AE13+AE33+AE53 -> 1933577.5 | AI74: =AF13+AF33+AF53 -> 573630.83
A75: 46357 | B75: {=INDEX(Fluxo_Caixa_Mensal!$H$90:$S$90, ROW(B75)-ROW($B$64)+1)} -> 100000 | C75: =C74*0.99 -> 12.661349 | D75: =D14+D34+D54 -> 7898.0525 | E75: 0.3 | F75: =F14+F34+F54 -> 2369.4158 | G75: 0.6 | H75: =H14+H34+H54 -> 1421.6495 | I75: 0.3 | J75: 0 | K75: 0 | L75: =L14+L34+L54 -> 426.49484 | M75: =L75/D75 -> 0.054 | N75: =M14+M34+M54 -> 2711.2439 | O75: =AVERAGE(N14,N34,N54) -> 234.46943 | P75: =AVERAGE(O14,O34,O54) -> 0.03 | Q75: =P14+P34+P54 -> 68.542472 | R75: =Q14+Q34+Q54 -> 2642.7014 | S75: =R54 -> 15 | T75: =AVERAGE(S14,S34,S54) -> 880.98198 | U75: =IFERROR((M14*T14 + M34*T34 + M54*T54)/(M14 + M34 + M54),"0" ) -> 20371.702 | V75: =U14+U34+U54 -> 42283.223 | W75: =V14+V34+V54 -> 45675159 | X75: =W14+W34+W54 -> 913503.19 | Y75: =AVERAGE(X14,X34,X54) -> 14.25 | Z75: =AVERAGE(Y14,Y34,Y54) -> 0.05 | AA75: =IFERROR((M14*Z14 + M34*Z34 + M54*Z54)/(M14 + M34 + M54),"0" ) -> 19353.117 | AB75: =AA14+AA34+AA54 -> 37658.496 | AC75: =AB14+AB34+AB54 -> 43391401 | AD75: =AC14+AC34+AC54 -> 867828.03 | AE75: =((((Q54+Q34)/R75))*R75)*189.9 -> 471771.47 | AF75: =AB75*3.99 -> 150257.4 | AG75: =AD14+AD34+AD54 -> 1.4007028e+08 | AH75: =AE14+AE34+AE54 -> 2801405.6 | AI75: =AF14+AF34+AF54 -> 673630.83
A76: 46388 | B76: 100000 | C76: =C75*0.99 -> 12.534736 | D76: =D15+D35+D55 -> 7977.8308 | E76: 0.3 | F76: =F15+F35+F55 -> 2393.3493 | G76: 0.6 | H76: =H15+H35+H55 -> 1436.0096 | I76: 0.3 | J76: 0 | K76: 0 | L76: =L15+L35+L55 -> 430.80287 | M76: =L76/D76 -> 0.054 | N76: =M15+M35+M55 -> 3142.0468 | O76: =AVERAGE(N15,N35,N55) -> 232.12473 | P76: =AVERAGE(O15,O35,O55) -> 0.03 | Q76: =P15+P35+P55 -> 81.337317 | R76: =Q15+Q35+Q55 -> 3060.7095 | S76: =R55 -> 15 | T76: =AVERAGE(S15,S35,S55) -> 894.19671 | U76: =IFERROR((M15*T15 + M35*T35 + M55*T55)/(M15 + M35 + M55),"0" ) -> 20714.731 | V76: =U15+U35+U55 -> 48971.351 | W76: =V15+V35+V55 -> 54647367 | X76: =W15+W35+W55 -> 1092947.3 | Y76: =AVERAGE(X15,X35,X55) -> 14.25 | Z76: =AVERAGE(Y15,Y35,Y55) -> 0.05 | AA76: =IFERROR((M15*Z15 + M35*Z35 + M55*Z55)/(M15 + M35 + M55),"0" ) -> 19678.995 | AB76: =AA15+AA35+AA55 -> 43615.11 | AC76: =AB15+AB35+AB55 -> 51914998 | AD76: =AC15+AC35+AC55 -> 1038300 | AE76: =((((Q55+Q35)/R76))*R76)*189.9 -> 547182.2 | AF76: =AB76*3.99 -> 174024.29 | AG76: =AD15+AD35+AD55 -> 1.9198528e+08 | AH76: =AE15+AE35+AE55 -> 3839705.5 | AI76: =AF15+AF35+AF55 -> 773630.83
A77: 46419 | B77: 100000 | C77: =C76*0.99 -> 12.409388 | D77: =D16+D36+D56 -> 8058.415 | E77: 0.3 | F77: =F16+F36+F56 -> 2417.5245 | G77: 0.6 | H77: =H16+H36+H56 -> 1450.5147 | I77: 0.3 | J77: 0 | K77: 0 | L77: =L16+L36+L56 -> 435.15441 | M77: =L77/D77 -> 0.054 | N77: =M16+M36+M56 -> 3577.2012 | O77: =AVERAGE(N16,N36,N56) -> 229.80349 | P77: =AVERAGE(O16,O36,O56) -> 0.06 | Q77: =P16+P36+P56 -> 188.52281 | R77: =Q16+Q36+Q56 -> 3388.6784 | S77: =R56 -> 15 | T77: =AVERAGE(S16,S36,S56) -> 907.60966 | U77: =IFERROR((M16*T16 + M36*T36 + M56*T56)/(M16 + M36 + M56),"0" ) -> 21054.556 | V77: =U16+U36+U56 -> 54218.854 | W77: =V16+V36+V56 -> 64355893 | X77: =W16+W36+W56 -> 1287117.9 | Y77: =AVERAGE(X16,X36,X56) -> 14.25 | Z77: =AVERAGE(Y16,Y36,Y56) -> 0.05 | AA77: =IFERROR((M16*Z16 + M36*Z36 + M56*Z56)/(M16 + M36 + M56),"0" ) -> 20001.829 | AB77: =AA16+AA36+AA56 -> 48288.667 | AC77: =AB16+AB36+AB56 -> 61138099 | AD77: =AC16+AC36+AC56 -> 1222762 | AE77: =((((Q56+Q36)/R77))*R77)*189.9 -> 606503.62 | AF77: =AB77*3.99 -> 192671.78 | AG77: =AD16+AD36+AD56 -> 2.5312337e+08 | AH77: =AE16+AE36+AE56 -> 5062467.5 | AI77: =AF16+AF36+AF56 -> 873630.83
B78: =SUBTOTAL(109,B64:B77) -> 873630.83 | C78: =SUBTOTAL(101,C64:C77) -> 13.105041 | D78: =SUBTOTAL(109,D64:D77) -> 69422.393 | E78: =AVERAGE(E64:E77) -> 0.26142857 | G78: =AVERAGE(G64:G77) -> 0.53571429 | I78: =AVERAGE(I64:I77) -> 0.32857143 | L78: =SUBTOTAL(109,L64:L77) -> 3577.2012 | M78: =AVERAGE(M64:M77) -> 0.043714286 | N78: =AVERAGE(N64:N77) -> 1230.2021 | O78: =SUBTOTAL(101,O64:O77) -> 253.79248 | P78: =AVERAGE(P64:P77) -> 0.025714286 | Q78: =SUBTOTAL(109,Q64:Q77) -> 465.67173 | R78: =R77 -> 3388.6784 | U78: =SUBTOTAL(101,U64:U77) -> 16580.485 | W78: =SUBTOTAL(109,W64:W77) -> 2.6644566e+08 | X78: =SUBTOTAL(109,X64:X77) -> 5328913.2 | Z78: =AVERAGE(Z64:Z77) -> 0.11785714 | AA78: =AVERAGE(AA64:AA77) -> 15263.859 | AC78: =SUBTOTAL(109,AC64:AC77) -> 2.5312337e+08 | AD78: =SUBTOTAL(109,AD64:AD77) -> 5062467.5 | AE78: =SUBTOTAL(109,AE64:AE77) -> 2949198.8 | AF78: =SUBTOTAL(109,AF64:AF77) -> 948372.77 | AG78: =SUBTOTAL(109,AG64:AG77) -> 8.1145195e+08
C80: % sob TAM Nacional | D80: =D78/130000 -> 0.53401841 | Q80: % sob TAM Nacional | R80: =R78/130000 -> 0.026066757
T85: =R66*62% -> 47.854267
T86: =T85*189.9 -> 9087.5254
D88: 2578 | E88: =D88*F88 -> 515.6 | F88: 0.2
D89: 2578 | E89: =D89*F89 -> 1031.2 | F89: 0.4 | G89: =57/1429 -> 0.039888034
D90: 2578 | E90: =D90*F90 -> 1031.2 | F90: 0.4
Z91: =Q55+Q35 -> 2881.4229
Z92: =Q15 -> 179.28658
R100: =31/(19+31) -> 0.62

Sheet Proj. Vendas MUVX Digital
A1: Mês | B1: Investimento no Mês (Growth ** 40%** | C1: CPL (cadastro) | D1: Novos Cadastros no App Personal | E1: Tx. % Ativação Personais (Conversão) | F1: Novos Personais Ativados | G1: Personais Totais | H1: CAC (ativação)2 | I1: Tx. % Churn | J1: Qtde. Churn no Mês | K1: Personais Ativos Mês | L1: Média Alunos Estimada Total Personal | M1: Ticket Médio Aluno Personal | N1: Média Faturamento Estimada Personal | O1: Total Usuários Estimado | P1: Faturamento Estimado | Q1: Receita MUVX (7,5%) Estimada | R1: Receita MUVX (Tarifa Alunos R$2,99) Estimada | S1: Média Real Alunos Ativos Personal | T1: Tx. % Real Alunos não ativados | U1: Média Real por Personal | V1: Total Real Usuários | W1: Media Real de Infra AWS | X1: Media Real de Infra AWS (usuário) | Y1: Faturamento Real Bruto | Z1: Receita MUVX (7,5%) | AA1: Receita MUVX (Tarifa Alunos R$3,99) | AB1: Faturamento Real Acumulado | AC1: Receita MUVX Acumulada | AD1: Investimento Acumulado | AE1: ROI | AF1: ROI Acumulado
A2: 45962 | B2: 0 | C2: 25 | D2: =Table13[[#This Row],[Investimento no Mês (Growth ** 40%**]]/Table13[[#This Row],[CPL (cadastro)]] -> 0 | E2: 0 | F2: =Table13[[#This Row],[Novos Cadastros no App Personal]]*Table13[[#This Row],[Tx. % Ativação Personais (Conversão)]] -> 0 | G2: =Table13[[#This Row],[Novos Personais Ativados]] -> 0 | H2: =IFERROR(Table13[[#This Row],[Investimento no Mês (Growth ** 40%**]]/Table13[[#This Row],[Novos Personais Ativados]],0) -> 0 | I2: 0 | J2: =Table13[[#This Row],[Personais Totais]]*Table13[[#This Row],[Tx. % Churn]] -> 0 | K2: =Table13[[#This Row],[Personais Totais]]-Table13[[#This Row],[Qtde. Churn no Mês]] -> 0 | M2: - | N2: - | O2: =Table13[[#This Row],[Personais Ativos Mês]]+(Table13[[#This Row],[Personais Ativos Mês]]*Table13[[#This Row],[Média Alunos Estimada Total Personal]]) -> 0 | P2: - | Q2: - | R2: =Table13[[#This Row],[Total Usuários Estimado]]*2.99 -> 0 | S2: =Table13[[#This Row],[Média Alunos Estimada Total Personal]]-(Table13[[#This Row],[Tx. % Real Alunos não ativados]]*Table13[[#This Row],[Média Alunos Estimada Total Personal]]) -> 0 | T2: 0.54 | U2: =Y2/K2 -> #DIV/0! | V2: =Table13[[#This Row],[Média Real Alunos Ativos Personal]]*Table13[[#This Row],[Personais Ativos Mês]] -> 0 | W2: 390.06 | Y2: 0 | Z2: 0 | AA2: =Table13[[#This Row],[Total Real Usuários ]]*3.99 -> 0 | AB2: =Table13[[#This Row],[Faturamento Real Bruto]] -> 0 | AC2: 0 | AD2: =Table13[[#This Row],[Investimento no Mês (Growth ** 40%**]] -> 0 | AE2: 0 | AF2: 0
A3: 45992 | B3: 0 | C3: 45 | D3: =Table13[[#This Row],[Investimento no Mês (Growth ** 40%**]]/Table13[[#This Row],[CPL (cadastro)]] -> 0 | E3: 0 | F3: =Table13[[#This Row],[Novos Cadastros no App Personal]]*Table13[[#This Row],[Tx. % Ativação Personais (Conversão)]] -> 0 | G3: =Table13[[#This Row],[Novos Personais Ativados]]+G2 -> 0 | H3: =IFERROR(Table13[[#This Row],[Investimento no Mês (Growth ** 40%**]]/Table13[[#This Row],[Novos Personais Ativados]],0) -> 0 | I3: 0 | J3: =Table13[[#This Row],[Personais Totais]]*Table13[[#This Row],[Tx. % Churn]] -> 0 | K3: =Table13[[#This Row],[Personais Totais]]-Table13[[#This Row],[Qtde. Churn no Mês]] -> 0 | M3: 0 | N3: =Table13[[#This Row],[Média Alunos Estimada Total Personal]]*Table13[[#This Row],[Ticket Médio Aluno Personal]] -> 0 | O3: =Table13[[#This Row],[Personais Ativos Mês]]+(Table13[[#This Row],[Personais Ativos Mês]]*Table13[[#This Row],[Média Alunos Estimada Total Personal]]) -> 0 | P3: =Table13[[#This Row],[Média Faturamento Estimada Personal]]*K2 -> 0 | Q3: =Table13[[#This Row],[Faturamento Estimado]]*7.5% -> 0 | R3: =Table13[[#This Row],[Total Usuários Estimado]]*2.99 -> 0 | S3: =Table13[[#This Row],[Média Alunos Estimada Total Personal]]-(Table13[[#This Row],[Tx. % Real Alunos não ativados]]*Table13[[#This Row],[Média Alunos Estimada Total Personal]]) -> 0 | T3: 0.54 | U3: =Table13[[#This Row],[Ticket Médio Aluno Personal]]*Table13[[#This Row],[Média Real Alunos Ativos Personal]] -> 0 | V3: =Table13[[#This Row],[Média Real Alunos Ativos Personal]]*Table13[[#This Row],[Personais Ativos Mês]] -> 0 | W3: 499.27 | Y3: =Table13[[#This Row],[Média Real por Personal]]*K2 -> 0 | Z3: =Table13[[#This Row],[Faturamento Real Bruto]]*5% -> 0 | AA3: =Table13[[#This Row],[Total Real Usuários ]]*3.99 -> 0 | AB3: =Table13[[#This Row],[Faturamento Real Bruto]]+Y2 -> 0 | AC3: =Table13[[#This Row],[Receita MUVX (7,5%)]]+Z2 -> 0 | AD3: =Table13[[#This Row],[Investimento no Mês (Growth ** 40%**]]+AD2 -> 0 | AE3: =Table13[[#This Row],[Receita MUVX Acumulada]]/Table13[[#This Row],[Investimento Acumulado]] -> #DIV/0! | AF3: =Table13[[#This Row],[ROI]]+AF2 -> #DIV/0!
A4: 46023 | B4: =B62*0.4 -> 0 | C4: 12 | D4: =Table13[[#This Row],[Investimento no Mês (Growth ** 40%**]]/Table13[[#This Row],[CPL (cadastro)]] -> 0 | E4: 0 | F4: =Table13[[#This Row],[Novos Cadastros no App Personal]]*Table13[[#This Row],[Tx. % Ativação Personais (Conversão)]] -> 0 | G4: =Table13[[#This Row],[Novos Personais Ativados]]+G3 -> 0 | H4: =IFERROR(Table13[[#This Row],[Investimento no Mês (Growth ** 40%**]]/Table13[[#This Row],[Novos Personais Ativados]],0) -> 0 | I4: 0 | J4: =Table13[[#This Row],[Personais Totais]]*Table13[[#This Row],[Tx. % Churn]] -> 0 | K4: =Table13[[#This Row],[Personais Totais]]-Table13[[#This Row],[Qtde. Churn no Mês]] -> 0 | L4: 30 | M4: 60 | N4: =Table13[[#This Row],[Média Alunos Estimada Total Personal]]*Table13[[#This Row],[Ticket Médio Aluno Personal]] -> 1800 | O4: 0 | P4: =Table13[[#This Row],[Média Faturamento Estimada Personal]]*K3 -> 0 | Q4: =Table13[[#This Row],[Faturamento Estimado]]*7.5% -> 0 | R4: =Table13[[#This Row],[Total Usuários Estimado]]*2.99 -> 0 | S4: =Table13[[#This Row],[Média Alunos Estimada Total Personal]]-(Table13[[#This Row],[Tx. % Real Alunos não ativados]]*Table13[[#This Row],[Média Alunos Estimada Total Personal]]) -> 13.8 | T4: 0.54 | U4: =Table13[[#This Row],[Ticket Médio Aluno Personal]]*Table13[[#This Row],[Média Real Alunos Ativos Personal]] -> 828 | V4: 0 | W4: 874.55 | Y4: =Table13[[#This Row],[Média Real por Personal]]*K3 -> 0 | Z4: =Table13[[#This Row],[Faturamento Real Bruto]]*5% -> 0 | AA4: =Table13[[#This Row],[Total Real Usuários ]]*3.99 -> 0 | AB4: =AB3+Table13[[#This Row],[Faturamento Real Bruto]] -> 0 | AC4: =AC3+Table13[[#This Row],[Receita MUVX (7,5%)]] -> 0 | AD4: =Table13[[#This Row],[Investimento no Mês (Growth ** 40%**]]+AD3 -> 0 | AE4: =Table13[[#This Row],[Receita MUVX Acumulada]]/Table13[[#This Row],[Investimento Acumulado]] -> #DIV/0! | AF4: =Table13[[#This Row],[ROI]]+AF3 -> #DIV/0!
A5: 46054 | B5: =B63*0.4 -> 0 | C5: =C4*0.98 -> 11.76 | D5: =Table13[[#This Row],[Investimento no Mês (Growth ** 40%**]]/Table13[[#This Row],[CPL (cadastro)]] -> 0 | E5: 0.06 | F5: =Table13[[#This Row],[Novos Cadastros no App Personal]]*Table13[[#This Row],[Tx. % Ativação Personais (Conversão)]] -> 0 | G5: =Table13[[#This Row],[Novos Personais Ativados]]+G4 -> 0 | H5: =IFERROR(Table13[[#This Row],[Investimento no Mês (Growth ** 40%**]]/Table13[[#This Row],[Novos Personais Ativados]],0) -> 0 | I5: 0.04 | J5: =Table13[[#This Row],[Personais Totais]]*Table13[[#This Row],[Tx. % Churn]] -> 0 | K5: =Table13[[#This Row],[Personais Totais]]-Table13[[#This Row],[Qtde. Churn no Mês]] -> 0 | L5: 30 | M5: =M4*1.015 -> 60.9 | N5: =N4*1.015 -> 1827 | O5: 0 | P5: =Table13[[#This Row],[Média Faturamento Estimada Personal]]*K4 -> 0 | Q5: =Table13[[#This Row],[Faturamento Estimado]]*7.5% -> 0 | R5: =Table13[[#This Row],[Total Usuários Estimado]]*2.99 -> 0 | S5: =Table13[[#This Row],[Média Alunos Estimada Total Personal]]-(Table13[[#This Row],[Tx. % Real Alunos não ativados]]*Table13[[#This Row],[Média Alunos Estimada Total Personal]]) -> 18 | T5: 0.4 | U5: =Table13[[#This Row],[Ticket Médio Aluno Personal]]*Table13[[#This Row],[Média Real Alunos Ativos Personal]] -> 1096.2 | V5: =Table13[[#This Row],[Média Real Alunos Ativos Personal]]*Table13[[#This Row],[Personais Ativos Mês]] -> 0 | W5: 1030.71 | Y5: =Table13[[#This Row],[Média Real por Personal]]*K4 -> 0 | Z5: =Table13[[#This Row],[Faturamento Real Bruto]]*5% -> 0 | AA5: =Table13[[#This Row],[Total Real Usuários ]]*3.99 -> 0 | AB5: =AB4+Table13[[#This Row],[Faturamento Real Bruto]] -> 0 | AC5: =AC4+Table13[[#This Row],[Receita MUVX (7,5%)]] -> 0 | AD5: =Table13[[#This Row],[Investimento no Mês (Growth ** 40%**]]+AD4 -> 0 | AE5: =Table13[[#This Row],[Receita MUVX Acumulada]]/Table13[[#This Row],[Investimento Acumulado]] -> #DIV/0! | AF5: =Table13[[#This Row],[ROI]]+AF4 -> #DIV/0!
A6: 46082 | B6: =B64*0.4 -> 4000 | C6: =C5*0.98 -> 11.5248 | D6: =Table13[[#This Row],[Investimento no Mês (Growth ** 40%**]]/Table13[[#This Row],[CPL (cadastro)]] -> 347.07761 | E6: 0.03 | F6: =Table13[[#This Row],[Novos Cadastros no App Personal]]*Table13[[#This Row],[Tx. % Ativação Personais (Conversão)]] -> 10.412328 | G6: =Table13[[#This Row],[Novos Personais Ativados]]+G5 -> 10.412328 | H6: =IFERROR(Table13[[#This Row],[Investimento no Mês (Growth ** 40%**]]/Table13[[#This Row],[Novos Personais Ativados]],0) -> 384.16 | I6: 0.06 | J6: =Table13[[#This Row],[Personais Totais]]*Table13[[#This Row],[Tx. % Churn]] -> 0.62473969 | K6: =Table13[[#This Row],[Personais Totais]]-Table13[[#This Row],[Qtde. Churn no Mês]] -> 9.7875885 | L6: 30 | M6: =M5*1.015 -> 61.8135 | N6: =N5*1.015 -> 1854.405 | O6: =Table13[[#This Row],[Personais Ativos Mês]]+(Table13[[#This Row],[Personais Ativos Mês]]*Table13[[#This Row],[Média Alunos Estimada Total Personal]]) -> 303.41524 | P6: =Table13[[#This Row],[Média Faturamento Estimada Personal]]*K5 -> 0 | Q6: =Table13[[#This Row],[Faturamento Estimado]]*7.5% -> 0 | R6: =Table13[[#This Row],[Total Usuários Estimado]]*2.99 -> 907.21158 | S6: =Table13[[#This Row],[Média Alunos Estimada Total Personal]]-(Table13[[#This Row],[Tx. % Real Alunos não ativados]]*Table13[[#This Row],[Média Alunos Estimada Total Personal]]) -> 21 | T6: 0.3 | U6: =Table13[[#This Row],[Ticket Médio Aluno Personal]]*Table13[[#This Row],[Média Real Alunos Ativos Personal]] -> 1298.0835 | V6: =Table13[[#This Row],[Média Real Alunos Ativos Personal]]*Table13[[#This Row],[Personais Ativos Mês]] -> 205.53936 | W6: 1177.87 | Y6: =Table13[[#This Row],[Média Real por Personal]]*K5 -> 0 | Z6: =Table13[[#This Row],[Faturamento Real Bruto]]*5% -> 0 | AA6: =Table13[[#This Row],[Total Real Usuários ]]*3.99 -> 820.10204 | AB6: =AB5+Table13[[#This Row],[Faturamento Real Bruto]] -> 0 | AC6: =AC5+Table13[[#This Row],[Receita MUVX (7,5%)]] -> 0 | AD6: =Table13[[#This Row],[Investimento no Mês (Growth ** 40%**]]+AD5 -> 4000 | AE6: =Table13[[#This Row],[Receita MUVX Acumulada]]/Table13[[#This Row],[Investimento Acumulado]] -> 0 | AF6: =Table13[[#This Row],[ROI]]+AF5 -> #DIV/0!
A7: 46113 | B7: =B65*0.4 -> 4000 | C7: =C6*0.98 -> 11.294304 | D7: =Table13[[#This Row],[Investimento no Mês (Growth ** 40%**]]/Table13[[#This Row],[CPL (cadastro)]] -> 354.16082 | E7: 0.04 | F7: =Table13[[#This Row],[Novos Cadastros no App Personal]]*Table13[[#This Row],[Tx. % Ativação Personais (Conversão)]] -> 14.166433 | G7: =Table13[[#This Row],[Novos Personais Ativados]]+G6 -> 24.578761 | H7: =IFERROR(Table13[[#This Row],[Investimento no Mês (Growth ** 40%**]]/Table13[[#This Row],[Novos Personais Ativados]],0) -> 282.3576 | I7: 0.04 | J7: =Table13[[#This Row],[Personais Totais]]*Table13[[#This Row],[Tx. % Churn]] -> 0.98315044 | K7: =Table13[[#This Row],[Personais Totais]]-Table13[[#This Row],[Qtde. Churn no Mês]] -> 23.595611 | L7: 30 | M7: =M6*1.015 -> 62.740702 | N7: =N6*1.015 -> 1882.2211 | O7: =Table13[[#This Row],[Personais Ativos Mês]]+(Table13[[#This Row],[Personais Ativos Mês]]*Table13[[#This Row],[Média Alunos Estimada Total Personal]]) -> 731.46393 | P7: =Table13[[#This Row],[Média Faturamento Estimada Personal]]*K6 -> 18422.405 | Q7: =Table13[[#This Row],[Faturamento Estimado]]*7.5% -> 1381.6804 | R7: =Table13[[#This Row],[Total Usuários Estimado]]*2.99 -> 2187.0772 | S7: =Table13[[#This Row],[Média Alunos Estimada Total Personal]]-(Table13[[#This Row],[Tx. % Real Alunos não ativados]]*Table13[[#This Row],[Média Alunos Estimada Total Personal]]) -> 27 | T7: 0.1 | U7: =Table13[[#This Row],[Ticket Médio Aluno Personal]]*Table13[[#This Row],[Média Real Alunos Ativos Personal]] -> 1693.999 | V7: =Table13[[#This Row],[Média Real Alunos Ativos Personal]]*Table13[[#This Row],[Personais Ativos Mês]] -> 637.08149 | W7: 1404.73 | Y7: =Table13[[#This Row],[Média Real por Personal]]*K6 -> 16580.165 | Z7: =Table13[[#This Row],[Faturamento Real Bruto]]*5% -> 829.00824 | AA7: =Table13[[#This Row],[Total Real Usuários ]]*3.99 -> 2541.9551 | AB7: =AB6+Table13[[#This Row],[Faturamento Real Bruto]] -> 16580.165 | AC7: =AC6+Table13[[#This Row],[Receita MUVX (7,5%)]] -> 829.00824 | AD7: =Table13[[#This Row],[Investimento no Mês (Growth ** 40%**]]+AD6 -> 8000 | AE7: =Table13[[#This Row],[Receita MUVX Acumulada]]/Table13[[#This Row],[Investimento Acumulado]] -> 0.10362603 | AF7: =Table13[[#This Row],[ROI]]+AF6 -> #DIV/0!
A8: 46143 | B8: =B66*0.4 -> 12000 | C8: =C7*0.98 -> 11.068418 | D8: =Table13[[#This Row],[Investimento no Mês (Growth ** 40%**]]/Table13[[#This Row],[CPL (cadastro)]] -> 1084.1658 | E8: 0.07 | F8: =Table13[[#This Row],[Novos Cadastros no App Personal]]*Table13[[#This Row],[Tx. % Ativação Personais (Conversão)]] -> 75.891605 | G8: =Table13[[#This Row],[Novos Personais Ativados]]+G7 -> 100.47037 | H8: =IFERROR(Table13[[#This Row],[Investimento no Mês (Growth ** 40%**]]/Table13[[#This Row],[Novos Personais Ativados]],0) -> 158.12026 | I8: 0.05 | J8: =Table13[[#This Row],[Personais Totais]]*Table13[[#This Row],[Tx. % Churn]] -> 5.0235183 | K8: =Table13[[#This Row],[Personais Totais]]-Table13[[#This Row],[Qtde. Churn no Mês]] -> 95.446848 | L8: 30 | M8: =M7*1.015 -> 63.681813 | N8: =N7*1.015 -> 1910.4544 | O8: =Table13[[#This Row],[Personais Ativos Mês]]+(Table13[[#This Row],[Personais Ativos Mês]]*Table13[[#This Row],[Média Alunos Estimada Total Personal]]) -> 2958.8523 | P8: =Table13[[#This Row],[Média Faturamento Estimada Personal]]*K7 -> 45078.338 | Q8: =Table13[[#This Row],[Faturamento Estimado]]*7.5% -> 3380.8754 | R8: =Table13[[#This Row],[Total Usuários Estimado]]*2.99 -> 8846.9683 | S8: =Table13[[#This Row],[Média Alunos Estimada Total Personal]]-(Table13[[#This Row],[Tx. % Real Alunos não ativados]]*Table13[[#This Row],[Média Alunos Estimada Total Personal]]) -> 27 | T8: 0.1 | U8: =Table13[[#This Row],[Ticket Médio Aluno Personal]]*Table13[[#This Row],[Média Real Alunos Ativos Personal]] -> 1719.409 | V8: =Table13[[#This Row],[Média Real Alunos Ativos Personal]]*Table13[[#This Row],[Personais Ativos Mês]] -> 2577.0649 | W8: 1617.95 | Y8: =Table13[[#This Row],[Média Real por Personal]]*K7 -> 40570.504 | Z8: =Table13[[#This Row],[Faturamento Real Bruto]]*5% -> 2028.5252 | AA8: =Table13[[#This Row],[Total Real Usuários ]]*3.99 -> 10282.489 | AB8: =AB7+Table13[[#This Row],[Faturamento Real Bruto]] -> 57150.669 | AC8: =AC7+Table13[[#This Row],[Receita MUVX (7,5%)]] -> 2857.5335 | AD8: =Table13[[#This Row],[Investimento no Mês (Growth ** 40%**]]+AD7 -> 20000 | AE8: =Table13[[#This Row],[Receita MUVX Acumulada]]/Table13[[#This Row],[Investimento Acumulado]] -> 0.14287667 | AF8: =Table13[[#This Row],[ROI]]+AF7 -> #DIV/0!
A9: 46174 | B9: =B67*0.4 -> 16000 | C9: =C8*0.98 -> 10.84705 | D9: =Table13[[#This Row],[Investimento no Mês (Growth ** 40%**]]/Table13[[#This Row],[CPL (cadastro)]] -> 1475.0555 | E9: 0.05 | F9: =Table13[[#This Row],[Novos Cadastros no App Personal]]*Table13[[#This Row],[Tx. % Ativação Personais (Conversão)]] -> 73.752774 | G9: =Table13[[#This Row],[Novos Personais Ativados]]+G8 -> 174.22314 | H9: =IFERROR(Table13[[#This Row],[Investimento no Mês (Growth ** 40%**]]/Table13[[#This Row],[Novos Personais Ativados]],0) -> 216.94099 | I9: 0.05 | J9: =Table13[[#This Row],[Personais Totais]]*Table13[[#This Row],[Tx. % Churn]] -> 8.711157 | K9: =Table13[[#This Row],[Personais Totais]]-Table13[[#This Row],[Qtde. Churn no Mês]] -> 165.51198 | L9: 30 | M9: =M8*1.015 -> 64.63704 | N9: =N8*1.015 -> 1939.1112 | O9: =Table13[[#This Row],[Personais Ativos Mês]]+(Table13[[#This Row],[Personais Ativos Mês]]*Table13[[#This Row],[Média Alunos Estimada Total Personal]]) -> 5130.8715 | P9: =Table13[[#This Row],[Média Faturamento Estimada Personal]]*K8 -> 185082.05 | Q9: =Table13[[#This Row],[Faturamento Estimado]]*7.5% -> 13881.154 | R9: =Table13[[#This Row],[Total Usuários Estimado]]*2.99 -> 15341.306 | S9: =Table13[[#This Row],[Média Alunos Estimada Total Personal]]-(Table13[[#This Row],[Tx. % Real Alunos não ativados]]*Table13[[#This Row],[Média Alunos Estimada Total Personal]]) -> 27 | T9: 0.1 | U9: =Table13[[#This Row],[Ticket Médio Aluno Personal]]*Table13[[#This Row],[Média Real Alunos Ativos Personal]] -> 1745.2001 | V9: =Table13[[#This Row],[Média Real Alunos Ativos Personal]]*Table13[[#This Row],[Personais Ativos Mês]] -> 4468.8236 | W9: 1904.26 | Y9: =Table13[[#This Row],[Média Real por Personal]]*K8 -> 166573.85 | Z9: =Table13[[#This Row],[Faturamento Real Bruto]]*5% -> 8328.6923 | AA9: =Table13[[#This Row],[Total Real Usuários ]]*3.99 -> 17830.606 | AB9: =AB8+Table13[[#This Row],[Faturamento Real Bruto]] -> 223724.52 | AC9: =AC8+Table13[[#This Row],[Receita MUVX (7,5%)]] -> 11186.226 | AD9: =Table13[[#This Row],[Investimento no Mês (Growth ** 40%**]]+AD8 -> 36000 | AE9: =Table13[[#This Row],[Receita MUVX Acumulada]]/Table13[[#This Row],[Investimento Acumulado]] -> 0.31072849 | AF9: =Table13[[#This Row],[ROI]]+AF8 -> #DIV/0!
A10: 46204 | B10: =B68*0.4 -> 69920 | C10: =C9*0.98 -> 10.630109 | D10: =Table13[[#This Row],[Investimento no Mês (Growth ** 40%**]]/Table13[[#This Row],[CPL (cadastro)]] -> 6577.5434 | E10: 0.06 | F10: =Table13[[#This Row],[Novos Cadastros no App Personal]]*Table13[[#This Row],[Tx. % Ativação Personais (Conversão)]] -> 394.6526 | G10: =Table13[[#This Row],[Novos Personais Ativados]]+G9 -> 568.87574 | H10: =IFERROR(Table13[[#This Row],[Investimento no Mês (Growth ** 40%**]]/Table13[[#This Row],[Novos Personais Ativados]],0) -> 177.16848 | I10: 0.02 | J10: =Table13[[#This Row],[Personais Totais]]*Table13[[#This Row],[Tx. % Churn]] -> 11.377515 | K10: =Table13[[#This Row],[Personais Totais]]-Table13[[#This Row],[Qtde. Churn no Mês]] -> 557.49823 | L10: 30 | M10: =M9*1.015 -> 65.606596 | N10: =N9*1.015 -> 1968.1979 | O10: =Table13[[#This Row],[Personais Ativos Mês]]+(Table13[[#This Row],[Personais Ativos Mês]]*Table13[[#This Row],[Média Alunos Estimada Total Personal]]) -> 17282.445 | P10: =Table13[[#This Row],[Média Faturamento Estimada Personal]]*K9 -> 325760.33 | Q10: =Table13[[#This Row],[Faturamento Estimado]]*7.5% -> 24432.025 | R10: =Table13[[#This Row],[Total Usuários Estimado]]*2.99 -> 51674.511 | S10: =Table13[[#This Row],[Média Alunos Estimada Total Personal]]-(Table13[[#This Row],[Tx. % Real Alunos não ativados]]*Table13[[#This Row],[Média Alunos Estimada Total Personal]]) -> 27 | T10: 0.1 | U10: =Table13[[#This Row],[Ticket Médio Aluno Personal]]*Table13[[#This Row],[Média Real Alunos Ativos Personal]] -> 1771.3781 | V10: =Table13[[#This Row],[Média Real Alunos Ativos Personal]]*Table13[[#This Row],[Personais Ativos Mês]] -> 15052.452 | W10: 2334.79 | Y10: =Table13[[#This Row],[Média Real por Personal]]*K9 -> 293184.3 | Z10: =Table13[[#This Row],[Faturamento Real Bruto]]*5% -> 14659.215 | AA10: =Table13[[#This Row],[Total Real Usuários ]]*3.99 -> 60059.284 | AB10: =AB9+Table13[[#This Row],[Faturamento Real Bruto]] -> 516908.82 | AC10: =AC9+Table13[[#This Row],[Receita MUVX (7,5%)]] -> 25845.441 | AD10: =Table13[[#This Row],[Investimento no Mês (Growth ** 40%**]]+AD9 -> 105920 | AE10: =Table13[[#This Row],[Receita MUVX Acumulada]]/Table13[[#This Row],[Investimento Acumulado]] -> 0.24400907 | AF10: =Table13[[#This Row],[ROI]]+AF9 -> #DIV/0!
A11: 46235 | B11: =B69*0.4 -> 80408 | C11: =C10*0.98 -> 10.417506 | D11: =Table13[[#This Row],[Investimento no Mês (Growth ** 40%**]]/Table13[[#This Row],[CPL (cadastro)]] -> 7718.5458 | E11: 0.08 | F11: =Table13[[#This Row],[Novos Cadastros no App Personal]]*Table13[[#This Row],[Tx. % Ativação Personais (Conversão)]] -> 617.48366 | G11: =Table13[[#This Row],[Novos Personais Ativados]]+G10 -> 1186.3594 | H11: =IFERROR(Table13[[#This Row],[Investimento no Mês (Growth ** 40%**]]/Table13[[#This Row],[Novos Personais Ativados]],0) -> 130.21883 | I11: 0.03 | J11: =Table13[[#This Row],[Personais Totais]]*Table13[[#This Row],[Tx. % Churn]] -> 35.590782 | K11: =Table13[[#This Row],[Personais Totais]]-Table13[[#This Row],[Qtde. Churn no Mês]] -> 1150.7686 | L11: 30 | M11: =M10*1.015 -> 66.590695 | N11: =N10*1.015 -> 1997.7208 | O11: =Table13[[#This Row],[Personais Ativos Mês]]+(Table13[[#This Row],[Personais Ativos Mês]]*Table13[[#This Row],[Média Alunos Estimada Total Personal]]) -> 35673.827 | P11: =Table13[[#This Row],[Média Faturamento Estimada Personal]]*K10 -> 1113725.8 | Q11: =Table13[[#This Row],[Faturamento Estimado]]*7.5% -> 83529.437 | R11: =Table13[[#This Row],[Total Usuários Estimado]]*2.99 -> 106664.74 | S11: =Table13[[#This Row],[Média Alunos Estimada Total Personal]]-(Table13[[#This Row],[Tx. % Real Alunos não ativados]]*Table13[[#This Row],[Média Alunos Estimada Total Personal]]) -> 27 | T11: 0.1 | U11: =Table13[[#This Row],[Ticket Médio Aluno Personal]]*Table13[[#This Row],[Média Real Alunos Ativos Personal]] -> 1797.9488 | V11: =Table13[[#This Row],[Média Real Alunos Ativos Personal]]*Table13[[#This Row],[Personais Ativos Mês]] -> 31070.753 | W11: 2731.57 | Y11: =Table13[[#This Row],[Média Real por Personal]]*K10 -> 1002353.2 | Z11: =Table13[[#This Row],[Faturamento Real Bruto]]*5% -> 50117.662 | AA11: =Table13[[#This Row],[Total Real Usuários ]]*3.99 -> 123972.3 | AB11: =AB10+Table13[[#This Row],[Faturamento Real Bruto]] -> 1519262.1 | AC11: =AC10+Table13[[#This Row],[Receita MUVX (7,5%)]] -> 75963.103 | AD11: =Table13[[#This Row],[Investimento no Mês (Growth ** 40%**]]+AD10 -> 186328 | AE11: =Table13[[#This Row],[Receita MUVX Acumulada]]/Table13[[#This Row],[Investimento Acumulado]] -> 0.40768485 | AF11: =Table13[[#This Row],[ROI]]+AF10 -> #DIV/0!
A12: 46266 | B12: =B70*0.4 -> 92469.2 | C12: =C11*0.98 -> 10.209156 | D12: =Table13[[#This Row],[Investimento no Mês (Growth ** 40%**]]/Table13[[#This Row],[CPL (cadastro)]] -> 9057.4772 | E12: 0.08 | F12: =Table13[[#This Row],[Novos Cadastros no App Personal]]*Table13[[#This Row],[Tx. % Ativação Personais (Conversão)]] -> 724.59817 | G12: =Table13[[#This Row],[Novos Personais Ativados]]+G11 -> 1910.9576 | H12: =IFERROR(Table13[[#This Row],[Investimento no Mês (Growth ** 40%**]]/Table13[[#This Row],[Novos Personais Ativados]],0) -> 127.61445 | I12: 0.02 | J12: =Table13[[#This Row],[Personais Totais]]*Table13[[#This Row],[Tx. % Churn]] -> 38.219152 | K12: =Table13[[#This Row],[Personais Totais]]-Table13[[#This Row],[Qtde. Churn no Mês]] -> 1872.7384 | L12: 30 | M12: =M11*1.015 -> 67.589555 | N12: =N11*1.015 -> 2027.6867 | O12: =Table13[[#This Row],[Personais Ativos Mês]]+(Table13[[#This Row],[Personais Ativos Mês]]*Table13[[#This Row],[Média Alunos Estimada Total Personal]]) -> 58054.891 | P12: =Table13[[#This Row],[Média Faturamento Estimada Personal]]*K11 -> 2333398.2 | Q12: =Table13[[#This Row],[Faturamento Estimado]]*7.5% -> 175004.86 | R12: =Table13[[#This Row],[Total Usuários Estimado]]*2.99 -> 173584.12 | S12: =Table13[[#This Row],[Média Alunos Estimada Total Personal]]-(Table13[[#This Row],[Tx. % Real Alunos não ativados]]*Table13[[#This Row],[Média Alunos Estimada Total Personal]]) -> 27 | T12: 0.1 | U12: =Table13[[#This Row],[Ticket Médio Aluno Personal]]*Table13[[#This Row],[Média Real Alunos Ativos Personal]] -> 1824.918 | V12: =Table13[[#This Row],[Média Real Alunos Ativos Personal]]*Table13[[#This Row],[Personais Ativos Mês]] -> 50563.938 | W12: 3259.22 | Y12: =Table13[[#This Row],[Média Real por Personal]]*K11 -> 2100058.4 | Z12: =Table13[[#This Row],[Faturamento Real Bruto]]*5% -> 105002.92 | AA12: =Table13[[#This Row],[Total Real Usuários ]]*3.99 -> 201750.11 | AB12: =AB11+Table13[[#This Row],[Faturamento Real Bruto]] -> 3619320.4 | AC12: =AC11+Table13[[#This Row],[Receita MUVX (7,5%)]] -> 180966.02 | AD12: =Table13[[#This Row],[Investimento no Mês (Growth ** 40%**]]+AD11 -> 278797.2 | AE12: =Table13[[#This Row],[Receita MUVX Acumulada]]/Table13[[#This Row],[Investimento Acumulado]] -> 0.64909555 | AF12: =Table13[[#This Row],[ROI]]+AF11 -> #DIV/0!
A13: 46296 | B13: =B71*0.4 -> 106339.58 | C13: =C12*0.98 -> 10.004973 | D13: =Table13[[#This Row],[Investimento no Mês (Growth ** 40%**]]/Table13[[#This Row],[CPL (cadastro)]] -> 10628.672 | E13: 0.07 | F13: =Table13[[#This Row],[Novos Cadastros no App Personal]]*Table13[[#This Row],[Tx. % Ativação Personais (Conversão)]] -> 744.00705 | G13: =Table13[[#This Row],[Novos Personais Ativados]]+G12 -> 2654.9646 | H13: =IFERROR(Table13[[#This Row],[Investimento no Mês (Growth ** 40%**]]/Table13[[#This Row],[Novos Personais Ativados]],0) -> 142.92819 | I13: 0.03 | J13: =Table13[[#This Row],[Personais Totais]]*Table13[[#This Row],[Tx. % Churn]] -> 79.648939 | K13: =Table13[[#This Row],[Personais Totais]]-Table13[[#This Row],[Qtde. Churn no Mês]] -> 2575.3157 | L13: 30 | M13: =M12*1.015 -> 68.603399 | N13: =N12*1.015 -> 2058.102 | O13: =Table13[[#This Row],[Personais Ativos Mês]]+(Table13[[#This Row],[Personais Ativos Mês]]*Table13[[#This Row],[Média Alunos Estimada Total Personal]]) -> 79834.787 | P13: =Table13[[#This Row],[Média Faturamento Estimada Personal]]*K12 -> 3854286.6 | Q13: =Table13[[#This Row],[Faturamento Estimado]]*7.5% -> 289071.5 | R13: =Table13[[#This Row],[Total Usuários Estimado]]*2.99 -> 238706.01 | S13: =Table13[[#This Row],[Média Alunos Estimada Total Personal]]-(Table13[[#This Row],[Tx. % Real Alunos não ativados]]*Table13[[#This Row],[Média Alunos Estimada Total Personal]]) -> 27 | T13: 0.1 | U13: =Table13[[#This Row],[Ticket Médio Aluno Personal]]*Table13[[#This Row],[Média Real Alunos Ativos Personal]] -> 1852.2918 | V13: =Table13[[#This Row],[Média Real Alunos Ativos Personal]]*Table13[[#This Row],[Personais Ativos Mês]] -> 69533.524 | W13: 3862.91 | Y13: =Table13[[#This Row],[Média Real por Personal]]*K12 -> 3468858 | Z13: =Table13[[#This Row],[Faturamento Real Bruto]]*5% -> 173442.9 | AA13: =Table13[[#This Row],[Total Real Usuários ]]*3.99 -> 277438.76 | AB13: =AB12+Table13[[#This Row],[Faturamento Real Bruto]] -> 7088178.4 | AC13: =AC12+Table13[[#This Row],[Receita MUVX (7,5%)]] -> 354408.92 | AD13: =Table13[[#This Row],[Investimento no Mês (Growth ** 40%**]]+AD12 -> 385136.78 | AE13: =Table13[[#This Row],[Receita MUVX Acumulada]]/Table13[[#This Row],[Investimento Acumulado]] -> 0.92021572 | AF13: =Table13[[#This Row],[ROI]]+AF12 -> #DIV/0!
A14: 46327 | B14: =B72*0.4 -> 122290.52 | C14: =C13*0.98 -> 9.8048737 | D14: =Table13[[#This Row],[Investimento no Mês (Growth ** 40%**]]/Table13[[#This Row],[CPL (cadastro)]] -> 12472.421 | E14: 0.1 | F14: =Table13[[#This Row],[Novos Cadastros no App Personal]]*Table13[[#This Row],[Tx. % Ativação Personais (Conversão)]] -> 1247.2421 | G14: =Table13[[#This Row],[Novos Personais Ativados]]+G13 -> 3902.2068 | H14: =IFERROR(Table13[[#This Row],[Investimento no Mês (Growth ** 40%**]]/Table13[[#This Row],[Novos Personais Ativados]],0) -> 98.048737 | I14: 0.03 | J14: =Table13[[#This Row],[Personais Totais]]*Table13[[#This Row],[Tx. % Churn]] -> 117.0662 | K14: =Table13[[#This Row],[Personais Totais]]-Table13[[#This Row],[Qtde. Churn no Mês]] -> 3785.1406 | L14: 30 | M14: =M13*1.015 -> 69.63245 | N14: =N13*1.015 -> 2088.9735 | O14: =Table13[[#This Row],[Personais Ativos Mês]]+(Table13[[#This Row],[Personais Ativos Mês]]*Table13[[#This Row],[Média Alunos Estimada Total Personal]]) -> 117339.36 | P14: =Table13[[#This Row],[Média Faturamento Estimada Personal]]*K13 -> 5379766.2 | Q14: =Table13[[#This Row],[Faturamento Estimado]]*7.5% -> 403482.47 | R14: =Table13[[#This Row],[Total Usuários Estimado]]*2.99 -> 350844.68 | S14: =Table13[[#This Row],[Média Alunos Estimada Total Personal]]-(Table13[[#This Row],[Tx. % Real Alunos não ativados]]*Table13[[#This Row],[Média Alunos Estimada Total Personal]]) -> 27 | T14: 0.1 | U14: =Table13[[#This Row],[Ticket Médio Aluno Personal]]*Table13[[#This Row],[Média Real Alunos Ativos Personal]] -> 1880.0761 | V14: =Table13[[#This Row],[Média Real Alunos Ativos Personal]]*Table13[[#This Row],[Personais Ativos Mês]] -> 102198.8 | W14: 4572.01 | Y14: =Table13[[#This Row],[Média Real por Personal]]*K13 -> 4841789.6 | Z14: =Table13[[#This Row],[Faturamento Real Bruto]]*5% -> 242089.48 | AA14: =Table13[[#This Row],[Total Real Usuários ]]*3.99 -> 407773.19 | AB14: =AB13+Table13[[#This Row],[Faturamento Real Bruto]] -> 11929968 | AC14: =AC13+Table13[[#This Row],[Receita MUVX (7,5%)]] -> 596498.4 | AD14: =Table13[[#This Row],[Investimento no Mês (Growth ** 40%**]]+AD13 -> 507427.3 | AE14: =Table13[[#This Row],[Receita MUVX Acumulada]]/Table13[[#This Row],[Investimento Acumulado]] -> 1.1755347 | AF14: =Table13[[#This Row],[ROI]]+AF13 -> #DIV/0!
